Workbook

Sheet Accueil
B1: HUB QUILL
B2: Suivi des formations des agents — Montréal & Lisbonne
B4: EN UN COUP D’ŒIL
B5: Agents actifs | C5: =COUNTIF(Skills!M:M,"Active") -> 147
B6: Formations en cours | C6: =SUM(Pipeline!K400:K4395) -> 19
B7: Agents en arrêt (maladie) | C7: =COUNTIF(Skills!M:M,"Maladie") -> 3
B9: COMMENT ÇA MARCHE
B10: • Les cellules dorées sont à remplir ; tout ce qui est bleu est automatique.
B11: • Le Pipeline et le Tableau de bord se mettent à jour tout seuls.
B12: • Marquez une formation « Terminé » dans son onglet : elle quitte le Pipeline.
B14: QUE VOULEZ-VOUS FAIRE ?
B15: Astuce : Ctrl + clic (Cmd + clic sur Mac) sur un lien pour ouvrir l’onglet.
B16: =HYPERLINK("#'Pipeline'!A1","→ Voir les formations en cours") -> → Voir les formations en cours
B17: =HYPERLINK("#'Tableau de Bord'!A1","→ Tableau de bord (indicateurs)") -> → Tableau de bord (indicateurs)
B18: =HYPERLINK("#'Skills'!A1","→ Compétences et agents") -> → Compétences et agents
B19: =HYPERLINK("#'Formation Initiale'!A1","→ Formation initiale (B2C / B2B)") -> → Formation initiale (B2C / B2B)
B20: =HYPERLINK("#'Agences & Après-vente'!A1","→ Nouvelle compétence — Agences & Après-vente") -> → Nouvelle compétence — Agences & Après-vente
B21: =HYPERLINK("#'Evermont'!A1","→ Nouvelle compétence — Evermont") -> → Nouvelle compétence — Evermont
B22: =HYPERLINK("#'Planner'!A1","→ Calendrier des cohortes (Planner)") -> → Calendrier des cohortes (Planner)
B23: =HYPERLINK("#'Mode d''emploi'!A1","→ Mode d’emploi") -> → Mode d’emploi
B25: LÉGENDE
B26: Cellule à remplir (vous écrivez ici)
B27: Cellule automatique — ne pas modifier
B29: Onglets : verts = saisie · bleus = automatiques · gris = références.

Sheet Tableau de Bord
A1: HUB FORMATION QUILL · TABLEAU DE BORD
A2: ="Vue d'ensemble des formations · Mis à jour le "&TEXT(TODAY(),"dddd dd mmmm yyyy") -> Vue d'ensemble des formations · Mis à jour le Friday 19 June 2026
A3: =HYPERLINK("#Accueil!A1","⌂ Accueil") -> ⌂ Accueil
A4: ▌ INDICATEURS CLÉS
A6: AGENTS TOTAUX | C6: AGENTS MONTRÉAL | E6: AGENTS LISBONNE | G6: GROUPES ACTIFS | I6: EN FORMATION
A7: =COUNTIFS(Skills!$A$2:$A$999,"?*",Skills!$M$2:$M$999,"Active") -> 147 | C7: =COUNTIFS(Skills!$D$2:$D$999,"Montréal",Skills!$M$2:$M$999,"Active") -> 112 | E7: =COUNTIFS(Skills!$D$2:$D$999,"Lisbonne",Skills!$M$2:$M$999,"Active") -> 35 | G7: =SUMPRODUCT(IFERROR(1/COUNTIFS('Formation Initiale'!$B$2:$B$999,'Formation Initiale'!$B$2:$B$999,'Formation Initiale'!$R$2:$R$999,"En cours"),0)*('Formation Initiale'!$R$2:$R$999="En cours")) -> 2 | I7: =COUNTIF('Formation Initiale'!$R$2:$R$999,"En cours")+COUNTIF('Agences & Après-vente'!$I$2:$I$1000,"En cours")+COUNTIF(Evermont!$Q$2:$Q$1000,"En cours") -> 18
A9: ▌ COUVERTURE DES COMPÉTENCES
A11: B2C | B11: B2B | C11: Agences B2C | D11: Agences B2B | E11: Après-vente B2C | F11: Après-vente B2B | G11: Evermont
A12: =COUNTIFS(Skills!$E$2:$E$999,"✓",Skills!$M$2:$M$999,"Active") -> 132 | B12: =COUNTIFS(Skills!$F$2:$F$999,"✓",Skills!$M$2:$M$999,"Active") -> 97 | C12: =COUNTIFS(Skills!$G$2:$G$999,"✓",Skills!$M$2:$M$999,"Active") -> 101 | D12: =COUNTIFS(Skills!$H$2:$H$999,"✓",Skills!$M$2:$M$999,"Active") -> 79 | E12: =COUNTIFS(Skills!$I$2:$I$999,"✓",Skills!$M$2:$M$999,"Active") -> 95 | F12: =COUNTIFS(Skills!$J$2:$J$999,"✓",Skills!$M$2:$M$999,"Active") -> 76 | G12: =COUNTIFS(Skills!$K$2:$K$999,"✓",Skills!$M$2:$M$999,"Active") -> 61
A13: ="/ "&COUNTIFS(Skills!$A$2:$A$999,"?*",Skills!$M$2:$M$999,"Active") -> / 147 | B13: ="/ "&COUNTIFS(Skills!$D$2:$D$999,"Montréal",Skills!$M$2:$M$999,"Active") -> / 112 | C13: ="/ "&COUNTIFS(Skills!$A$2:$A$999,"?*",Skills!$M$2:$M$999,"Active") -> / 147 | D13: ="/ "&COUNTIFS(Skills!$D$2:$D$999,"Montréal",Skills!$M$2:$M$999,"Active") -> / 112 | E13: ="/ "&COUNTIFS(Skills!$A$2:$A$999,"?*",Skills!$M$2:$M$999,"Active") -> / 147 | F13: ="/ "&COUNTIFS(Skills!$D$2:$D$999,"Montréal",Skills!$M$2:$M$999,"Active") -> / 112 | G13: ="/ "&COUNTIFS(Skills!$A$2:$A$999,"?*",Skills!$M$2:$M$999,"Active") -> / 147
A15: ▌ STATUT DES FORMATIONS (Cumul: B2C/B2B + Agences/Après-vente + Evermont)
A17: TERMINÉES | C17: EN COURS | E17: À VENIR | G17: PROG. MOYENNE | I17: % AGENTS PRÊTS
A18: =COUNTIF('Formation Initiale'!$R$2:$R$999,"Terminé")+COUNTIF('Agences & Après-vente'!$I$2:$I$1000,"DONE")+COUNTIF(Evermont!$Q$2:$Q$1000,"Terminé") -> 261 | C18: =COUNTIF('Formation Initiale'!$R$2:$R$999,"En cours")+COUNTIF('Agences & Après-vente'!$I$2:$I$1000,"En cours")+COUNTIF(Evermont!$Q$2:$Q$1000,"En cours") -> 18 | E18: =COUNTIF('Formation Initiale'!$R$2:$R$999,"À venir")+COUNTIF('Agences & Après-vente'!$I$2:$I$1000,"À venir")+COUNTIF(Evermont!$Q$2:$Q$1000,"À venir") -> 1 | G18: =IFERROR(AVERAGEIFS('Formation Initiale'!$M$2:$M$999,'Formation Initiale'!$R$2:$R$999,"En cours"),0) -> 0.166 | I18: =IFERROR(COUNTIF('Formation Initiale'!$W$2:$W$999,"Y")/COUNTIF(Skills!$A$2:$A$999,"?*"),0) -> 0.37853107
A20: ▌ RÉPARTITION PAR PRIORITÉ (Formations en cours)
A22: P1 — CRITIQUE (retard ≥12%) | C22: P2 — À SURVEILLER (retard ≥6%) | E22: P3 — SUR LA VOIE (retard <6%) | G22: NON ÉVALUÉS
A23: =COUNTIF('Formation Initiale'!$P$2:$P$999,"P1") -> 20 | C23: =COUNTIF('Formation Initiale'!$P$2:$P$999,"P2") -> 7 | E23: =COUNTIF('Formation Initiale'!$P$2:$P$999,"P3") -> 70 | G23: =SUMPRODUCT(('Formation Initiale'!$R$2:$R$999="En cours")*('Formation Initiale'!$P$2:$P$999="")) -> 0
A25: ▌ RÉPARTITION PAR SITE
A27: Site | B27: Total Agents | C27: En Formation | D27: B2C | E27: B2B | F27: Agences B2C | G27: Agences B2B | H27: Après-vente B2C | I27: Après-vente B2B | J27: Evermont | K27: % Prêts
A28: 🇨🇦 Montréal | B28: =COUNTIFS(Skills!$D$2:$D$999,"Montréal",Skills!$M$2:$M$999,"Active") -> 112 | C28: =COUNTIFS('Formation Initiale'!$R$2:$R$999,"En cours",'Formation Initiale'!$F$2:$F$999,"Montréal") -> 15 | D28: =COUNTIFS(Skills!$E$2:$E$999,"✓",Skills!$D$2:$D$999,"Montréal",Skills!$M$2:$M$999,"Active") -> 97 | E28: =COUNTIFS(Skills!$F$2:$F$999,"✓",Skills!$D$2:$D$999,"Montréal",Skills!$M$2:$M$999,"Active") -> 97 | F28: =COUNTIFS(Skills!$G$2:$G$999,"✓",Skills!$D$2:$D$999,"Montréal",Skills!$M$2:$M$999,"Active") -> 79 | G28: =COUNTIFS(Skills!$H$2:$H$999,"✓",Skills!$D$2:$D$999,"Montréal",Skills!$M$2:$M$999,"Active") -> 79 | H28: =COUNTIFS(Skills!$I$2:$I$999,"✓",Skills!$D$2:$D$999,"Montréal",Skills!$M$2:$M$999,"Active") -> 76 | I28: =COUNTIFS(Skills!$J$2:$J$999,"✓",Skills!$D$2:$D$999,"Montréal",Skills!$M$2:$M$999,"Active") -> 76 | J28: =COUNTIFS(Skills!$K$2:$K$999,"✓",Skills!$D$2:$D$999,"Montréal",Skills!$M$2:$M$999,"Active") -> 61 | K28: =IFERROR(COUNTIFS('Formation Initiale'!$W$2:$W$999,"Y",'Formation Initiale'!$F$2:$F$999,"Montréal")/COUNTIFS('Formation Initiale'!$F$2:$F$999,"Montréal"),0) -> 0.45454545
A29: 🇵🇹 Lisbonne | B29: =COUNTIFS(Skills!$D$2:$D$999,"Lisbonne",Skills!$M$2:$M$999,"Active") -> 35 | C29: =COUNTIFS('Formation Initiale'!$R$2:$R$999,"En cours",'Formation Initiale'!$F$2:$F$999,"Lisbonne") -> 0 | D29: =COUNTIFS(Skills!$E$2:$E$999,"✓",Skills!$D$2:$D$999,"Lisbonne",Skills!$M$2:$M$999,"Active") -> 35 | E29: =COUNTIFS(Skills!$F$2:$F$999,"✓",Skills!$D$2:$D$999,"Lisbonne",Skills!$M$2:$M$999,"Active") -> 0 | F29: =COUNTIFS(Skills!$G$2:$G$999,"✓",Skills!$D$2:$D$999,"Lisbonne",Skills!$M$2:$M$999,"Active") -> 22 | G29: =COUNTIFS(Skills!$H$2:$H$999,"✓",Skills!$D$2:$D$999,"Lisbonne",Skills!$M$2:$M$999,"Active") -> 0 | H29: =COUNTIFS(Skills!$I$2:$I$999,"✓",Skills!$D$2:$D$999,"Lisbonne",Skills!$M$2:$M$999,"Active") -> 19 | I29: =COUNTIFS(Skills!$J$2:$J$999,"✓",Skills!$D$2:$D$999,"Lisbonne",Skills!$M$2:$M$999,"Active") -> 0 | J29: =COUNTIFS(Skills!$K$2:$K$999,"✓",Skills!$D$2:$D$999,"Lisbonne",Skills!$M$2:$M$999,"Active") -> 0 | K29: =IFERROR(COUNTIFS('Formation Initiale'!$W$2:$W$999,"Y",'Formation Initiale'!$F$2:$F$999,"Lisbonne")/COUNTIFS('Formation Initiale'!$F$2:$F$999,"Lisbonne"),0) -> 0.88679245
A30: 🌍 TOTAL | B30: =COUNTIFS(Skills!$A$2:$A$999,"?*",Skills!$M$2:$M$999,"Active") -> 147 | C30: =COUNTIF('Formation Initiale'!$R$2:$R$999,"En cours") -> 15 | D30: =COUNTIFS(Skills!$E$2:$E$999,"✓",Skills!$M$2:$M$999,"Active") -> 132 | E30: =COUNTIFS(Skills!$F$2:$F$999,"✓",Skills!$M$2:$M$999,"Active") -> 97 | F30: =COUNTIFS(Skills!$G$2:$G$999,"✓",Skills!$M$2:$M$999,"Active") -> 101 | G30: =COUNTIFS(Skills!$H$2:$H$999,"✓",Skills!$M$2:$M$999,"Active") -> 79 | H30: =COUNTIFS(Skills!$I$2:$I$999,"✓",Skills!$M$2:$M$999,"Active") -> 95 | I30: =COUNTIFS(Skills!$J$2:$J$999,"✓",Skills!$M$2:$M$999,"Active") -> 76 | J30: =COUNTIFS(Skills!$K$2:$K$999,"✓",Skills!$M$2:$M$999,"Active") -> 61 | K30: =IFERROR(COUNTIF('Formation Initiale'!$W$2:$W$999,"Y")/COUNTA('Formation Initiale'!$E$2:$E$999),0) -> 0.067134269
A33: ▌ STATUT PAR COHORTE (Formation initiale B2C/B2B)
A35: Cohorte | B35: Total | C35: Site | D35: Date début | E35: Date fin | F35: Terminés | G35: En cours | H35: % Complétion | I35: Prêts (Y)
A36: 173 | B36: =COUNTIF('Formation Initiale'!$B$2:$B$999,"173") -> 6 | C36: =IF(LEFT($A36,2)="OS","🇵🇹 Lisbonne","🇨🇦 Montréal") -> 🇨🇦 Montréal | D36: =IFERROR(_xlfn.MINIFS('Formation Initiale'!$G$2:$G$999,'Formation Initiale'!$B$2:$B$999,"173"),"") -> 46056 | E36: =IFERROR(_xlfn.MAXIFS('Formation Initiale'!$H$2:$H$999,'Formation Initiale'!$B$2:$B$999,"173"),"") -> 46070 | F36: =COUNTIFS('Formation Initiale'!$B$2:$B$999,"173",'Formation Initiale'!$R$2:$R$999,"Terminé") -> 6 | G36: =COUNTIFS('Formation Initiale'!$B$2:$B$999,"173",'Formation Initiale'!$R$2:$R$999,"En cours") -> 0 | H36: =IFERROR(COUNTIFS('Formation Initiale'!$B$2:$B$999,"173",'Formation Initiale'!$R$2:$R$999,"Terminé")/COUNTIF('Formation Initiale'!$B$2:$B$999,"173"),0) -> 1 | I36: =COUNTIFS('Formation Initiale'!$B$2:$B$999,"173",'Formation Initiale'!$W$2:$W$999,"Y") -> 6
A37: 174 | B37: =COUNTIF('Formation Initiale'!$B$2:$B$999,"174") -> 5 | C37: =IF(LEFT($A37,2)="OS","🇵🇹 Lisbonne","🇨🇦 Montréal") -> 🇨🇦 Montréal | D37: =IFERROR(_xlfn.MINIFS('Formation Initiale'!$G$2:$G$999,'Formation Initiale'!$B$2:$B$999,"174"),"") -> 46099 | E37: =IFERROR(_xlfn.MAXIFS('Formation Initiale'!$H$2:$H$999,'Formation Initiale'!$B$2:$B$999,"174"),"") -> 46114 | F37: =COUNTIFS('Formation Initiale'!$B$2:$B$999,"174",'Formation Initiale'!$R$2:$R$999,"Terminé") -> 5 | G37: =COUNTIFS('Formation Initiale'!$B$2:$B$999,"174",'Formation Initiale'!$R$2:$R$999,"En cours") -> 0 | H37: =IFERROR(COUNTIFS('Formation Initiale'!$B$2:$B$999,"174",'Formation Initiale'!$R$2:$R$999,"Terminé")/COUNTIF('Formation Initiale'!$B$2:$B$999,"174"),0) -> 1 | I37: =COUNTIFS('Formation Initiale'!$B$2:$B$999,"174",'Formation Initiale'!$W$2:$W$999,"Y") -> 5
A38: 175 | B38: =COUNTIF('Formation Initiale'!$B$2:$B$999,"175") -> 8 | C38: =IF(LEFT($A38,2)="OS","🇵🇹 Lisbonne","🇨🇦 Montréal") -> 🇨🇦 Montréal | D38: =IFERROR(_xlfn.MINIFS('Formation Initiale'!$G$2:$G$999,'Formation Initiale'!$B$2:$B$999,"175"),"") -> 46125 | E38: =IFERROR(_xlfn.MAXIFS('Formation Initiale'!$H$2:$H$999,'Formation Initiale'!$B$2:$B$999,"175"),"") -> 46139 | F38: =COUNTIFS('Formation Initiale'!$B$2:$B$999,"175",'Formation Initiale'!$R$2:$R$999,"Terminé") -> 8 | G38: =COUNTIFS('Formation Initiale'!$B$2:$B$999,"175",'Formation Initiale'!$R$2:$R$999,"En cours") -> 0 | H38: =IFERROR(COUNTIFS('Formation Initiale'!$B$2:$B$999,"175",'Formation Initiale'!$R$2:$R$999,"Terminé")/COUNTIF('Formation Initiale'!$B$2:$B$999,"175"),0) -> 1 | I38: =COUNTIFS('Formation Initiale'!$B$2:$B$999,"175",'Formation Initiale'!$W$2:$W$999,"Y") -> 8
A39: 176 | B39: =COUNTIF('Formation Initiale'!$B$2:$B$999,"176") -> 1 | C39: =IF(LEFT($A39,2)="OS","🇵🇹 Lisbonne","🇨🇦 Montréal") -> 🇨🇦 Montréal | D39: =IFERROR(_xlfn.MINIFS('Formation Initiale'!$G$2:$G$999,'Formation Initiale'!$B$2:$B$999,"176"),"") -> 46146 | E39: =IFERROR(_xlfn.MAXIFS('Formation Initiale'!$H$2:$H$999,'Formation Initiale'!$B$2:$B$999,"176"),"") -> 46161 | F39: =COUNTIFS('Formation Initiale'!$B$2:$B$999,"176",'Formation Initiale'!$R$2:$R$999,"Terminé") -> 1 | G39: =COUNTIFS('Formation Initiale'!$B$2:$B$999,"176",'Formation Initiale'!$R$2:$R$999,"En cours") -> 0 | H39: =IFERROR(COUNTIFS('Formation Initiale'!$B$2:$B$999,"176",'Formation Initiale'!$R$2:$R$999,"Terminé")/COUNTIF('Formation Initiale'!$B$2:$B$999,"176"),0) -> 1 | I39: =COUNTIFS('Formation Initiale'!$B$2:$B$999,"176",'Formation Initiale'!$W$2:$W$999,"Y") -> 1
A40: 177 | B40: =COUNTIF('Formation Initiale'!$B$2:$B$999,"177") -> 9 | C40: =IF(LEFT($A40,2)="OS","🇵🇹 Lisbonne","🇨🇦 Montréal") -> 🇨🇦 Montréal | D40: =IFERROR(_xlfn.MINIFS('Formation Initiale'!$G$2:$G$999,'Formation Initiale'!$B$2:$B$999,"177"),"") -> 46167 | E40: =IFERROR(_xlfn.MAXIFS('Formation Initiale'!$H$2:$H$999,'Formation Initiale'!$B$2:$B$999,"177"),"") -> 46181 | F40: =COUNTIFS('Formation Initiale'!$B$2:$B$999,"177",'Formation Initiale'!$R$2:$R$999,"Terminé") -> 9 | G40: =COUNTIFS('Formation Initiale'!$B$2:$B$999,"177",'Formation Initiale'!$R$2:$R$999,"En cours") -> 0 | H40: =IFERROR(COUNTIFS('Formation Initiale'!$B$2:$B$999,"177",'Formation Initiale'!$R$2:$R$999,"Terminé")/COUNTIF('Formation Initiale'!$B$2:$B$999,"177"),0) -> 1 | I40: =COUNTIFS('Formation Initiale'!$B$2:$B$999,"177",'Formation Initiale'!$W$2:$W$999,"Y") -> 0
A41: OS1 | B41: =COUNTIF('Formation Initiale'!$B$2:$B$999,"OS1") -> 13 | C41: =IF(LEFT($A41,2)="OS","🇵🇹 Lisbonne","🇨🇦 Montréal") -> 🇵🇹 Lisbonne | D41: =IFERROR(_xlfn.MINIFS('Formation Initiale'!$G$2:$G$999,'Formation Initiale'!$B$2:$B$999,"OS1"),"") -> 46006 | E41: =IFERROR(_xlfn.MAXIFS('Formation Initiale'!$H$2:$H$999,'Formation Initiale'!$B$2:$B$999,"OS1"),"") -> 46017 | F41: =COUNTIFS('Formation Initiale'!$B$2:$B$999,"OS1",'Formation Initiale'!$R$2:$R$999,"Terminé") -> 13 | G41: =COUNTIFS('Formation Initiale'!$B$2:$B$999,"OS1",'Formation Initiale'!$R$2:$R$999,"En cours") -> 0 | H41: =IFERROR(COUNTIFS('Formation Initiale'!$B$2:$B$999,"OS1",'Formation Initiale'!$R$2:$R$999,"Terminé")/COUNTIF('Formation Initiale'!$B$2:$B$999,"OS1"),0) -> 1 | I41: =COUNTIFS('Formation Initiale'!$B$2:$B$999,"OS1",'Formation Initiale'!$W$2:$W$999,"Y") -> 13
A42: OS2 | B42: =COUNTIF('Formation Initiale'!$B$2:$B$999,"OS2") -> 5 | C42: =IF(LEFT($A42,2)="OS","🇵🇹 Lisbonne","🇨🇦 Montréal") -> 🇵🇹 Lisbonne | D42: =IFERROR(_xlfn.MINIFS('Formation Initiale'!$G$2:$G$999,'Formation Initiale'!$B$2:$B$999,"OS2"),"") -> 46027 | E42: =IFERROR(_xlfn.MAXIFS('Formation Initiale'!$H$2:$H$999,'Formation Initiale'!$B$2:$B$999,"OS2"),"") -> 46038 | F42: =COUNTIFS('Formation Initiale'!$B$2:$B$999,"OS2",'Formation Initiale'!$R$2:$R$999,"Terminé") -> 5 | G42: =COUNTIFS('Formation Initiale'!$B$2:$B$999,"OS2",'Formation Initiale'!$R$2:$R$999,"En cours") -> 0 | H42: =IFERROR(COUNTIFS('Formation Initiale'!$B$2:$B$999,"OS2",'Formation Initiale'!$R$2:$R$999,"Terminé")/COUNTIF('Formation Initiale'!$B$2:$B$999,"OS2"),0) -> 1 | I42: =COUNTIFS('Formation Initiale'!$B$2:$B$999,"OS2",'Formation Initiale'!$W$2:$W$999,"Y") -> 5
A43: OS3 | B43: =COUNTIF('Formation Initiale'!$B$2:$B$999,"OS3") -> 9 | C43: =IF(LEFT($A43,2)="OS","🇵🇹 Lisbonne","🇨🇦 Montréal") -> 🇵🇹 Lisbonne | D43: =IFERROR(_xlfn.MINIFS('Formation Initiale'!$G$2:$G$999,'Formation Initiale'!$B$2:$B$999,"OS3"),"") -> 46034 | E43: =IFERROR(_xlfn.MAXIFS('Formation Initiale'!$H$2:$H$999,'Formation Initiale'!$B$2:$B$999,"OS3"),"") -> 46045 | F43: =COUNTIFS('Formation Initiale'!$B$2:$B$999,"OS3",'Formation Initiale'!$R$2:$R$999,"Terminé") -> 9 | G43: =COUNTIFS('Formation Initiale'!$B$2:$B$999,"OS3",'Formation Initiale'!$R$2:$R$999,"En cours") -> 0 | H43: =IFERROR(COUNTIFS('Formation Initiale'!$B$2:$B$999,"OS3",'Formation Initiale'!$R$2:$R$999,"Terminé")/COUNTIF('Formation Initiale'!$B$2:$B$999,"OS3"),0) -> 1 | I43: =COUNTIFS('Formation Initiale'!$B$2:$B$999,"OS3",'Formation Initiale'!$W$2:$W$999,"Y") -> 9
A44: OS4 | B44: =COUNTIF('Formation Initiale'!$B$2:$B$999,"OS4") -> 5 | C44: =IF(LEFT($A44,2)="OS","🇵🇹 Lisbonne","🇨🇦 Montréal") -> 🇵🇹 Lisbonne | D44: =IFERROR(_xlfn.MINIFS('Formation Initiale'!$G$2:$G$999,'Formation Initiale'!$B$2:$B$999,"OS4"),"") -> 46043 | E44: =IFERROR(_xlfn.MAXIFS('Formation Initiale'!$H$2:$H$999,'Formation Initiale'!$B$2:$B$999,"OS4"),"") -> 46056 | F44: =COUNTIFS('Formation Initiale'!$B$2:$B$999,"OS4",'Formation Initiale'!$R$2:$R$999,"Terminé") -> 5 | G44: =COUNTIFS('Formation Initiale'!$B$2:$B$999,"OS4",'Formation Initiale'!$R$2:$R$999,"En cours") -> 0 | H44: =IFERROR(COUNTIFS('Formation Initiale'!$B$2:$B$999,"OS4",'Formation Initiale'!$R$2:$R$999,"Terminé")/COUNTIF('Formation Initiale'!$B$2:$B$999,"OS4"),0) -> 1 | I44: =COUNTIFS('Formation Initiale'!$B$2:$B$999,"OS4",'Formation Initiale'!$W$2:$W$999,"Y") -> 5
A45: OS5 | B45: =COUNTIF('Formation Initiale'!$B$2:$B$999,"OS5") -> 5 | C45: =IF(LEFT($A45,2)="OS","🇵🇹 Lisbonne","🇨🇦 Montréal") -> 🇵🇹 Lisbonne | D45: =IFERROR(_xlfn.MINIFS('Formation Initiale'!$G$2:$G$999,'Formation Initiale'!$B$2:$B$999,"OS5"),"") -> 46111 | E45: =IFERROR(_xlfn.MAXIFS('Formation Initiale'!$H$2:$H$999,'Formation Initiale'!$B$2:$B$999,"OS5"),"") -> 46122 | F45: =COUNTIFS('Formation Initiale'!$B$2:$B$999,"OS5",'Formation Initiale'!$R$2:$R$999,"Terminé") -> 5 | G45: =COUNTIFS('Formation Initiale'!$B$2:$B$999,"OS5",'Formation Initiale'!$R$2:$R$999,"En cours") -> 0 | H45: =IFERROR(COUNTIFS('Formation Initiale'!$B$2:$B$999,"OS5",'Formation Initiale'!$R$2:$R$999,"Terminé")/COUNTIF('Formation Initiale'!$B$2:$B$999,"OS5"),0) -> 1 | I45: =COUNTIFS('Formation Initiale'!$B$2:$B$999,"OS5",'Formation Initiale'!$W$2:$W$999,"Y") -> 5
A46: OS6 | B46: =COUNTIF('Formation Initiale'!$B$2:$B$999,"OS6") -> 4 | C46: =IF(LEFT($A46,2)="OS","🇵🇹 Lisbonne","🇨🇦 Montréal") -> 🇵🇹 Lisbonne | D46: =IFERROR(_xlfn.MINIFS('Formation Initiale'!$G$2:$G$999,'Formation Initiale'!$B$2:$B$999,"OS6"),"") -> 46132 | E46: =IFERROR(_xlfn.MAXIFS('Formation Initiale'!$H$2:$H$999,'Formation Initiale'!$B$2:$B$999,"OS6"),"") -> 46143 | F46: =COUNTIFS('Formation Initiale'!$B$2:$B$999,"OS6",'Formation Initiale'!$R$2:$R$999,"Terminé") -> 4 | G46: =COUNTIFS('Formation Initiale'!$B$2:$B$999,"OS6",'Formation Initiale'!$R$2:$R$999,"En cours") -> 0 | H46: =IFERROR(COUNTIFS('Formation Initiale'!$B$2:$B$999,"OS6",'Formation Initiale'!$R$2:$R$999,"Terminé")/COUNTIF('Formation Initiale'!$B$2:$B$999,"OS6"),0) -> 1 | I46: =COUNTIFS('Formation Initiale'!$B$2:$B$999,"OS6",'Formation Initiale'!$W$2:$W$999,"Y") -> 4
A47: OS7 | B47: =COUNTIF('Formation Initiale'!$B$2:$B$999,"OS7") -> 6 | C47: =IF(LEFT($A47,2)="OS","🇵🇹 Lisbonne","🇨🇦 Montréal") -> 🇵🇹 Lisbonne | D47: =IFERROR(_xlfn.MINIFS('Formation Initiale'!$G$2:$G$999,'Formation Initiale'!$B$2:$B$999,"OS7"),"") -> 46139 | E47: =IFERROR(_xlfn.MAXIFS('Formation Initiale'!$H$2:$H$999,'Formation Initiale'!$B$2:$B$999,"OS7"),"") -> 46150 | F47: =COUNTIFS('Formation Initiale'!$B$2:$B$999,"OS7",'Formation Initiale'!$R$2:$R$999,"Terminé") -> 6 | G47: =COUNTIFS('Formation Initiale'!$B$2:$B$999,"OS7",'Formation Initiale'!$R$2:$R$999,"En cours") -> 0 | H47: =IFERROR(COUNTIFS('Formation Initiale'!$B$2:$B$999,"OS7",'Formation Initiale'!$R$2:$R$999,"Terminé")/COUNTIF('Formation Initiale'!$B$2:$B$999,"OS7"),0) -> 1 | I47: =COUNTIFS('Formation Initiale'!$B$2:$B$999,"OS7",'Formation Initiale'!$W$2:$W$999,"Y") -> 6
A50: ▌ ENTONNOIR DE PROGRESSION (Tous types de formation)
A52: Type de formation | B52: Sessions Total | C52: Terminées | D52: En cours | E52: À venir | F52: % Complétion
A53: Formation B2C/B2B | B53: =COUNTA('Formation Initiale'!$E$2:$E$999) -> 998 | C53: =COUNTIF('Formation Initiale'!$R$2:$R$999,"Terminé") -> 82 | D53: =COUNTIF('Formation Initiale'!$R$2:$R$999,"En cours") -> 15 | E53: =COUNTIF('Formation Initiale'!$R$2:$R$999,"À venir") -> 0 | F53: =IFERROR(C53/B53,0) -> 0.082164329
A54: Agences | B54: =COUNTIFS('Agences & Après-vente'!$D$2:$D$1000,"Agences")+COUNTIFS('Agences & Après-vente'!$D$2:$D$1000,"Agences et Après-vente") -> 82 | C54: =SUMPRODUCT((('Agences & Après-vente'!$D$2:$D$1000="Agences")+('Agences & Après-vente'!$D$2:$D$1000="Agences et Après-vente"))*('Agences & Après-vente'!$I$2:$I$1000="DONE")) -> 80 | D54: =SUMPRODUCT((('Agences & Après-vente'!$D$2:$D$1000="Agences")+('Agences & Après-vente'!$D$2:$D$1000="Agences et Après-vente"))*('Agences & Après-vente'!$I$2:$I$1000="En cours")) -> 2 | E54: =SUMPRODUCT((('Agences & Après-vente'!$D$2:$D$1000="Agences")+('Agences & Après-vente'!$D$2:$D$1000="Agences et Après-vente"))*('Agences & Après-vente'!$I$2:$I$1000="À venir")) -> 0 | F54: =IFERROR(C54/B54,0) -> 0.97560976
A55: Après-vente | B55: =COUNTIFS('Agences & Après-vente'!$D$2:$D$1000,"Après-vente")+COUNTIFS('Agences & Après-vente'!$D$2:$D$1000,"Agences et Après-vente") -> 91 | C55: =SUMPRODUCT((('Agences & Après-vente'!$D$2:$D$1000="Après-vente")+('Agences & Après-vente'!$D$2:$D$1000="Agences et Après-vente"))*('Agences & Après-vente'!$I$2:$I$1000="DONE")) -> 89 | D55: =SUMPRODUCT((('Agences & Après-vente'!$D$2:$D$1000="Après-vente")+('Agences & Après-vente'!$D$2:$D$1000="Agences et Après-vente"))*('Agences & Après-vente'!$I$2:$I$1000="En cours")) -> 2 | E55: =SUMPRODUCT((('Agences & Après-vente'!$D$2:$D$1000="Après-vente")+('Agences & Après-vente'!$D$2:$D$1000="Agences et Après-vente"))*('Agences & Après-vente'!$I$2:$I$1000="À venir")) -> 0 | F55: =IFERROR(C55/B55,0) -> 0.97802198
A56: Evermont | B56: =COUNTA(Evermont!$A$2:$A$1000) -> 24 | C56: =COUNTIF(Evermont!$Q$2:$Q$1000,"Terminé") -> 22 | D56: =COUNTIF(Evermont!$Q$2:$Q$1000,"En cours") -> 1 | E56: =COUNTIF(Evermont!$Q$2:$Q$1000,"À venir") -> 1 | F56: =IFERROR(C56/B56,0) -> 0.91666667
A59: ▌ AGENTS POLYVALENTS (Nombre de compétences acquises)
A61: Nb compétences | B61: Agents | C61: %
A62: 0 compétences | B62: =COUNTIFS(Skills!$L$2:$L$999,0,Skills!$M$2:$M$999,"Active") -> 15 | C62: =IFERROR(B62/COUNTIFS(Skills!$A$2:$A$999,"?*",Skills!$M$2:$M$999,"Active"),0) -> 0.10204082
A63: 1 compétence | B63: =COUNTIFS(Skills!$L$2:$L$999,1,Skills!$M$2:$M$999,"Active") -> 13 | C63: =IFERROR(B63/COUNTIFS(Skills!$A$2:$A$999,"?*",Skills!$M$2:$M$999,"Active"),0) -> 0.088435374
A64: 2 compétences | B64: =COUNTIFS(Skills!$L$2:$L$999,2,Skills!$M$2:$M$999,"Active") -> 21 | C64: =IFERROR(B64/COUNTIFS(Skills!$A$2:$A$999,"?*",Skills!$M$2:$M$999,"Active"),0) -> 0.14285714
A65: 3 compétences | B65: =COUNTIFS(Skills!$L$2:$L$999,3,Skills!$M$2:$M$999,"Active") -> 19 | C65: =IFERROR(B65/COUNTIFS(Skills!$A$2:$A$999,"?*",Skills!$M$2:$M$999,"Active"),0) -> 0.1292517
A66: 4 compétences | B66: =COUNTIFS(Skills!$L$2:$L$999,4,Skills!$M$2:$M$999,"Active") -> 2 | C66: =IFERROR(B66/COUNTIFS(Skills!$A$2:$A$999,"?*",Skills!$M$2:$M$999,"Active"),0) -> 0.013605442
A67: 5 compétences | B67: =COUNTIFS(Skills!$L$2:$L$999,5,Skills!$M$2:$M$999,"Active") -> 1 | C67: =IFERROR(B67/COUNTIFS(Skills!$A$2:$A$999,"?*",Skills!$M$2:$M$999,"Active"),0) -> 0.0068027211
A68: 6 compétences | B68: =COUNTIFS(Skills!$L$2:$L$999,6,Skills!$M$2:$M$999,"Active") -> 16 | C68: =IFERROR(B68/COUNTIFS(Skills!$A$2:$A$999,"?*",Skills!$M$2:$M$999,"Active"),0) -> 0.10884354
A69: 7 compétences | B69: =COUNTIFS(Skills!$L$2:$L$999,7,Skills!$M$2:$M$999,"Active") -> 60 | C69: =IFERROR(B69/COUNTIFS(Skills!$A$2:$A$999,"?*",Skills!$M$2:$M$999,"Active"),0) -> 0.40816327
A72: ▌ DURÉE MOYENNE DE COMPLÉTION — jours ouvrés (hors Agences / Après-vente)
A74: FORMATION INITIALE (B2C / B2B) | C74: INITIALE — MONTRÉAL | E74: INITIALE — LISBONNE | G74: Evermont
A75: =IFERROR(AVERAGE('Formation Initiale'!$Z$2:$Z$999),0) -> 11.304878 | C75: =IFERROR(AVERAGEIFS('Formation Initiale'!$Z$2:$Z$999,'Formation Initiale'!$F$2:$F$999,"Montréal",'Formation Initiale'!$R$2:$R$999,"Terminé"),0) -> 13.310345 | E75: =IFERROR(AVERAGEIFS('Formation Initiale'!$Z$2:$Z$999,'Formation Initiale'!$F$2:$F$999,"Lisbonne",'Formation Initiale'!$R$2:$R$999,"Terminé"),0) -> 10.207547 | G75: =IFERROR(AVERAGE(Evermont!$V$2:$V$1000),0) -> 7.7272727
A78: ▌ DÉTAIL Agences / Après-vente / Evermont (Statut courant)
A80: Formation | B80: Total sessions | C80: DONE | D80: En cours | E80: À venir | F80: Site Ulman | G80: Site Valmont
A81: Agences (toutes) | B81: =COUNTIFS('Agences & Après-vente'!$D$2:$D$1000,"Agences")+COUNTIFS('Agences & Après-vente'!$D$2:$D$1000,"Agences et Après-vente") -> 82 | C81: =SUMPRODUCT((('Agences & Après-vente'!$D$2:$D$1000="Agences")+('Agences & Après-vente'!$D$2:$D$1000="Agences et Après-vente"))*('Agences & Après-vente'!$I$2:$I$1000="DONE")) -> 80 | D81: =SUMPRODUCT((('Agences & Après-vente'!$D$2:$D$1000="Agences")+('Agences & Après-vente'!$D$2:$D$1000="Agences et Après-vente"))*('Agences & Après-vente'!$I$2:$I$1000="En cours")) -> 2 | E81: =SUMPRODUCT((('Agences & Après-vente'!$D$2:$D$1000="Agences")+('Agences & Après-vente'!$D$2:$D$1000="Agences et Après-vente"))*('Agences & Après-vente'!$I$2:$I$1000="À venir")) -> 0 | F81: =SUMPRODUCT((('Agences & Après-vente'!$D$2:$D$1000="Agences")+('Agences & Après-vente'!$D$2:$D$1000="Agences et Après-vente"))*('Agences & Après-vente'!$C$2:$C$1000="Montréal")) -> 59 | G81: =SUMPRODUCT((('Agences & Après-vente'!$D$2:$D$1000="Agences")+('Agences & Après-vente'!$D$2:$D$1000="Agences et Après-vente"))*('Agences & Après-vente'!$C$2:$C$1000="Lisbonne")) -> 23
A82: Après-vente (toutes) | B82: =COUNTIFS('Agences & Après-vente'!$D$2:$D$1000,"Après-vente")+COUNTIFS('Agences & Après-vente'!$D$2:$D$1000,"Agences et Après-vente") -> 91 | C82: =SUMPRODUCT((('Agences & Après-vente'!$D$2:$D$1000="Après-vente")+('Agences & Après-vente'!$D$2:$D$1000="Agences et Après-vente"))*('Agences & Après-vente'!$I$2:$I$1000="DONE")) -> 89 | D82: =SUMPRODUCT((('Agences & Après-vente'!$D$2:$D$1000="Après-vente")+('Agences & Après-vente'!$D$2:$D$1000="Agences et Après-vente"))*('Agences & Après-vente'!$I$2:$I$1000="En cours")) -> 2 | E82: =SUMPRODUCT((('Agences & Après-vente'!$D$2:$D$1000="Après-vente")+('Agences & Après-vente'!$D$2:$D$1000="Agences et Après-vente"))*('Agences & Après-vente'!$I$2:$I$1000="À venir")) -> 0 | F82: =SUMPRODUCT((('Agences & Après-vente'!$D$2:$D$1000="Après-vente")+('Agences & Après-vente'!$D$2:$D$1000="Agences et Après-vente"))*('Agences & Après-vente'!$C$2:$C$1000="Montréal")) -> 71 | G82: =SUMPRODUCT((('Agences & Après-vente'!$D$2:$D$1000="Après-vente")+('Agences & Après-vente'!$D$2:$D$1000="Agences et Après-vente"))*('Agences & Après-vente'!$C$2:$C$1000="Lisbonne")) -> 20
A83: Evermont | B83: =COUNTA(Evermont!$A$2:$A$1000) -> 24 | C83: =COUNTIF(Evermont!$Q$2:$Q$1000,"Terminé") -> 22 | D83: =COUNTIF(Evermont!$Q$2:$Q$1000,"En cours") -> 1 | E83: =COUNTIF(Evermont!$Q$2:$Q$1000,"À venir") -> 1 | F83: =COUNTIF(Evermont!$C$2:$C$1000,"Montréal") -> 24 | G83: =COUNTIF(Evermont!$C$2:$C$1000,"Lisbonne") -> 0
A85: 💡 Astuce : Tous les chiffres se mettent à jour automatiquement quand vous modifiez Formation Initiale, Agences & Après-vente ou Evermont.
A87: ▌ EFFECTIFS & ATTRITION (Statut COS = départ)
A89: ACTIFS | C89: DÉPARTS (COS) | E89: EN ARRÊT (Maladie) | G89: TAUX D'ATTRITION | I89: EFFECTIF TOTAL
A90: =COUNTIF(Skills!$M$2:$M$999,"Active") -> 147 | C90: =COUNTIF(Skills!$M$2:$M$999,"COS") -> 27 | E90: =COUNTIF(Skills!$M$2:$M$999,"Maladie") -> 3 | G90: =IFERROR(COUNTIF(Skills!$M$2:$M$999,"COS")/COUNTIF(Skills!$A$2:$A$999,"?*"),0) -> 0.15254237 | I90: =COUNTIF(Skills!$A$2:$A$999,"?*") -> 177
A92: ▌ ATTRITION PAR GROUPE / COHORTE
A94: Groupe | B94: Site | C94: Effectif (roster) | D94: Actifs | E94: Départs (COS) | F94: Taux d'attrition | G94: Absences (jours) | H94: Sessions touchées | I94: Jours / actif
A95: 173 | B95: =IF(LEFT($A95,2)="OS","🇵🇹 Lisbonne","🇨🇦 Montréal") -> 🇨🇦 Montréal | C95: =COUNTIF(Skills!$W$2:$W$999,$A95) -> 6 | D95: =COUNTIFS(Skills!$W$2:$W$999,$A95,Skills!$M$2:$M$999,"Active") -> 4 | E95: =COUNTIFS(Skills!$W$2:$W$999,$A95,Skills!$M$2:$M$999,"COS") -> 2 | F95: =IFERROR($E95/$C95,0) -> 0.33333333 | G95: =SUMIF('Formation Initiale'!$B$2:$B$999,$A95,'Formation Initiale'!$AB$2:$AB$999)+SUMPRODUCT(Evermont!$X$2:$X$1000*ISNUMBER(MATCH(Evermont!$A$2:$A$1000,IF(Skills!$W$2:$W$999=$A95,Skills!$A$2:$A$999),0))) -> 0 | H95: =COUNTIFS('Formation Initiale'!$B$2:$B$999,$A95,'Formation Initiale'!$AB$2:$AB$999,">0")+SUMPRODUCT((Evermont!$X$2:$X$1000>0)*ISNUMBER(MATCH(Evermont!$A$2:$A$1000,IF(Skills!$W$2:$W$999=$A95,Skills!$A$2:$A$999),0))) -> 0 | I95: =IFERROR($G95/$D95,0) -> 0
A96: 174 | B96: =IF(LEFT($A96,2)="OS","🇵🇹 Lisbonne","🇨🇦 Montréal") -> 🇨🇦 Montréal | C96: =COUNTIF(Skills!$W$2:$W$999,$A96) -> 5 | D96: =COUNTIFS(Skills!$W$2:$W$999,$A96,Skills!$M$2:$M$999,"Active") -> 5 | E96: =COUNTIFS(Skills!$W$2:$W$999,$A96,Skills!$M$2:$M$999,"COS") -> 0 | F96: =IFERROR($E96/$C96,0) -> 0 | G96: =SUMIF('Formation Initiale'!$B$2:$B$999,$A96,'Formation Initiale'!$AB$2:$AB$999)+SUMPRODUCT(Evermont!$X$2:$X$1000*ISNUMBER(MATCH(Evermont!$A$2:$A$1000,IF(Skills!$W$2:$W$999=$A96,Skills!$A$2:$A$999),0))) -> 0 | H96: =COUNTIFS('Formation Initiale'!$B$2:$B$999,$A96,'Formation Initiale'!$AB$2:$AB$999,">0")+SUMPRODUCT((Evermont!$X$2:$X$1000>0)*ISNUMBER(MATCH(Evermont!$A$2:$A$1000,IF(Skills!$W$2:$W$999=$A96,Skills!$A$2:$A$999),0))) -> 0 | I96: =IFERROR($G96/$D96,0) -> 0
A97: 175 | B97: =IF(LEFT($A97,2)="OS","🇵🇹 Lisbonne","🇨🇦 Montréal") -> 🇨🇦 Montréal | C97: =COUNTIF(Skills!$W$2:$W$999,$A97) -> 8 | D97: =COUNTIFS(Skills!$W$2:$W$999,$A97,Skills!$M$2:$M$999,"Active") -> 8 | E97: =COUNTIFS(Skills!$W$2:$W$999,$A97,Skills!$M$2:$M$999,"COS") -> 0 | F97: =IFERROR($E97/$C97,0) -> 0 | G97: =SUMIF('Formation Initiale'!$B$2:$B$999,$A97,'Formation Initiale'!$AB$2:$AB$999)+SUMPRODUCT(Evermont!$X$2:$X$1000*ISNUMBER(MATCH(Evermont!$A$2:$A$1000,IF(Skills!$W$2:$W$999=$A97,Skills!$A$2:$A$999),0))) -> 0 | H97: =COUNTIFS('Formation Initiale'!$B$2:$B$999,$A97,'Formation Initiale'!$AB$2:$AB$999,">0")+SUMPRODUCT((Evermont!$X$2:$X$1000>0)*ISNUMBER(MATCH(Evermont!$A$2:$A$1000,IF(Skills!$W$2:$W$999=$A97,Skills!$A$2:$A$999),0))) -> 0 | I97: =IFERROR($G97/$D97,0) -> 0
A98: 176 | B98: =IF(LEFT($A98,2)="OS","🇵🇹 Lisbonne","🇨🇦 Montréal") -> 🇨🇦 Montréal | C98: =COUNTIF(Skills!$W$2:$W$999,$A98) -> 1 | D98: =COUNTIFS(Skills!$W$2:$W$999,$A98,Skills!$M$2:$M$999,"Active") -> 0 | E98: =COUNTIFS(Skills!$W$2:$W$999,$A98,Skills!$M$2:$M$999,"COS") -> 1 | F98: =IFERROR($E98/$C98,0) -> 1 | G98: =SUMIF('Formation Initiale'!$B$2:$B$999,$A98,'Formation Initiale'!$AB$2:$AB$999)+SUMPRODUCT(Evermont!$X$2:$X$1000*ISNUMBER(MATCH(Evermont!$A$2:$A$1000,IF(Skills!$W$2:$W$999=$A98,Skills!$A$2:$A$999),0))) -> 0 | H98: =COUNTIFS('Formation Initiale'!$B$2:$B$999,$A98,'Formation Initiale'!$AB$2:$AB$999,">0")+SUMPRODUCT((Evermont!$X$2:$X$1000>0)*ISNUMBER(MATCH(Evermont!$A$2:$A$1000,IF(Skills!$W$2:$W$999=$A98,Skills!$A$2:$A$999),0))) -> 0 | I98: =IFERROR($G98/$D98,0) -> 0
A99: 177 | B99: =IF(LEFT($A99,2)="OS","🇵🇹 Lisbonne","🇨🇦 Montréal") -> 🇨🇦 Montréal | C99: =COUNTIF(Skills!$W$2:$W$999,$A99) -> 9 | D99: =COUNTIFS(Skills!$W$2:$W$999,$A99,Skills!$M$2:$M$999,"Active") -> 8 | E99: =COUNTIFS(Skills!$W$2:$W$999,$A99,Skills!$M$2:$M$999,"COS") -> 1 | F99: =IFERROR($E99/$C99,0) -> 0.11111111 | G99: =SUMIF('Formation Initiale'!$B$2:$B$999,$A99,'Formation Initiale'!$AB$2:$AB$999)+SUMPRODUCT(Evermont!$X$2:$X$1000*ISNUMBER(MATCH(Evermont!$A$2:$A$1000,IF(Skills!$W$2:$W$999=$A99,Skills!$A$2:$A$999),0))) -> 2 | H99: =COUNTIFS('Formation Initiale'!$B$2:$B$999,$A99,'Formation Initiale'!$AB$2:$AB$999,">0")+SUMPRODUCT((Evermont!$X$2:$X$1000>0)*ISNUMBER(MATCH(Evermont!$A$2:$A$1000,IF(Skills!$W$2:$W$999=$A99,Skills!$A$2:$A$999),0))) -> 1 | I99: =IFERROR($G99/$D99,0) -> 0.25
A100: OS1 | B100: =IF(LEFT($A100,2)="OS","🇵🇹 Lisbonne","🇨🇦 Montréal") -> 🇵🇹 Lisbonne | C100: =COUNTIF(Skills!$W$2:$W$999,$A100) -> 13 | D100: =COUNTIFS(Skills!$W$2:$W$999,$A100,Skills!$M$2:$M$999,"Active") -> 9 | E100: =COUNTIFS(Skills!$W$2:$W$999,$A100,Skills!$M$2:$M$999,"COS") -> 4 | F100: =IFERROR($E100/$C100,0) -> 0.30769231 | G100: =SUMIF('Formation Initiale'!$B$2:$B$999,$A100,'Formation Initiale'!$AB$2:$AB$999)+SUMPRODUCT(Evermont!$X$2:$X$1000*ISNUMBER(MATCH(Evermont!$A$2:$A$1000,IF(Skills!$W$2:$W$999=$A100,Skills!$A$2:$A$999),0))) -> 0 | H100: =COUNTIFS('Formation Initiale'!$B$2:$B$999,$A100,'Formation Initiale'!$AB$2:$AB$999,">0")+SUMPRODUCT((Evermont!$X$2:$X$1000>0)*ISNUMBER(MATCH(Evermont!$A$2:$A$1000,IF(Skills!$W$2:$W$999=$A100,Skills!$A$2:$A$999),0))) -> 0 | I100: =IFERROR($G100/$D100,0) -> 0
A101: OS2 | B101: =IF(LEFT($A101,2)="OS","🇵🇹 Lisbonne","🇨🇦 Montréal") -> 🇵🇹 Lisbonne | C101: =COUNTIF(Skills!$W$2:$W$999,$A101) -> 5 | D101: =COUNTIFS(Skills!$W$2:$W$999,$A101,Skills!$M$2:$M$999,"Active") -> 2 | E101: =COUNTIFS(Skills!$W$2:$W$999,$A101,Skills!$M$2:$M$999,"COS") -> 3 | F101: =IFERROR($E101/$C101,0) -> 0.6 | G101: =SUMIF('Formation Initiale'!$B$2:$B$999,$A101,'Formation Initiale'!$AB$2:$AB$999)+SUMPRODUCT(Evermont!$X$2:$X$1000*ISNUMBER(MATCH(Evermont!$A$2:$A$1000,IF(Skills!$W$2:$W$999=$A101,Skills!$A$2:$A$999),0))) -> 0 | H101: =COUNTIFS('Formation Initiale'!$B$2:$B$999,$A101,'Formation Initiale'!$AB$2:$AB$999,">0")+SUMPRODUCT((Evermont!$X$2:$X$1000>0)*ISNUMBER(MATCH(Evermont!$A$2:$A$1000,IF(Skills!$W$2:$W$999=$A101,Skills!$A$2:$A$999),0))) -> 0 | I101: =IFERROR($G101/$D101,0) -> 0
A102: OS3 | B102: =IF(LEFT($A102,2)="OS","🇵🇹 Lisbonne","🇨🇦 Montréal") -> 🇵🇹 Lisbonne | C102: =COUNTIF(Skills!$W$2:$W$999,$A102) -> 9 | D102: =COUNTIFS(Skills!$W$2:$W$999,$A102,Skills!$M$2:$M$999,"Active") -> 3 | E102: =COUNTIFS(Skills!$W$2:$W$999,$A102,Skills!$M$2:$M$999,"COS") -> 6 | F102: =IFERROR($E102/$C102,0) -> 0.66666667 | G102: =SUMIF('Formation Initiale'!$B$2:$B$999,$A102,'Formation Initiale'!$AB$2:$AB$999)+SUMPRODUCT(Evermont!$X$2:$X$1000*ISNUMBER(MATCH(Evermont!$A$2:$A$1000,IF(Skills!$W$2:$W$999=$A102,Skills!$A$2:$A$999),0))) -> 0 | H102: =COUNTIFS('Formation Initiale'!$B$2:$B$999,$A102,'Formation Initiale'!$AB$2:$AB$999,">0")+SUMPRODUCT((Evermont!$X$2:$X$1000>0)*ISNUMBER(MATCH(Evermont!$A$2:$A$1000,IF(Skills!$W$2:$W$999=$A102,Skills!$A$2:$A$999),0))) -> 0 | I102: =IFERROR($G102/$D102,0) -> 0
A103: OS4 | B103: =IF(LEFT($A103,2)="OS","🇵🇹 Lisbonne","🇨🇦 Montréal") -> 🇵🇹 Lisbonne | C103: =COUNTIF(Skills!$W$2:$W$999,$A103) -> 5 | D103: =COUNTIFS(Skills!$W$2:$W$999,$A103,Skills!$M$2:$M$999,"Active") -> 2 | E103: =COUNTIFS(Skills!$W$2:$W$999,$A103,Skills!$M$2:$M$999,"COS") -> 3 | F103: =IFERROR($E103/$C103,0) -> 0.6 | G103: =SUMIF('Formation Initiale'!$B$2:$B$999,$A103,'Formation Initiale'!$AB$2:$AB$999)+SUMPRODUCT(Evermont!$X$2:$X$1000*ISNUMBER(MATCH(Evermont!$A$2:$A$1000,IF(Skills!$W$2:$W$999=$A103,Skills!$A$2:$A$999),0))) -> 0 | H103: =COUNTIFS('Formation Initiale'!$B$2:$B$999,$A103,'Formation Initiale'!$AB$2:$AB$999,">0")+SUMPRODUCT((Evermont!$X$2:$X$1000>0)*ISNUMBER(MATCH(Evermont!$A$2:$A$1000,IF(Skills!$W$2:$W$999=$A103,Skills!$A$2:$A$999),0))) -> 0 | I103: =IFERROR($G103/$D103,0) -> 0
A104: OS5 | B104: =IF(LEFT($A104,2)="OS","🇵🇹 Lisbonne","🇨🇦 Montréal") -> 🇵🇹 Lisbonne | C104: =COUNTIF(Skills!$W$2:$W$999,$A104) -> 5 | D104: =COUNTIFS(Skills!$W$2:$W$999,$A104,Skills!$M$2:$M$999,"Active") -> 5 | E104: =COUNTIFS(Skills!$W$2:$W$999,$A104,Skills!$M$2:$M$999,"COS") -> 0 | F104: =IFERROR($E104/$C104,0) -> 0 | G104: =SUMIF('Formation Initiale'!$B$2:$B$999,$A104,'Formation Initiale'!$AB$2:$AB$999)+SUMPRODUCT(Evermont!$X$2:$X$1000*ISNUMBER(MATCH(Evermont!$A$2:$A$1000,IF(Skills!$W$2:$W$999=$A104,Skills!$A$2:$A$999),0))) -> 0 | H104: =COUNTIFS('Formation Initiale'!$B$2:$B$999,$A104,'Formation Initiale'!$AB$2:$AB$999,">0")+SUMPRODUCT((Evermont!$X$2:$X$1000>0)*ISNUMBER(MATCH(Evermont!$A$2:$A$1000,IF(Skills!$W$2:$W$999=$A104,Skills!$A$2:$A$999),0))) -> 0 | I104: =IFERROR($G104/$D104,0) -> 0
A105: OS6 | B105: =IF(LEFT($A105,2)="OS","🇵🇹 Lisbonne","🇨🇦 Montréal") -> 🇵🇹 Lisbonne | C105: =COUNTIF(Skills!$W$2:$W$999,$A105) -> 4 | D105: =COUNTIFS(Skills!$W$2:$W$999,$A105,Skills!$M$2:$M$999,"Active") -> 4 | E105: =COUNTIFS(Skills!$W$2:$W$999,$A105,Skills!$M$2:$M$999,"COS") -> 0 | F105: =IFERROR($E105/$C105,0) -> 0 | G105: =SUMIF('Formation Initiale'!$B$2:$B$999,$A105,'Formation Initiale'!$AB$2:$AB$999)+SUMPRODUCT(Evermont!$X$2:$X$1000*ISNUMBER(MATCH(Evermont!$A$2:$A$1000,IF(Skills!$W$2:$W$999=$A105,Skills!$A$2:$A$999),0))) -> 0 | H105: =COUNTIFS('Formation Initiale'!$B$2:$B$999,$A105,'Formation Initiale'!$AB$2:$AB$999,">0")+SUMPRODUCT((Evermont!$X$2:$X$1000>0)*ISNUMBER(MATCH(Evermont!$A$2:$A$1000,IF(Skills!$W$2:$W$999=$A105,Skills!$A$2:$A$999),0))) -> 0 | I105: =IFERROR($G105/$D105,0) -> 0
A106: OS7 | B106: =IF(LEFT($A106,2)="OS","🇵🇹 Lisbonne","🇨🇦 Montréal") -> 🇵🇹 Lisbonne | C106: =COUNTIF(Skills!$W$2:$W$999,$A106) -> 6 | D106: =COUNTIFS(Skills!$W$2:$W$999,$A106,Skills!$M$2:$M$999,"Active") -> 4 | E106: =COUNTIFS(Skills!$W$2:$W$999,$A106,Skills!$M$2:$M$999,"COS") -> 2 | F106: =IFERROR($E106/$C106,0) -> 0.33333333 | G106: =SUMIF('Formation Initiale'!$B$2:$B$999,$A106,'Formation Initiale'!$AB$2:$AB$999)+SUMPRODUCT(Evermont!$X$2:$X$1000*ISNUMBER(MATCH(Evermont!$A$2:$A$1000,IF(Skills!$W$2:$W$999=$A106,Skills!$A$2:$A$999),0))) -> 0 | H106: =COUNTIFS('Formation Initiale'!$B$2:$B$999,$A106,'Formation Initiale'!$AB$2:$AB$999,">0")+SUMPRODUCT((Evermont!$X$2:$X$1000>0)*ISNUMBER(MATCH(Evermont!$A$2:$A$1000,IF(Skills!$W$2:$W$999=$A106,Skills!$A$2:$A$999),0))) -> 0 | I106: =IFERROR($G106/$D106,0) -> 0
A107: OS8 | B107: =IF(LEFT($A107,2)="OS","🇵🇹 Lisbonne","🇨🇦 Montréal") -> 🇵🇹 Lisbonne | C107: =COUNTIF(Skills!$W$2:$W$999,$A107) -> 6 | D107: =COUNTIFS(Skills!$W$2:$W$999,$A107,Skills!$M$2:$M$999,"Active") -> 6 | E107: =COUNTIFS(Skills!$W$2:$W$999,$A107,Skills!$M$2:$M$999,"COS") -> 0 | F107: =IFERROR($E107/$C107,0) -> 0 | G107: =SUMIF('Formation Initiale'!$B$2:$B$999,$A107,'Formation Initiale'!$AB$2:$AB$999)+SUMPRODUCT(Evermont!$X$2:$X$1000*ISNUMBER(MATCH(Evermont!$A$2:$A$1000,IF(Skills!$W$2:$W$999=$A107,Skills!$A$2:$A$999),0))) -> 3 | H107: =COUNTIFS('Formation Initiale'!$B$2:$B$999,$A107,'Formation Initiale'!$AB$2:$AB$999,">0")+SUMPRODUCT((Evermont!$X$2:$X$1000>0)*ISNUMBER(MATCH(Evermont!$A$2:$A$1000,IF(Skills!$W$2:$W$999=$A107,Skills!$A$2:$A$999),0))) -> 2 | I107: =IFERROR($G107/$D107,0) -> 0.5
A108: Général (sans cohorte) | B108: — | C108: =COUNTIF(Skills!$W$2:$W$999,"Général") -> 80 | D108: =COUNTIFS(Skills!$W$2:$W$999,"Général",Skills!$M$2:$M$999,"Active") -> 72 | E108: =COUNTIFS(Skills!$W$2:$W$999,"Général",Skills!$M$2:$M$999,"COS") -> 5 | F108: =IFERROR($E108/$C108,0) -> 0.0625 | G108: =SUMIF('Formation Initiale'!$B$2:$B$999,"Général",'Formation Initiale'!$AB$2:$AB$999)+SUMPRODUCT(Evermont!$X$2:$X$1000*ISNUMBER(MATCH(Evermont!$A$2:$A$1000,IF(Skills!$W$2:$W$999="Général",Skills!$A$2:$A$999),0))) -> 5 | H108: =COUNTIFS('Formation Initiale'!$B$2:$B$999,"Général",'Formation Initiale'!$AB$2:$AB$999,">0")+SUMPRODUCT((Evermont!$X$2:$X$1000>0)*ISNUMBER(MATCH(Evermont!$A$2:$A$1000,IF(Skills!$W$2:$W$999="Général",Skills!$A$2:$A$999),0))) -> 4 | I108: =IFERROR($G108/$D108,0) -> 0.069444444
A109: TOTAL | C109: =COUNTIF(Skills!$A$2:$A$999,"?*") -> 177 | D109: =COUNTIF(Skills!$M$2:$M$999,"Active") -> 147 | E109: =COUNTIF(Skills!$M$2:$M$999,"COS") -> 27 | F109: =IFERROR($E109/$C109,0) -> 0.15254237 | G109: =SUM('Formation Initiale'!$AB$2:$AB$999)+SUM(Evermont!$X$2:$X$1000) -> 10 | H109: =COUNTIF('Formation Initiale'!$AB$2:$AB$999,">0")+COUNTIF(Evermont!$X$2:$X$1000,">0") -> 7 | I109: =IFERROR($G109/$D109,0) -> 0.068027211
A111: ▌ INTÉGRITÉ DES DONNÉES (ancrage sur Active + Skills)
A113: Vérification | C113: Nombre
A114: IDs orphelins — Formation Initiale (absents du roster) | C114: =SUMPRODUCT(('Formation Initiale'!$A$2:$A$999<>"")*(COUNTIF(Skills!$A$2:$A$999,'Formation Initiale'!$A$2:$A$999)=0)) -> 0
A115: IDs orphelins — Agences & Après-vente | C115: =SUMPRODUCT(('Agences & Après-vente'!$A$2:$A$1000<>"")*(COUNTIF(Skills!$A$2:$A$999,'Agences & Après-vente'!$A$2:$A$1000)=0)) -> 0
A116: IDs orphelins — Evermont | C116: =SUMPRODUCT((Evermont!$A$2:$A$1000<>"")*(COUNTIF(Skills!$A$2:$A$999,Evermont!$A$2:$A$1000)=0)) -> 0
A117: IDs en double dans le roster | C117: =SUMPRODUCT((Skills!$A$2:$A$999<>"")*(COUNTIF(Skills!$A$2:$A$999,Skills!$A$2:$A$999)>1)) -> 0
A118: 💡 Les lignes concernées sont signalées « ⚠ ID absent du roster » dans la colonne « Intégrité » de chaque onglet. Ajoutez la personne dans Active + Skills (avec son Lieu) pour résoudre.
A120: ▌ ABSENCES (Formation Initiale + Evermont)
A121: JOURS D'ABSENCE (total) | C121: SESSIONS AVEC ABSENCE | E121: JOURS — FORMATIONS EN COURS | G121: MOY. JOURS / SESSION TOUCHÉE | I121: JOURS — FORMATION INITIALE | K121: JOURS — Evermont
A122: =SUM('Formation Initiale'!$AB$2:$AB$999)+SUM(Evermont!$X$2:$X$1000) -> 10 | C122: =COUNTIF('Formation Initiale'!$AB$2:$AB$999,">0")+COUNTIF(Evermont!$X$2:$X$1000,">0") -> 7 | E122: =SUMIFS('Formation Initiale'!$AB$2:$AB$999,'Formation Initiale'!$R$2:$R$999,"En cours")+SUMIFS(Evermont!$X$2:$X$1000,Evermont!$Q$2:$Q$1000,"En cours") -> 1 | G122: =IFERROR((SUM('Formation Initiale'!$AB$2:$AB$999)+SUM(Evermont!$X$2:$X$1000))/(COUNTIF('Formation Initiale'!$AB$2:$AB$999,">0")+COUNTIF(Evermont!$X$2:$X$1000,">0")),0) -> 1.4285714 | I122: =SUM('Formation Initiale'!$AB$2:$AB$999) -> 5 | K122: =SUM(Evermont!$X$2:$X$1000) -> 5
A124: ▌ ABSENCES PAR SITE
A125: Site | B125: Jours d'absence | C125: % du total | D125: Sessions touchées
A126: 🇨🇦 Montréal | B126: =SUMIF('Formation Initiale'!$F$2:$F$999,"Montréal",'Formation Initiale'!$AB$2:$AB$999)+SUMIF(Evermont!$C$2:$C$1000,"Montréal",Evermont!$X$2:$X$1000) -> 7 | C126: =IFERROR((SUMIF('Formation Initiale'!$F$2:$F$999,"Montréal",'Formation Initiale'!$AB$2:$AB$999)+SUMIF(Evermont!$C$2:$C$1000,"Montréal",Evermont!$X$2:$X$1000))/(SUM('Formation Initiale'!$AB$2:$AB$999)+SUM(Evermont!$X$2:$X$1000)),0) -> 0.7 | D126: =COUNTIFS('Formation Initiale'!$F$2:$F$999,"Montréal",'Formation Initiale'!$AB$2:$AB$999,">0")+COUNTIFS(Evermont!$C$2:$C$1000,"Montréal",Evermont!$X$2:$X$1000,">0") -> 5
A127: 🇵🇹 Lisbonne | B127: =SUMIF('Formation Initiale'!$F$2:$F$999,"Lisbonne",'Formation Initiale'!$AB$2:$AB$999)+SUMIF(Evermont!$C$2:$C$1000,"Lisbonne",Evermont!$X$2:$X$1000) -> 3 | C127: =IFERROR((SUMIF('Formation Initiale'!$F$2:$F$999,"Lisbonne",'Formation Initiale'!$AB$2:$AB$999)+SUMIF(Evermont!$C$2:$C$1000,"Lisbonne",Evermont!$X$2:$X$1000))/(SUM('Formation Initiale'!$AB$2:$AB$999)+SUM(Evermont!$X$2:$X$1000)),0) -> 0.3 | D127: =COUNTIFS('Formation Initiale'!$F$2:$F$999,"Lisbonne",'Formation Initiale'!$AB$2:$AB$999,">0")+COUNTIFS(Evermont!$C$2:$C$1000,"Lisbonne",Evermont!$X$2:$X$1000,">0") -> 2
A128: 🌍 TOTAL | B128: =SUM('Formation Initiale'!$AB$2:$AB$999)+SUM(Evermont!$X$2:$X$1000) -> 10 | C128: =IFERROR(SUM(C125:C126),0) -> 0.7 | D128: =COUNTIF('Formation Initiale'!$AB$2:$AB$999,">0")+COUNTIF(Evermont!$X$2:$X$1000,">0") -> 7
A130: ▌ ABSENCES PAR TYPE DE FORMATION
A131: Formation | B131: Jours d'absence | C131: % du total | D131: Sessions touchées | E131: Moy. j./session
A132: Formation Initiale | B132: =SUM('Formation Initiale'!$AB$2:$AB$999) -> 5 | C132: =IFERROR(SUM('Formation Initiale'!$AB$2:$AB$999)/(SUM('Formation Initiale'!$AB$2:$AB$999)+SUM(Evermont!$X$2:$X$1000)),0) -> 0.5 | D132: =COUNTIF('Formation Initiale'!$AB$2:$AB$999,">0") -> 3 | E132: =IFERROR(SUM('Formation Initiale'!$AB$2:$AB$999)/COUNTIF('Formation Initiale'!$AB$2:$AB$999,">0"),0) -> 1.6666667
A133: Evermont | B133: =SUM(Evermont!$X$2:$X$1000) -> 5 | C133: =IFERROR(SUM(Evermont!$X$2:$X$1000)/(SUM('Formation Initiale'!$AB$2:$AB$999)+SUM(Evermont!$X$2:$X$1000)),0) -> 0.5 | D133: =COUNTIF(Evermont!$X$2:$X$1000,">0") -> 4 | E133: =IFERROR(SUM(Evermont!$X$2:$X$1000)/COUNTIF(Evermont!$X$2:$X$1000,">0"),0) -> 1.25
A134: TOTAL | B134: =SUM('Formation Initiale'!$AB$2:$AB$999)+SUM(Evermont!$X$2:$X$1000) -> 10 | C134: =IFERROR(SUM(C131:C132),0) -> 0.5 | D134: =COUNTIF('Formation Initiale'!$AB$2:$AB$999,">0")+COUNTIF(Evermont!$X$2:$X$1000,">0") -> 7 | E134: =IFERROR((SUM('Formation Initiale'!$AB$2:$AB$999)+SUM(Evermont!$X$2:$X$1000))/(COUNTIF('Formation Initiale'!$AB$2:$AB$999,">0")+COUNTIF(Evermont!$X$2:$X$1000,">0")),0) -> 1.4285714
...

Sheet Pipeline
A1: PIPELINE — AGENTS EN FORMATION ACTIVE | N1: =HYPERLINK("#Accueil!A1","⌂ Accueil") -> ⌂ Accueil
A2: Formation en cours / à venir / à planifier · Auto-rempli depuis Active + Skills, Formation Initiale, Agences & Après-vente, Evermont
A3: Filtres : | B3: Lieu | C3: Tous | D3: Statut | E3: Tous
A6: ="FORMATION INITIALE — Formation Initiale · "&$L$799 -> FORMATION INITIALE — Formation Initiale · 15 | F6: ="NOUVELLE COMPÉTENCE — Agences & Après-vente · "&($L$1199-$L$799) -> NOUVELLE COMPÉTENCE — Agences & Après-vente · 2 | K6: ="NOUVELLE COMPÉTENCE — Evermont · "&($L$1599-$L$1199) -> NOUVELLE COMPÉTENCE — Evermont · 2
A7: ID | B7: Agent | C7: Jrs rest. | D7: Statut | F7: ID | G7: Agent | H7: Jrs rest. | I7: Statut | K7: ID | L7: Agent | M7: Jrs rest. | N7: Statut
A8: =IFERROR(INDEX($A:$A,MATCH(1,$L$400:$L$799,0)+399),"") -> TR163 | B8: =IFERROR(INDEX($B:$B,MATCH(1,$L$400:$L$799,0)+399),"") -> Rhoea Thornshaw | C8: =IFERROR(INDEX($H:$H,MATCH(1,$L$400:$L$799,0)+399),"") -> 0 | D8: =IFERROR(INDEX($I:$I,MATCH(1,$L$400:$L$799,0)+399),"") -> En cours | F8: =IFERROR(INDEX($A:$A,MATCH($L$799+1,$L$800:$L$1199,0)+799),"") -> TR163 | G8: =IFERROR(INDEX($B:$B,MATCH($L$799+1,$L$800:$L$1199,0)+799),"") -> Rhoea Thornshaw | H8: =IFERROR(INDEX($H:$H,MATCH($L$799+1,$L$800:$L$1199,0)+799),"") | I8: =IFERROR(INDEX($I:$I,MATCH($L$799+1,$L$800:$L$1199,0)+799),"") -> En cours | K8: =IFERROR(INDEX($A:$A,MATCH($L$1199+1,$L$1200:$L$1599,0)+1199),"") -> TR140 | L8: =IFERROR(INDEX($B:$B,MATCH($L$1199+1,$L$1200:$L$1599,0)+1199),"") -> Kelen Toric | M8: =IFERROR(INDEX($H:$H,MATCH($L$1199+1,$L$1200:$L$1599,0)+1199),"") -> 0 | N8: =IFERROR(INDEX($I:$I,MATCH($L$1199+1,$L$1200:$L$1599,0)+1199),"") -> En cours
A9: =IFERROR(INDEX($A:$A,MATCH(2,$L$400:$L$799,0)+399),"") -> TR164 | B9: =IFERROR(INDEX($B:$B,MATCH(2,$L$400:$L$799,0)+399),"") -> Weson Pykefield | C9: =IFERROR(INDEX($H:$H,MATCH(2,$L$400:$L$799,0)+399),"") -> 6 | D9: =IFERROR(INDEX($I:$I,MATCH(2,$L$400:$L$799,0)+399),"") -> En cours | F9: =IFERROR(INDEX($A:$A,MATCH($L$799+2,$L$800:$L$1199,0)+799),"") -> TR164 | G9: =IFERROR(INDEX($B:$B,MATCH($L$799+2,$L$800:$L$1199,0)+799),"") -> Weson Pykefield | H9: =IFERROR(INDEX($H:$H,MATCH($L$799+2,$L$800:$L$1199,0)+799),"") | I9: =IFERROR(INDEX($I:$I,MATCH($L$799+2,$L$800:$L$1199,0)+799),"") -> En cours | K9: =IFERROR(INDEX($A:$A,MATCH($L$1199+2,$L$1200:$L$1599,0)+1199),"") -> TR164 | L9: =IFERROR(INDEX($B:$B,MATCH($L$1199+2,$L$1200:$L$1599,0)+1199),"") -> Weson Pykefield | M9: =IFERROR(INDEX($H:$H,MATCH($L$1199+2,$L$1200:$L$1599,0)+1199),"") | N9: =IFERROR(INDEX($I:$I,MATCH($L$1199+2,$L$1200:$L$1599,0)+1199),"") -> À venir
A10: =IFERROR(INDEX($A:$A,MATCH(3,$L$400:$L$799,0)+399),"") -> TR165 | B10: =IFERROR(INDEX($B:$B,MATCH(3,$L$400:$L$799,0)+399),"") -> Holtmont Rhous Dorum | C10: =IFERROR(INDEX($H:$H,MATCH(3,$L$400:$L$799,0)+399),"") -> 7 | D10: =IFERROR(INDEX($I:$I,MATCH(3,$L$400:$L$799,0)+399),"") -> En cours | F10: =IFERROR(INDEX($A:$A,MATCH($L$799+3,$L$800:$L$1199,0)+799),"") | G10: =IFERROR(INDEX($B:$B,MATCH($L$799+3,$L$800:$L$1199,0)+799),"") | H10: =IFERROR(INDEX($H:$H,MATCH($L$799+3,$L$800:$L$1199,0)+799),"") | I10: =IFERROR(INDEX($I:$I,MATCH($L$799+3,$L$800:$L$1199,0)+799),"") | K10: =IFERROR(INDEX($A:$A,MATCH($L$1199+3,$L$1200:$L$1599,0)+1199),"") | L10: =IFERROR(INDEX($B:$B,MATCH($L$1199+3,$L$1200:$L$1599,0)+1199),"") | M10: =IFERROR(INDEX($H:$H,MATCH($L$1199+3,$L$1200:$L$1599,0)+1199),"") | N10: =IFERROR(INDEX($I:$I,MATCH($L$1199+3,$L$1200:$L$1599,0)+1199),"")
A11: =IFERROR(INDEX($A:$A,MATCH(4,$L$400:$L$799,0)+399),"") -> TR166 | B11: =IFERROR(INDEX($B:$B,MATCH(4,$L$400:$L$799,0)+399),"") -> Norwood Torol Holtridge Ivermont | C11: =IFERROR(INDEX($H:$H,MATCH(4,$L$400:$L$799,0)+399),"") -> 7 | D11: =IFERROR(INDEX($I:$I,MATCH(4,$L$400:$L$799,0)+399),"") -> En cours | F11: =IFERROR(INDEX($A:$A,MATCH($L$799+4,$L$800:$L$1199,0)+799),"") | G11: =IFERROR(INDEX($B:$B,MATCH($L$799+4,$L$800:$L$1199,0)+799),"") | H11: =IFERROR(INDEX($H:$H,MATCH($L$799+4,$L$800:$L$1199,0)+799),"") | I11: =IFERROR(INDEX($I:$I,MATCH($L$799+4,$L$800:$L$1199,0)+799),"") | K11: =IFERROR(INDEX($A:$A,MATCH($L$1199+4,$L$1200:$L$1599,0)+1199),"") | L11: =IFERROR(INDEX($B:$B,MATCH($L$1199+4,$L$1200:$L$1599,0)+1199),"") | M11: =IFERROR(INDEX($H:$H,MATCH($L$1199+4,$L$1200:$L$1599,0)+1199),"") | N11: =IFERROR(INDEX($I:$I,MATCH($L$1199+4,$L$1200:$L$1599,0)+1199),"")
A12: =IFERROR(INDEX($A:$A,MATCH(5,$L$400:$L$799,0)+399),"") -> TR167 | B12: =IFERROR(INDEX($B:$B,MATCH(5,$L$400:$L$799,0)+399),"") -> Wesil Orinen | C12: =IFERROR(INDEX($H:$H,MATCH(5,$L$400:$L$799,0)+399),"") -> 7 | D12: =IFERROR(INDEX($I:$I,MATCH(5,$L$400:$L$799,0)+399),"") -> En cours | F12: =IFERROR(INDEX($A:$A,MATCH($L$799+5,$L$800:$L$1199,0)+799),"") | G12: =IFERROR(INDEX($B:$B,MATCH($L$799+5,$L$800:$L$1199,0)+799),"") | H12: =IFERROR(INDEX($H:$H,MATCH($L$799+5,$L$800:$L$1199,0)+799),"") | I12: =IFERROR(INDEX($I:$I,MATCH($L$799+5,$L$800:$L$1199,0)+799),"") | K12: =IFERROR(INDEX($A:$A,MATCH($L$1199+5,$L$1200:$L$1599,0)+1199),"") | L12: =IFERROR(INDEX($B:$B,MATCH($L$1199+5,$L$1200:$L$1599,0)+1199),"") | M12: =IFERROR(INDEX($H:$H,MATCH($L$1199+5,$L$1200:$L$1599,0)+1199),"") | N12: =IFERROR(INDEX($I:$I,MATCH($L$1199+5,$L$1200:$L$1599,0)+1199),"")
A13: =IFERROR(INDEX($A:$A,MATCH(6,$L$400:$L$799,0)+399),"") -> TR168 | B13: =IFERROR(INDEX($B:$B,MATCH(6,$L$400:$L$799,0)+399),"") -> Ashwood Zanay | C13: =IFERROR(INDEX($H:$H,MATCH(6,$L$400:$L$799,0)+399),"") -> 7 | D13: =IFERROR(INDEX($I:$I,MATCH(6,$L$400:$L$799,0)+399),"") -> En cours | F13: =IFERROR(INDEX($A:$A,MATCH($L$799+6,$L$800:$L$1199,0)+799),"") | G13: =IFERROR(INDEX($B:$B,MATCH($L$799+6,$L$800:$L$1199,0)+799),"") | H13: =IFERROR(INDEX($H:$H,MATCH($L$799+6,$L$800:$L$1199,0)+799),"") | I13: =IFERROR(INDEX($I:$I,MATCH($L$799+6,$L$800:$L$1199,0)+799),"") | K13: =IFERROR(INDEX($A:$A,MATCH($L$1199+6,$L$1200:$L$1599,0)+1199),"") | L13: =IFERROR(INDEX($B:$B,MATCH($L$1199+6,$L$1200:$L$1599,0)+1199),"") | M13: =IFERROR(INDEX($H:$H,MATCH($L$1199+6,$L$1200:$L$1599,0)+1199),"") | N13: =IFERROR(INDEX($I:$I,MATCH($L$1199+6,$L$1200:$L$1599,0)+1199),"")
A14: =IFERROR(INDEX($A:$A,MATCH(7,$L$400:$L$799,0)+399),"") -> TR169 | B14: =IFERROR(INDEX($B:$B,MATCH(7,$L$400:$L$799,0)+399),"") -> Dorel Wrenhaven | C14: =IFERROR(INDEX($H:$H,MATCH(7,$L$400:$L$799,0)+399),"") -> 7 | D14: =IFERROR(INDEX($I:$I,MATCH(7,$L$400:$L$799,0)+399),"") -> En cours | F14: =IFERROR(INDEX($A:$A,MATCH($L$799+7,$L$800:$L$1199,0)+799),"") | G14: =IFERROR(INDEX($B:$B,MATCH($L$799+7,$L$800:$L$1199,0)+799),"") | H14: =IFERROR(INDEX($H:$H,MATCH($L$799+7,$L$800:$L$1199,0)+799),"") | I14: =IFERROR(INDEX($I:$I,MATCH($L$799+7,$L$800:$L$1199,0)+799),"") | K14: =IFERROR(INDEX($A:$A,MATCH($L$1199+7,$L$1200:$L$1599,0)+1199),"") | L14: =IFERROR(INDEX($B:$B,MATCH($L$1199+7,$L$1200:$L$1599,0)+1199),"") | M14: =IFERROR(INDEX($H:$H,MATCH($L$1199+7,$L$1200:$L$1599,0)+1199),"") | N14: =IFERROR(INDEX($I:$I,MATCH($L$1199+7,$L$1200:$L$1599,0)+1199),"")
A15: =IFERROR(INDEX($A:$A,MATCH(8,$L$400:$L$799,0)+399),"") -> TR170 | B15: =IFERROR(INDEX($B:$B,MATCH(8,$L$400:$L$799,0)+399),"") -> Moril Wesus Wrenfield | C15: =IFERROR(INDEX($H:$H,MATCH(8,$L$400:$L$799,0)+399),"") -> 7 | D15: =IFERROR(INDEX($I:$I,MATCH(8,$L$400:$L$799,0)+399),"") -> En cours | F15: =IFERROR(INDEX($A:$A,MATCH($L$799+8,$L$800:$L$1199,0)+799),"") | G15: =IFERROR(INDEX($B:$B,MATCH($L$799+8,$L$800:$L$1199,0)+799),"") | H15: =IFERROR(INDEX($H:$H,MATCH($L$799+8,$L$800:$L$1199,0)+799),"") | I15: =IFERROR(INDEX($I:$I,MATCH($L$799+8,$L$800:$L$1199,0)+799),"") | K15: =IFERROR(INDEX($A:$A,MATCH($L$1199+8,$L$1200:$L$1599,0)+1199),"") | L15: =IFERROR(INDEX($B:$B,MATCH($L$1199+8,$L$1200:$L$1599,0)+1199),"") | M15: =IFERROR(INDEX($H:$H,MATCH($L$1199+8,$L$1200:$L$1599,0)+1199),"") | N15: =IFERROR(INDEX($I:$I,MATCH($L$1199+8,$L$1200:$L$1599,0)+1199),"")
A16: =IFERROR(INDEX($A:$A,MATCH(9,$L$400:$L$799,0)+399),"") -> TR171 | B16: =IFERROR(INDEX($B:$B,MATCH(9,$L$400:$L$799,0)+399),"") -> Zanan Pelol | C16: =IFERROR(INDEX($H:$H,MATCH(9,$L$400:$L$799,0)+399),"") -> 7 | D16: =IFERROR(INDEX($I:$I,MATCH(9,$L$400:$L$799,0)+399),"") -> En cours | F16: =IFERROR(INDEX($A:$A,MATCH($L$799+9,$L$800:$L$1199,0)+799),"") | G16: =IFERROR(INDEX($B:$B,MATCH($L$799+9,$L$800:$L$1199,0)+799),"") | H16: =IFERROR(INDEX($H:$H,MATCH($L$799+9,$L$800:$L$1199,0)+799),"") | I16: =IFERROR(INDEX($I:$I,MATCH($L$799+9,$L$800:$L$1199,0)+799),"") | K16: =IFERROR(INDEX($A:$A,MATCH($L$1199+9,$L$1200:$L$1599,0)+1199),"") | L16: =IFERROR(INDEX($B:$B,MATCH($L$1199+9,$L$1200:$L$1599,0)+1199),"") | M16: =IFERROR(INDEX($H:$H,MATCH($L$1199+9,$L$1200:$L$1599,0)+1199),"") | N16: =IFERROR(INDEX($I:$I,MATCH($L$1199+9,$L$1200:$L$1599,0)+1199),"")
A17: =IFERROR(INDEX($A:$A,MATCH(10,$L$400:$L$799,0)+399),"") -> TR172 | B17: =IFERROR(INDEX($B:$B,MATCH(10,$L$400:$L$799,0)+399),"") -> Ashmont Kendwood | C17: =IFERROR(INDEX($H:$H,MATCH(10,$L$400:$L$799,0)+399),"") -> 7 | D17: =IFERROR(INDEX($I:$I,MATCH(10,$L$400:$L$799,0)+399),"") -> En cours | F17: =IFERROR(INDEX($A:$A,MATCH($L$799+10,$L$800:$L$1199,0)+799),"") | G17: =IFERROR(INDEX($B:$B,MATCH($L$799+10,$L$800:$L$1199,0)+799),"") | H17: =IFERROR(INDEX($H:$H,MATCH($L$799+10,$L$800:$L$1199,0)+799),"") | I17: =IFERROR(INDEX($I:$I,MATCH($L$799+10,$L$800:$L$1199,0)+799),"") | K17: =IFERROR(INDEX($A:$A,MATCH($L$1199+10,$L$1200:$L$1599,0)+1199),"") | L17: =IFERROR(INDEX($B:$B,MATCH($L$1199+10,$L$1200:$L$1599,0)+1199),"") | M17: =IFERROR(INDEX($H:$H,MATCH($L$1199+10,$L$1200:$L$1599,0)+1199),"") | N17: =IFERROR(INDEX($I:$I,MATCH($L$1199+10,$L$1200:$L$1599,0)+1199),"")
A18: =IFERROR(INDEX($A:$A,MATCH(11,$L$400:$L$799,0)+399),"") -> TR173 | B18: =IFERROR(INDEX($B:$B,MATCH(11,$L$400:$L$799,0)+399),"") -> Marsmont Wesan | C18: =IFERROR(INDEX($H:$H,MATCH(11,$L$400:$L$799,0)+399),"") -> 7 | D18: =IFERROR(INDEX($I:$I,MATCH(11,$L$400:$L$799,0)+399),"") -> En cours | F18: =IFERROR(INDEX($A:$A,MATCH($L$799+11,$L$800:$L$1199,0)+799),"") | G18: =IFERROR(INDEX($B:$B,MATCH($L$799+11,$L$800:$L$1199,0)+799),"") | H18: =IFERROR(INDEX($H:$H,MATCH($L$799+11,$L$800:$L$1199,0)+799),"") | I18: =IFERROR(INDEX($I:$I,MATCH($L$799+11,$L$800:$L$1199,0)+799),"") | K18: =IFERROR(INDEX($A:$A,MATCH($L$1199+11,$L$1200:$L$1599,0)+1199),"") | L18: =IFERROR(INDEX($B:$B,MATCH($L$1199+11,$L$1200:$L$1599,0)+1199),"") | M18: =IFERROR(INDEX($H:$H,MATCH($L$1199+11,$L$1200:$L$1599,0)+1199),"") | N18: =IFERROR(INDEX($I:$I,MATCH($L$1199+11,$L$1200:$L$1599,0)+1199),"")
A19: =IFERROR(INDEX($A:$A,MATCH(12,$L$400:$L$799,0)+399),"") -> TR174 | B19: =IFERROR(INDEX($B:$B,MATCH(12,$L$400:$L$799,0)+399),"") -> Lumon Quillcroft Stelridge Gilus | C19: =IFERROR(INDEX($H:$H,MATCH(12,$L$400:$L$799,0)+399),"") -> 7 | D19: =IFERROR(INDEX($I:$I,MATCH(12,$L$400:$L$799,0)+399),"") -> En cours | F19: =IFERROR(INDEX($A:$A,MATCH($L$799+12,$L$800:$L$1199,0)+799),"") | G19: =IFERROR(INDEX($B:$B,MATCH($L$799+12,$L$800:$L$1199,0)+799),"") | H19: =IFERROR(INDEX($H:$H,MATCH($L$799+12,$L$800:$L$1199,0)+799),"") | I19: =IFERROR(INDEX($I:$I,MATCH($L$799+12,$L$800:$L$1199,0)+799),"") | K19: =IFERROR(INDEX($A:$A,MATCH($L$1199+12,$L$1200:$L$1599,0)+1199),"") | L19: =IFERROR(INDEX($B:$B,MATCH($L$1199+12,$L$1200:$L$1599,0)+1199),"") | M19: =IFERROR(INDEX($H:$H,MATCH($L$1199+12,$L$1200:$L$1599,0)+1199),"") | N19: =IFERROR(INDEX($I:$I,MATCH($L$1199+12,$L$1200:$L$1599,0)+1199),"")
A20: =IFERROR(INDEX($A:$A,MATCH(13,$L$400:$L$799,0)+399),"") -> TR175 | B20: =IFERROR(INDEX($B:$B,MATCH(13,$L$400:$L$799,0)+399),"") -> Gilor Stelbrook | C20: =IFERROR(INDEX($H:$H,MATCH(13,$L$400:$L$799,0)+399),"") -> 7 | D20: =IFERROR(INDEX($I:$I,MATCH(13,$L$400:$L$799,0)+399),"") -> En cours | F20: =IFERROR(INDEX($A:$A,MATCH($L$799+13,$L$800:$L$1199,0)+799),"") | G20: =IFERROR(INDEX($B:$B,MATCH($L$799+13,$L$800:$L$1199,0)+799),"") | H20: =IFERROR(INDEX($H:$H,MATCH($L$799+13,$L$800:$L$1199,0)+799),"") | I20: =IFERROR(INDEX($I:$I,MATCH($L$799+13,$L$800:$L$1199,0)+799),"") | K20: =IFERROR(INDEX($A:$A,MATCH($L$1199+13,$L$1200:$L$1599,0)+1199),"") | L20: =IFERROR(INDEX($B:$B,MATCH($L$1199+13,$L$1200:$L$1599,0)+1199),"") | M20: =IFERROR(INDEX($H:$H,MATCH($L$1199+13,$L$1200:$L$1599,0)+1199),"") | N20: =IFERROR(INDEX($I:$I,MATCH($L$1199+13,$L$1200:$L$1599,0)+1199),"")
A21: =IFERROR(INDEX($A:$A,MATCH(14,$L$400:$L$799,0)+399),"") -> TR176 | B21: =IFERROR(INDEX($B:$B,MATCH(14,$L$400:$L$799,0)+399),"") -> Rhoic Iverstone | C21: =IFERROR(INDEX($H:$H,MATCH(14,$L$400:$L$799,0)+399),"") -> 7 | D21: =IFERROR(INDEX($I:$I,MATCH(14,$L$400:$L$799,0)+399),"") -> En cours | F21: =IFERROR(INDEX($A:$A,MATCH($L$799+14,$L$800:$L$1199,0)+799),"") | G21: =IFERROR(INDEX($B:$B,MATCH($L$799+14,$L$800:$L$1199,0)+799),"") | H21: =IFERROR(INDEX($H:$H,MATCH($L$799+14,$L$800:$L$1199,0)+799),"") | I21: =IFERROR(INDEX($I:$I,MATCH($L$799+14,$L$800:$L$1199,0)+799),"") | K21: =IFERROR(INDEX($A:$A,MATCH($L$1199+14,$L$1200:$L$1599,0)+1199),"") | L21: =IFERROR(INDEX($B:$B,MATCH($L$1199+14,$L$1200:$L$1599,0)+1199),"") | M21: =IFERROR(INDEX($H:$H,MATCH($L$1199+14,$L$1200:$L$1599,0)+1199),"") | N21: =IFERROR(INDEX($I:$I,MATCH($L$1199+14,$L$1200:$L$1599,0)+1199),"")
A22: =IFERROR(INDEX($A:$A,MATCH(15,$L$400:$L$799,0)+399),"") -> TR177 | B22: =IFERROR(INDEX($B:$B,MATCH(15,$L$400:$L$799,0)+399),"") -> Corrfield Haxay Quenen | C22: =IFERROR(INDEX($H:$H,MATCH(15,$L$400:$L$799,0)+399),"") -> 7 | D22: =IFERROR(INDEX($I:$I,MATCH(15,$L$400:$L$799,0)+399),"") -> En cours | F22: =IFERROR(INDEX($A:$A,MATCH($L$799+15,$L$800:$L$1199,0)+799),"") | G22: =IFERROR(INDEX($B:$B,MATCH($L$799+15,$L$800:$L$1199,0)+799),"") | H22: =IFERROR(INDEX($H:$H,MATCH($L$799+15,$L$800:$L$1199,0)+799),"") | I22: =IFERROR(INDEX($I:$I,MATCH($L$799+15,$L$800:$L$1199,0)+799),"") | K22: =IFERROR(INDEX($A:$A,MATCH($L$1199+15,$L$1200:$L$1599,0)+1199),"") | L22: =IFERROR(INDEX($B:$B,MATCH($L$1199+15,$L$1200:$L$1599,0)+1199),"") | M22: =IFERROR(INDEX($H:$H,MATCH($L$1199+15,$L$1200:$L$1599,0)+1199),"") | N22: =IFERROR(INDEX($I:$I,MATCH($L$1199+15,$L$1200:$L$1599,0)+1199),"")
A23: =IFERROR(INDEX($A:$A,MATCH(16,$L$400:$L$799,0)+399),"") | B23: =IFERROR(INDEX($B:$B,MATCH(16,$L$400:$L$799,0)+399),"") | C23: =IFERROR(INDEX($H:$H,MATCH(16,$L$400:$L$799,0)+399),"") | D23: =IFERROR(INDEX($I:$I,MATCH(16,$L$400:$L$799,0)+399),"") | F23: =IFERROR(INDEX($A:$A,MATCH($L$799+16,$L$800:$L$1199,0)+799),"") | G23: =IFERROR(INDEX($B:$B,MATCH($L$799+16,$L$800:$L$1199,0)+799),"") | H23: =IFERROR(INDEX($H:$H,MATCH($L$799+16,$L$800:$L$1199,0)+799),"") | I23: =IFERROR(INDEX($I:$I,MATCH($L$799+16,$L$800:$L$1199,0)+799),"") | K23: =IFERROR(INDEX($A:$A,MATCH($L$1199+16,$L$1200:$L$1599,0)+1199),"") | L23: =IFERROR(INDEX($B:$B,MATCH($L$1199+16,$L$1200:$L$1599,0)+1199),"") | M23: =IFERROR(INDEX($H:$H,MATCH($L$1199+16,$L$1200:$L$1599,0)+1199),"") | N23: =IFERROR(INDEX($I:$I,MATCH($L$1199+16,$L$1200:$L$1599,0)+1199),"")
A24: =IFERROR(INDEX($A:$A,MATCH(17,$L$400:$L$799,0)+399),"") | B24: =IFERROR(INDEX($B:$B,MATCH(17,$L$400:$L$799,0)+399),"") | C24: =IFERROR(INDEX($H:$H,MATCH(17,$L$400:$L$799,0)+399),"") | D24: =IFERROR(INDEX($I:$I,MATCH(17,$L$400:$L$799,0)+399),"") | F24: =IFERROR(INDEX($A:$A,MATCH($L$799+17,$L$800:$L$1199,0)+799),"") | G24: =IFERROR(INDEX($B:$B,MATCH($L$799+17,$L$800:$L$1199,0)+799),"") | H24: =IFERROR(INDEX($H:$H,MATCH($L$799+17,$L$800:$L$1199,0)+799),"") | I24: =IFERROR(INDEX($I:$I,MATCH($L$799+17,$L$800:$L$1199,0)+799),"") | K24: =IFERROR(INDEX($A:$A,MATCH($L$1199+17,$L$1200:$L$1599,0)+1199),"") | L24: =IFERROR(INDEX($B:$B,MATCH($L$1199+17,$L$1200:$L$1599,0)+1199),"") | M24: =IFERROR(INDEX($H:$H,MATCH($L$1199+17,$L$1200:$L$1599,0)+1199),"") | N24: =IFERROR(INDEX($I:$I,MATCH($L$1199+17,$L$1200:$L$1599,0)+1199),"")
A25: =IFERROR(INDEX($A:$A,MATCH(18,$L$400:$L$799,0)+399),"") | B25: =IFERROR(INDEX($B:$B,MATCH(18,$L$400:$L$799,0)+399),"") | C25: =IFERROR(INDEX($H:$H,MATCH(18,$L$400:$L$799,0)+399),"") | D25: =IFERROR(INDEX($I:$I,MATCH(18,$L$400:$L$799,0)+399),"") | F25: =IFERROR(INDEX($A:$A,MATCH($L$799+18,$L$800:$L$1199,0)+799),"") | G25: =IFERROR(INDEX($B:$B,MATCH($L$799+18,$L$800:$L$1199,0)+799),"") | H25: =IFERROR(INDEX($H:$H,MATCH($L$799+18,$L$800:$L$1199,0)+799),"") | I25: =IFERROR(INDEX($I:$I,MATCH($L$799+18,$L$800:$L$1199,0)+799),"") | K25: =IFERROR(INDEX($A:$A,MATCH($L$1199+18,$L$1200:$L$1599,0)+1199),"") | L25: =IFERROR(INDEX($B:$B,MATCH($L$1199+18,$L$1200:$L$1599,0)+1199),"") | M25: =IFERROR(INDEX($H:$H,MATCH($L$1199+18,$L$1200:$L$1599,0)+1199),"") | N25: =IFERROR(INDEX($I:$I,MATCH($L$1199+18,$L$1200:$L$1599,0)+1199),"")
A26: =IFERROR(INDEX($A:$A,MATCH(19,$L$400:$L$799,0)+399),"") | B26: =IFERROR(INDEX($B:$B,MATCH(19,$L$400:$L$799,0)+399),"") | C26: =IFERROR(INDEX($H:$H,MATCH(19,$L$400:$L$799,0)+399),"") | D26: =IFERROR(INDEX($I:$I,MATCH(19,$L$400:$L$799,0)+399),"") | F26: =IFERROR(INDEX($A:$A,MATCH($L$799+19,$L$800:$L$1199,0)+799),"") | G26: =IFERROR(INDEX($B:$B,MATCH($L$799+19,$L$800:$L$1199,0)+799),"") | H26: =IFERROR(INDEX($H:$H,MATCH($L$799+19,$L$800:$L$1199,0)+799),"") | I26: =IFERROR(INDEX($I:$I,MATCH($L$799+19,$L$800:$L$1199,0)+799),"") | K26: =IFERROR(INDEX($A:$A,MATCH($L$1199+19,$L$1200:$L$1599,0)+1199),"") | L26: =IFERROR(INDEX($B:$B,MATCH($L$1199+19,$L$1200:$L$1599,0)+1199),"") | M26: =IFERROR(INDEX($H:$H,MATCH($L$1199+19,$L$1200:$L$1599,0)+1199),"") | N26: =IFERROR(INDEX($I:$I,MATCH($L$1199+19,$L$1200:$L$1599,0)+1199),"")
A27: =IFERROR(INDEX($A:$A,MATCH(20,$L$400:$L$799,0)+399),"") | B27: =IFERROR(INDEX($B:$B,MATCH(20,$L$400:$L$799,0)+399),"") | C27: =IFERROR(INDEX($H:$H,MATCH(20,$L$400:$L$799,0)+399),"") | D27: =IFERROR(INDEX($I:$I,MATCH(20,$L$400:$L$799,0)+399),"") | F27: =IFERROR(INDEX($A:$A,MATCH($L$799+20,$L$800:$L$1199,0)+799),"") | G27: =IFERROR(INDEX($B:$B,MATCH($L$799+20,$L$800:$L$1199,0)+799),"") | H27: =IFERROR(INDEX($H:$H,MATCH($L$799+20,$L$800:$L$1199,0)+799),"") | I27: =IFERROR(INDEX($I:$I,MATCH($L$799+20,$L$800:$L$1199,0)+799),"") | K27: =IFERROR(INDEX($A:$A,MATCH($L$1199+20,$L$1200:$L$1599,0)+1199),"") | L27: =IFERROR(INDEX($B:$B,MATCH($L$1199+20,$L$1200:$L$1599,0)+1199),"") | M27: =IFERROR(INDEX($H:$H,MATCH($L$1199+20,$L$1200:$L$1599,0)+1199),"") | N27: =IFERROR(INDEX($I:$I,MATCH($L$1199+20,$L$1200:$L$1599,0)+1199),"")
A28: =IFERROR(INDEX($A:$A,MATCH(21,$L$400:$L$799,0)+399),"") | B28: =IFERROR(INDEX($B:$B,MATCH(21,$L$400:$L$799,0)+399),"") | C28: =IFERROR(INDEX($H:$H,MATCH(21,$L$400:$L$799,0)+399),"") | D28: =IFERROR(INDEX($I:$I,MATCH(21,$L$400:$L$799,0)+399),"") | F28: =IFERROR(INDEX($A:$A,MATCH($L$799+21,$L$800:$L$1199,0)+799),"") | G28: =IFERROR(INDEX($B:$B,MATCH($L$799+21,$L$800:$L$1199,0)+799),"") | H28: =IFERROR(INDEX($H:$H,MATCH($L$799+21,$L$800:$L$1199,0)+799),"") | I28: =IFERROR(INDEX($I:$I,MATCH($L$799+21,$L$800:$L$1199,0)+799),"") | K28: =IFERROR(INDEX($A:$A,MATCH($L$1199+21,$L$1200:$L$1599,0)+1199),"") | L28: =IFERROR(INDEX($B:$B,MATCH($L$1199+21,$L$1200:$L$1599,0)+1199),"") | M28: =IFERROR(INDEX($H:$H,MATCH($L$1199+21,$L$1200:$L$1599,0)+1199),"") | N28: =IFERROR(INDEX($I:$I,MATCH($L$1199+21,$L$1200:$L$1599,0)+1199),"")
A29: =IFERROR(INDEX($A:$A,MATCH(22,$L$400:$L$799,0)+399),"") | B29: =IFERROR(INDEX($B:$B,MATCH(22,$L$400:$L$799,0)+399),"") | C29: =IFERROR(INDEX($H:$H,MATCH(22,$L$400:$L$799,0)+399),"") | D29: =IFERROR(INDEX($I:$I,MATCH(22,$L$400:$L$799,0)+399),"") | F29: =IFERROR(INDEX($A:$A,MATCH($L$799+22,$L$800:$L$1199,0)+799),"") | G29: =IFERROR(INDEX($B:$B,MATCH($L$799+22,$L$800:$L$1199,0)+799),"") | H29: =IFERROR(INDEX($H:$H,MATCH($L$799+22,$L$800:$L$1199,0)+799),"") | I29: =IFERROR(INDEX($I:$I,MATCH($L$799+22,$L$800:$L$1199,0)+799),"") | K29: =IFERROR(INDEX($A:$A,MATCH($L$1199+22,$L$1200:$L$1599,0)+1199),"") | L29: =IFERROR(INDEX($B:$B,MATCH($L$1199+22,$L$1200:$L$1599,0)+1199),"") | M29: =IFERROR(INDEX($H:$H,MATCH($L$1199+22,$L$1200:$L$1599,0)+1199),"") | N29: =IFERROR(INDEX($I:$I,MATCH($L$1199+22,$L$1200:$L$1599,0)+1199),"")
A30: =IFERROR(INDEX($A:$A,MATCH(23,$L$400:$L$799,0)+399),"") | B30: =IFERROR(INDEX($B:$B,MATCH(23,$L$400:$L$799,0)+399),"") | C30: =IFERROR(INDEX($H:$H,MATCH(23,$L$400:$L$799,0)+399),"") | D30: =IFERROR(INDEX($I:$I,MATCH(23,$L$400:$L$799,0)+399),"") | F30: =IFERROR(INDEX($A:$A,MATCH($L$799+23,$L$800:$L$1199,0)+799),"") | G30: =IFERROR(INDEX($B:$B,MATCH($L$799+23,$L$800:$L$1199,0)+799),"") | H30: =IFERROR(INDEX($H:$H,MATCH($L$799+23,$L$800:$L$1199,0)+799),"") | I30: =IFERROR(INDEX($I:$I,MATCH($L$799+23,$L$800:$L$1199,0)+799),"") | K30: =IFERROR(INDEX($A:$A,MATCH($L$1199+23,$L$1200:$L$1599,0)+1199),"") | L30: =IFERROR(INDEX($B:$B,MATCH($L$1199+23,$L$1200:$L$1599,0)+1199),"") | M30: =IFERROR(INDEX($H:$H,MATCH($L$1199+23,$L$1200:$L$1599,0)+1199),"") | N30: =IFERROR(INDEX($I:$I,MATCH($L$1199+23,$L$1200:$L$1599,0)+1199),"")
A31: =IFERROR(INDEX($A:$A,MATCH(24,$L$400:$L$799,0)+399),"") | B31: =IFERROR(INDEX($B:$B,MATCH(24,$L$400:$L$799,0)+399),"") | C31: =IFERROR(INDEX($H:$H,MATCH(24,$L$400:$L$799,0)+399),"") | D31: =IFERROR(INDEX($I:$I,MATCH(24,$L$400:$L$799,0)+399),"") | F31: =IFERROR(INDEX($A:$A,MATCH($L$799+24,$L$800:$L$1199,0)+799),"") | G31: =IFERROR(INDEX($B:$B,MATCH($L$799+24,$L$800:$L$1199,0)+799),"") | H31: =IFERROR(INDEX($H:$H,MATCH($L$799+24,$L$800:$L$1199,0)+799),"") | I31: =IFERROR(INDEX($I:$I,MATCH($L$799+24,$L$800:$L$1199,0)+799),"") | K31: =IFERROR(INDEX($A:$A,MATCH($L$1199+24,$L$1200:$L$1599,0)+1199),"") | L31: =IFERROR(INDEX($B:$B,MATCH($L$1199+24,$L$1200:$L$1599,0)+1199),"") | M31: =IFERROR(INDEX($H:$H,MATCH($L$1199+24,$L$1200:$L$1599,0)+1199),"") | N31: =IFERROR(INDEX($I:$I,MATCH($L$1199+24,$L$1200:$L$1599,0)+1199),"")
A399: HELPER (do not edit)
A400: =IF('Formation Initiale'!$A2="","",'Formation Initiale'!$A2) -> TR129 | B400: =IF($A400="","",'Formation Initiale'!$E2) -> Haxil Dellhaven | C400: =IF($A400="","",'Formation Initiale'!$F2) -> Lisbonne | D400: =IF($A400="","",IF('Formation Initiale'!$F2="Lisbonne","B2C (Initiale)","B2C+B2B (Initiale)")) -> B2C (Initiale) | E400: =IF($A400="","",'Formation Initiale'!$B2) -> OS1 | F400: =IF($A400="","",'Formation Initiale'!$G2) -> 46006 | G400: =IF($A400="","",'Formation Initiale'!$H2) -> 46017 | H400: =IF($A400="","",'Formation Initiale'!$L2) -> 0 | I400: =IF($A400="","",'Formation Initiale'!$R2) -> Terminé | K400: =IF(A400="",0,IF(IFERROR(VLOOKUP(A400,Skills!$A:$M,13,FALSE()),"")="COS",0,IF(OR(I400="En cours",I400="À venir",I400="À planifier"),IF(AND(OR($C$3="Tous",$C$3="",C400=$C$3),OR($E$3="Tous",$E$3="",I400=$E$3)),1,0),0))) -> 0 | L400: =K400 -> 0
A401: =IF('Formation Initiale'!$A3="","",'Formation Initiale'!$A3) -> TR099 | B401: =IF($A401="","",'Formation Initiale'!$E3) -> Haxay Corrfield Dellstone | C401: =IF($A401="","",'Formation Initiale'!$F3) -> Lisbonne | D401: =IF($A401="","",IF('Formation Initiale'!$F3="Lisbonne","B2C (Initiale)","B2C+B2B (Initiale)")) -> B2C (Initiale) | E401: =IF($A401="","",'Formation Initiale'!$B3) -> OS1 | F401: =IF($A401="","",'Formation Initiale'!$G3) -> 46006 | G401: =IF($A401="","",'Formation Initiale'!$H3) -> 46017 | H401: =IF($A401="","",'Formation Initiale'!$L3) -> 0 | I401: =IF($A401="","",'Formation Initiale'!$R3) -> Terminé | K401: =IF(A401="",0,IF(IFERROR(VLOOKUP(A401,Skills!$A:$M,13,FALSE()),"")="COS",0,IF(OR(I401="En cours",I401="À venir",I401="À planifier"),IF(AND(OR($C$3="Tous",$C$3="",C401=$C$3),OR($E$3="Tous",$E$3="",I401=$E$3)),1,0),0))) -> 0 | L401: =L400+K401 -> 0
A402: =IF('Formation Initiale'!$A4="","",'Formation Initiale'!$A4) -> TR021 | B402: =IF($A402="","",'Formation Initiale'!$E4) -> Nevus Kelir | C402: =IF($A402="","",'Formation Initiale'!$F4) -> Lisbonne | D402: =IF($A402="","",IF('Formation Initiale'!$F4="Lisbonne","B2C (Initiale)","B2C+B2B (Initiale)")) -> B2C (Initiale) | E402: =IF($A402="","",'Formation Initiale'!$B4) -> OS1 | F402: =IF($A402="","",'Formation Initiale'!$G4) -> 46006 | G402: =IF($A402="","",'Formation Initiale'!$H4) -> 46017 | H402: =IF($A402="","",'Formation Initiale'!$L4) -> 0 | I402: =IF($A402="","",'Formation Initiale'!$R4) -> Terminé | K402: =IF(A402="",0,IF(IFERROR(VLOOKUP(A402,Skills!$A:$M,13,FALSE()),"")="COS",0,IF(OR(I402="En cours",I402="À venir",I402="À planifier"),IF(AND(OR($C$3="Tous",$C$3="",C402=$C$3),OR($E$3="Tous",$E$3="",I402=$E$3)),1,0),0))) -> 0 | L402: =L401+K402 -> 0
A403: =IF('Formation Initiale'!$A5="","",'Formation Initiale'!$A5) -> TR018 | B403: =IF($A403="","",'Formation Initiale'!$E5) -> Granbrook Yoril Corrfield | C403: =IF($A403="","",'Formation Initiale'!$F5) -> Lisbonne | D403: =IF($A403="","",IF('Formation Initiale'!$F5="Lisbonne","B2C (Initiale)","B2C+B2B (Initiale)")) -> B2C (Initiale) | E403: =IF($A403="","",'Formation Initiale'!$B5) -> OS1 | F403: =IF($A403="","",'Formation Initiale'!$G5) -> 46006 | G403: =IF($A403="","",'Formation Initiale'!$H5) -> 46017 | H403: =IF($A403="","",'Formation Initiale'!$L5) -> 0 | I403: =IF($A403="","",'Formation Initiale'!$R5) -> Terminé | K403: =IF(A403="",0,IF(IFERROR(VLOOKUP(A403,Skills!$A:$M,13,FALSE()),"")="COS",0,IF(OR(I403="En cours",I403="À venir",I403="À planifier"),IF(AND(OR($C$3="Tous",$C$3="",C403=$C$3),OR($E$3="Tous",$E$3="",I403=$E$3)),1,0),0))) -> 0 | L403: =L402+K403 -> 0
A404: =IF('Formation Initiale'!$A6="","",'Formation Initiale'!$A6) -> TR093 | B404: =IF($A404="","",'Formation Initiale'!$E6) -> Holtshaw Haxor | C404: =IF($A404="","",'Formation Initiale'!$F6) -> Lisbonne | D404: =IF($A404="","",IF('Formation Initiale'!$F6="Lisbonne","B2C (Initiale)","B2C+B2B (Initiale)")) -> B2C (Initiale) | E404: =IF($A404="","",'Formation Initiale'!$B6) -> OS1 | F404: =IF($A404="","",'Formation Initiale'!$G6) -> 46006 | G404: =IF($A404="","",'Formation Initiale'!$H6) -> 46017 | H404: =IF($A404="","",'Formation Initiale'!$L6) -> 0 | I404: =IF($A404="","",'Formation Initiale'!$R6) -> Terminé | K404: =IF(A404="",0,IF(IFERROR(VLOOKUP(A404,Skills!$A:$M,13,FALSE()),"")="COS",0,IF(OR(I404="En cours",I404="À venir",I404="À planifier"),IF(AND(OR($C$3="Tous",$C$3="",C404=$C$3),OR($E$3="Tous",$E$3="",I404=$E$3)),1,0),0))) -> 0 | L404: =L403+K404 -> 0
A405: =IF('Formation Initiale'!$A7="","",'Formation Initiale'!$A7) -> TR100 | B405: =IF($A405="","",'Formation Initiale'!$E7) -> Ashdale Valedale | C405: =IF($A405="","",'Formation Initiale'!$F7) -> Lisbonne | D405: =IF($A405="","",IF('Formation Initiale'!$F7="Lisbonne","B2C (Initiale)","B2C+B2B (Initiale)")) -> B2C (Initiale) | E405: =IF($A405="","",'Formation Initiale'!$B7) -> OS1 | F405: =IF($A405="","",'Formation Initiale'!$G7) -> 46006 | G405: =IF($A405="","",'Formation Initiale'!$H7) -> 46017 | H405: =IF($A405="","",'Formation Initiale'!$L7) -> 0 | I405: =IF($A405="","",'Formation Initiale'!$R7) -> Terminé | K405: =IF(A405="",0,IF(IFERROR(VLOOKUP(A405,Skills!$A:$M,13,FALSE()),"")="COS",0,IF(OR(I405="En cours",I405="À venir",I405="À planifier"),IF(AND(OR($C$3="Tous",$C$3="",C405=$C$3),OR($E$3="Tous",$E$3="",I405=$E$3)),1,0),0))) -> 0 | L405: =L404+K405 -> 0
A406: =IF('Formation Initiale'!$A8="","",'Formation Initiale'!$A8) -> TR051 | B406: =IF($A406="","",'Formation Initiale'!$E8) -> Ashcroft Pelan | C406: =IF($A406="","",'Formation Initiale'!$F8) -> Lisbonne | D406: =IF($A406="","",IF('Formation Initiale'!$F8="Lisbonne","B2C (Initiale)","B2C+B2B (Initiale)")) -> B2C (Initiale) | E406: =IF($A406="","",'Formation Initiale'!$B8) -> OS1 | F406: =IF($A406="","",'Formation Initiale'!$G8) -> 46006 | G406: =IF($A406="","",'Formation Initiale'!$H8) -> 46017 | H406: =IF($A406="","",'Formation Initiale'!$L8) -> 0 | I406: =IF($A406="","",'Formation Initiale'!$R8) -> Terminé | K406: =IF(A406="",0,IF(IFERROR(VLOOKUP(A406,Skills!$A:$M,13,FALSE()),"")="COS",0,IF(OR(I406="En cours",I406="À venir",I406="À planifier"),IF(AND(OR($C$3="Tous",$C$3="",C406=$C$3),OR($E$3="Tous",$E$3="",I406=$E$3)),1,0),0))) -> 0 | L406: =L405+K406 -> 0
A407: =IF('Formation Initiale'!$A9="","",'Formation Initiale'!$A9) -> TR122 | B407: =IF($A407="","",'Formation Initiale'!$E9) -> Wrendale Wesum | C407: =IF($A407="","",'Formation Initiale'!$F9) -> Lisbonne | D407: =IF($A407="","",IF('Formation Initiale'!$F9="Lisbonne","B2C (Initiale)","B2C+B2B (Initiale)")) -> B2C (Initiale) | E407: =IF($A407="","",'Formation Initiale'!$B9) -> OS1 | F407: =IF($A407="","",'Formation Initiale'!$G9) -> 46006 | G407: =IF($A407="","",'Formation Initiale'!$H9) -> 46017 | H407: =IF($A407="","",'Formation Initiale'!$L9) -> 0 | I407: =IF($A407="","",'Formation Initiale'!$R9) -> Terminé | K407: =IF(A407="",0,IF(IFERROR(VLOOKUP(A407,Skills!$A:$M,13,FALSE()),"")="COS",0,IF(OR(I407="En cours",I407="À venir",I407="À planifier"),IF(AND(OR($C$3="Tous",$C$3="",C407=$C$3),OR($E$3="Tous",$E$3="",I407=$E$3)),1,0),0))) -> 0 | L407: =L406+K407 -> 0
A408: =IF('Formation Initiale'!$A10="","",'Formation Initiale'!$A10) -> TR073 | B408: =IF($A408="","",'Formation Initiale'!$E10) -> Brammont Holtvale | C408: =IF($A408="","",'Formation Initiale'!$F10) -> Lisbonne | D408: =IF($A408="","",IF('Formation Initiale'!$F10="Lisbonne","B2C (Initiale)","B2C+B2B (Initiale)")) -> B2C (Initiale) | E408: =IF($A408="","",'Formation Initiale'!$B10) -> OS1 | F408: =IF($A408="","",'Formation Initiale'!$G10) -> 46006 | G408: =IF($A408="","",'Formation Initiale'!$H10) -> 46017 | H408: =IF($A408="","",'Formation Initiale'!$L10) -> 0 | I408: =IF($A408="","",'Formation Initiale'!$R10) -> Terminé | K408: =IF(A408="",0,IF(IFERROR(VLOOKUP(A408,Skills!$A:$M,13,FALSE()),"")="COS",0,IF(OR(I408="En cours",I408="À venir",I408="À planifier"),IF(AND(OR($C$3="Tous",$C$3="",C408=$C$3),OR($E$3="Tous",$E$3="",I408=$E$3)),1,0),0))) -> 0 | L408: =L407+K408 -> 0
A409: =IF('Formation Initiale'!$A11="","",'Formation Initiale'!$A11) -> TR034 | B409: =IF($A409="","",'Formation Initiale'!$E11) -> Toril Rhoys | C409: =IF($A409="","",'Formation Initiale'!$F11) -> Lisbonne | D409: =IF($A409="","",IF('Formation Initiale'!$F11="Lisbonne","B2C (Initiale)","B2C+B2B (Initiale)")) -> B2C (Initiale) | E409: =IF($A409="","",'Formation Initiale'!$B11) -> OS1 | F409: =IF($A409="","",'Formation Initiale'!$G11) -> 46006 | G409: =IF($A409="","",'Formation Initiale'!$H11) -> 46017 | H409: =IF($A409="","",'Formation Initiale'!$L11) -> 0 | I409: =IF($A409="","",'Formation Initiale'!$R11) -> Terminé | K409: =IF(A409="",0,IF(IFERROR(VLOOKUP(A409,Skills!$A:$M,13,FALSE()),"")="COS",0,IF(OR(I409="En cours",I409="À venir",I409="À planifier"),IF(AND(OR($C$3="Tous",$C$3="",C409=$C$3),OR($E$3="Tous",$E$3="",I409=$E$3)),1,0),0))) -> 0 | L409: =L408+K409 -> 0
A410: =IF('Formation Initiale'!$A12="","",'Formation Initiale'!$A12) -> TR008 | B410: =IF($A410="","",'Formation Initiale'!$E12) -> Corrfield Doric Ulmel | C410: =IF($A410="","",'Formation Initiale'!$F12) -> Lisbonne | D410: =IF($A410="","",IF('Formation Initiale'!$F12="Lisbonne","B2C (Initiale)","B2C+B2B (Initiale)")) -> B2C (Initiale) | E410: =IF($A410="","",'Formation Initiale'!$B12) -> OS1 | F410: =IF($A410="","",'Formation Initiale'!$G12) -> 46006 | G410: =IF($A410="","",'Formation Initiale'!$H12) -> 46017 | H410: =IF($A410="","",'Formation Initiale'!$L12) -> 0 | I410: =IF($A410="","",'Formation Initiale'!$R12) -> Terminé | K410: =IF(A410="",0,IF(IFERROR(VLOOKUP(A410,Skills!$A:$M,13,FALSE()),"")="COS",0,IF(OR(I410="En cours",I410="À venir",I410="À planifier"),IF(AND(OR($C$3="Tous",$C$3="",C410=$C$3),OR($E$3="Tous",$E$3="",I410=$E$3)),1,0),0))) -> 0 | L410: =L409+K410 -> 0
A411: =IF('Formation Initiale'!$A13="","",'Formation Initiale'!$A13) -> TR085 | B411: =IF($A411="","",'Formation Initiale'!$E13) -> Larkshaw Moric | C411: =IF($A411="","",'Formation Initiale'!$F13) -> Lisbonne | D411: =IF($A411="","",IF('Formation Initiale'!$F13="Lisbonne","B2C (Initiale)","B2C+B2B (Initiale)")) -> B2C (Initiale) | E411: =IF($A411="","",'Formation Initiale'!$B13) -> OS1 | F411: =IF($A411="","",'Formation Initiale'!$G13) -> 46006 | G411: =IF($A411="","",'Formation Initiale'!$H13) -> 46017 | H411: =IF($A411="","",'Formation Initiale'!$L13) -> 0 | I411: =IF($A411="","",'Formation Initiale'!$R13) -> Terminé | K411: =IF(A411="",0,IF(IFERROR(VLOOKUP(A411,Skills!$A:$M,13,FALSE()),"")="COS",0,IF(OR(I411="En cours",I411="À venir",I411="À planifier"),IF(AND(OR($C$3="Tous",$C$3="",C411=$C$3),OR($E$3="Tous",$E$3="",I411=$E$3)),1,0),0))) -> 0 | L411: =L410+K411 -> 0
A412: =IF('Formation Initiale'!$A14="","",'Formation Initiale'!$A14) -> TR054 | B412: =IF($A412="","",'Formation Initiale'!$E14) -> Pykewood Stelshaw Doric | C412: =IF($A412="","",'Formation Initiale'!$F14) -> Lisbonne | D412: =IF($A412="","",IF('Formation Initiale'!$F14="Lisbonne","B2C (Initiale)","B2C+B2B (Initiale)")) -> B2C (Initiale) | E412: =IF($A412="","",'Formation Initiale'!$B14) -> OS1 | F412: =IF($A412="","",'Formation Initiale'!$G14) -> 46006 | G412: =IF($A412="","",'Formation Initiale'!$H14) -> 46017 | H412: =IF($A412="","",'Formation Initiale'!$L14) -> 0 | I412: =IF($A412="","",'Formation Initiale'!$R14) -> Terminé | K412: =IF(A412="",0,IF(IFERROR(VLOOKUP(A412,Skills!$A:$M,13,FALSE()),"")="COS",0,IF(OR(I412="En cours",I412="À venir",I412="À planifier"),IF(AND(OR($C$3="Tous",$C$3="",C412=$C$3),OR($E$3="Tous",$E$3="",I412=$E$3)),1,0),0))) -> 0 | L412: =L411+K412 -> 0
... A799: =IF('Formation Initiale'!$A401="","",'Formation Initiale'!$A401) | B799: =IF($A799="","",'Formation Initiale'!$E401) | C799: =IF($A799="","",'Formation Initiale'!$F401) | D799: =IF($A799="","",IF('Formation Initiale'!$F401="Lisbonne","B2C (Initiale)","B2C+B2B (Initiale)")) | E799: =IF($A799="","",'Formation Initiale'!$B401) | F799: =IF($A799="","",'Formation Initiale'!$G401) | G799: =IF($A799="","",'Formation Initiale'!$H401) | H799: =IF($A799="","",'Formation Initiale'!$L401) | I799: =IF($A799="","",'Formation Initiale'!$R401) | K799: =IF(A799="",0,IF(IFERROR(VLOOKUP(A799,Skills!$A:$M,13,FALSE()),"")="COS",0,IF(OR(I799="En cours",I799="À venir",I799="À planifier"),IF(AND(OR($C$3="Tous",$C$3="",C799=$C$3),OR($E$3="Tous",$E$3="",I799=$E$3)),1,0),0))) -> 0 | L799: =L798+K799 -> 15
A800: =IF('Agences & Après-vente'!$A2="","",'Agences & Après-vente'!$A2) -> TR060 | B800: =IF($A800="","",'Agences & Après-vente'!$B2) -> Stelvale Valebrook | C800: =IF($A800="","",'Agences & Après-vente'!$C2) -> Montréal | D800: =IF($A800="","","Nouvelle compétence") -> Nouvelle compétence | E800: =IF($A800="","",'Agences & Après-vente'!$D2) -> Agences et Après-vente | F800: =IF($A800="","",'Agences & Après-vente'!$E2) -> 46148 | G800: =IF($A800="","",'Agences & Après-vente'!$F2) -> 46150 | H800: =IF($A800="","",IFERROR(MAX(0,NETWORKDAYS(TODAY(),'Agences & Après-vente'!$F2)),"")) -> 0 | I800: =IF($A800="","",'Agences & Après-vente'!$I2) -> DONE | K800: =IF(A800="",0,IF(IFERROR(VLOOKUP(A800,Skills!$A:$M,13,FALSE()),"")="COS",0,IF(OR(I800="En cours",I800="À venir",I800="À planifier"),IF(AND(OR($C$3="Tous",$C$3="",C800=$C$3),OR($E$3="Tous",$E$3="",I800=$E$3)),1,0),0))) -> 0 | L800: =L799+K800 -> 15
A801: =IF('Agences & Après-vente'!$A3="","",'Agences & Après-vente'!$A3) -> TR094 | B801: =IF($A801="","",'Agences & Après-vente'!$B3) -> Braith Calith | C801: =IF($A801="","",'Agences & Après-vente'!$C3) -> Montréal | D801: =IF($A801="","","Nouvelle compétence") -> Nouvelle compétence | E801: =IF($A801="","",'Agences & Après-vente'!$D3) -> Agences et Après-vente | F801: =IF($A801="","",'Agences & Après-vente'!$E3) -> 46148 | G801: =IF($A801="","",'Agences & Après-vente'!$F3) -> 46149 | H801: =IF($A801="","",IFERROR(MAX(0,NETWORKDAYS(TODAY(),'Agences & Après-vente'!$F3)),"")) -> 0 | I801: =IF($A801="","",'Agences & Après-vente'!$I3) -> DONE | K801: =IF(A801="",0,IF(IFERROR(VLOOKUP(A801,Skills!$A:$M,13,FALSE()),"")="COS",0,IF(OR(I801="En cours",I801="À venir",I801="À planifier"),IF(AND(OR($C$3="Tous",$C$3="",C801=$C$3),OR($E$3="Tous",$E$3="",I801=$E$3)),1,0),0))) -> 0 | L801: =L800+K801 -> 15
A802: =IF('Agences & Après-vente'!$A4="","",'Agences & Après-vente'!$A4) -> TR030 | B802: =IF($A802="","",'Agences & Après-vente'!$B4) -> Fenus Yoror | C802: =IF($A802="","",'Agences & Après-vente'!$C4) -> Montréal | D802: =IF($A802="","","Nouvelle compétence") -> Nouvelle compétence | E802: =IF($A802="","",'Agences & Après-vente'!$D4) -> Agences et Après-vente | F802: =IF($A802="","",'Agences & Après-vente'!$E4) -> 46148 | G802: =IF($A802="","",'Agences & Après-vente'!$F4) -> 46150 | H802: =IF($A802="","",IFERROR(MAX(0,NETWORKDAYS(TODAY(),'Agences & Après-vente'!$F4)),"")) -> 0 | I802: =IF($A802="","",'Agences & Après-vente'!$I4) -> DONE | K802: =IF(A802="",0,IF(IFERROR(VLOOKUP(A802,Skills!$A:$M,13,FALSE()),"")="COS",0,IF(OR(I802="En cours",I802="À venir",I802="À planifier"),IF(AND(OR($C$3="Tous",$C$3="",C802=$C$3),OR($E$3="Tous",$E$3="",I802=$E$3)),1,0),0))) -> 0 | L802: =L801+K802 -> 15
A803: =IF('Agences & Après-vente'!$A5="","",'Agences & Après-vente'!$A5) -> TR003 | B803: =IF($A803="","",'Agences & Après-vente'!$B5) -> Kendfield Moran Lumith | C803: =IF($A803="","",'Agences & Après-vente'!$C5) -> Montréal | D803: =IF($A803="","","Nouvelle compétence") -> Nouvelle compétence | E803: =IF($A803="","",'Agences & Après-vente'!$D5) -> Agences et Après-vente | F803: =IF($A803="","",'Agences & Après-vente'!$E5) -> 46148 | G803: =IF($A803="","",'Agences & Après-vente'!$F5) -> 46150 | H803: =IF($A803="","",IFERROR(MAX(0,NETWORKDAYS(TODAY(),'Agences & Après-vente'!$F5)),"")) -> 0 | I803: =IF($A803="","",'Agences & Après-vente'!$I5) -> DONE | K803: =IF(A803="",0,IF(IFERROR(VLOOKUP(A803,Skills!$A:$M,13,FALSE()),"")="COS",0,IF(OR(I803="En cours",I803="À venir",I803="À planifier"),IF(AND(OR($C$3="Tous",$C$3="",C803=$C$3),OR($E$3="Tous",$E$3="",I803=$E$3)),1,0),0))) -> 0 | L803: =L802+K803 -> 15
A804: =IF('Agences & Après-vente'!$A6="","",'Agences & Après-vente'!$A6) -> TR016 | B804: =IF($A804="","",'Agences & Après-vente'!$B6) -> Gilum Larkfield | C804: =IF($A804="","",'Agences & Après-vente'!$C6) -> Montréal | D804: =IF($A804="","","Nouvelle compétence") -> Nouvelle compétence | E804: =IF($A804="","",'Agences & Après-vente'!$D6) -> Agences et Après-vente | F804: =IF($A804="","",'Agences & Après-vente'!$E6) -> 46149 | G804: =IF($A804="","",'Agences & Après-vente'!$F6) -> 46153 | H804: =IF($A804="","",IFERROR(MAX(0,NETWORKDAYS(TODAY(),'Agences & Après-vente'!$F6)),"")) -> 0 | I804: =IF($A804="","",'Agences & Après-vente'!$I6) -> DONE | K804: =IF(A804="",0,IF(IFERROR(VLOOKUP(A804,Skills!$A:$M,13,FALSE()),"")="COS",0,IF(OR(I804="En cours",I804="À venir",I804="À planifier"),IF(AND(OR($C$3="Tous",$C$3="",C804=$C$3),OR($E$3="Tous",$E$3="",I804=$E$3)),1,0),0))) -> 0 | L804: =L803+K804 -> 15
A805: =IF('Agences & Après-vente'!$A7="","",'Agences & Après-vente'!$A7) -> TR140 | B805: =IF($A805="","",'Agences & Après-vente'!$B7) -> Kelen Toric | C805: =IF($A805="","",'Agences & Après-vente'!$C7) -> Montréal | D805: =IF($A805="","","Nouvelle compétence") -> Nouvelle compétence | E805: =IF($A805="","",'Agences & Après-vente'!$D7) -> Agences et Après-vente | F805: =IF($A805="","",'Agences & Après-vente'!$E7) -> 46149 | G805: =IF($A805="","",'Agences & Après-vente'!$F7) -> 46153 | H805: =IF($A805="","",IFERROR(MAX(0,NETWORKDAYS(TODAY(),'Agences & Après-vente'!$F7)),"")) -> 0 | I805: =IF($A805="","",'Agences & Après-vente'!$I7) -> DONE | K805: =IF(A805="",0,IF(IFERROR(VLOOKUP(A805,Skills!$A:$M,13,FALSE()),"")="COS",0,IF(OR(I805="En cours",I805="À venir",I805="À planifier"),IF(AND(OR($C$3="Tous",$C$3="",C805=$C$3),OR($E$3="Tous",$E$3="",I805=$E$3)),1,0),0))) -> 0 | L805: =L804+K805 -> 15
A806: =IF('Agences & Après-vente'!$A8="","",'Agences & Après-vente'!$A8) -> TR104 | B806: =IF($A806="","",'Agences & Après-vente'!$B8) -> Haxus Corrridge | C806: =IF($A806="","",'Agences & Après-vente'!$C8) -> Montréal | D806: =IF($A806="","","Nouvelle compétence") -> Nouvelle compétence | E806: =IF($A806="","",'Agences & Après-vente'!$D8) -> Agences et Après-vente | F806: =IF($A806="","",'Agences & Après-vente'!$E8) -> 46150 | G806: =IF($A806="","",'Agences & Après-vente'!$F8) -> 46154 | H806: =IF($A806="","",IFERROR(MAX(0,NETWORKDAYS(TODAY(),'Agences & Après-vente'!$F8)),"")) -> 0 | I806: =IF($A806="","",'Agences & Après-vente'!$I8) -> DONE | K806: =IF(A806="",0,IF(IFERROR(VLOOKUP(A806,Skills!$A:$M,13,FALSE()),"")="COS",0,IF(OR(I806="En cours",I806="À venir",I806="À planifier"),IF(AND(OR($C$3="Tous",$C$3="",C806=$C$3),OR($E$3="Tous",$E$3="",I806=$E$3)),1,0),0))) -> 0 | L806: =L805+K806 -> 15
A807: =IF('Agences & Après-vente'!$A9="","",'Agences & Après-vente'!$A9) -> TR019 | B807: =IF($A807="","",'Agences & Après-vente'!$B9) -> Kelar Dellbrook | C807: =IF($A807="","",'Agences & Après-vente'!$C9) -> Montréal | D807: =IF($A807="","","Nouvelle compétence") -> Nouvelle compétence | E807: =IF($A807="","",'Agences & Après-vente'!$D9) -> Agences et Après-vente | F807: =IF($A807="","",'Agences & Après-vente'!$E9) -> 46150 | G807: =IF($A807="","",'Agences & Après-vente'!$F9) -> 46154 | H807: =IF($A807="","",IFERROR(MAX(0,NETWORKDAYS(TODAY(),'Agences & Après-vente'!$F9)),"")) -> 0 | I807: =IF($A807="","",'Agences & Après-vente'!$I9) -> DONE | K807: =IF(A807="",0,IF(IFERROR(VLOOKUP(A807,Skills!$A:$M,13,FALSE()),"")="COS",0,IF(OR(I807="En cours",I807="À venir",I807="À planifier"),IF(AND(OR($C$3="Tous",$C$3="",C807=$C$3),OR($E$3="Tous",$E$3="",I807=$E$3)),1,0),0))) -> 0 | L807: =L806+K807 -> 15
A808: =IF('Agences & Après-vente'!$A10="","",'Agences & Après-vente'!$A10) -> TR083 | B808: =IF($A808="","",'Agences & Après-vente'!$B10) -> Kendmere Selor | C808: =IF($A808="","",'Agences & Après-vente'!$C10) -> Montréal | D808: =IF($A808="","","Nouvelle compétence") -> Nouvelle compétence | E808: =IF($A808="","",'Agences & Après-vente'!$D10) -> Agences et Après-vente | F808: =IF($A808="","",'Agences & Après-vente'!$E10) -> 46151 | G808: =IF($A808="","",'Agences & Après-vente'!$F10) -> 46154 | H808: =IF($A808="","",IFERROR(MAX(0,NETWORKDAYS(TODAY(),'Agences & Après-vente'!$F10)),"")) -> 0 | I808: =IF($A808="","",'Agences & Après-vente'!$I10) -> DONE | K808: =IF(A808="",0,IF(IFERROR(VLOOKUP(A808,Skills!$A:$M,13,FALSE()),"")="COS",0,IF(OR(I808="En cours",I808="À venir",I808="À planifier"),IF(AND(OR($C$3="Tous",$C$3="",C808=$C$3),OR($E$3="Tous",$E$3="",I808=$E$3)),1,0),0))) -> 0 | L808: =L807+K808 -> 15
A809: =IF('Agences & Après-vente'!$A11="","",'Agences & Après-vente'!$A11) -> TR063 | B809: =IF($A809="","",'Agences & Après-vente'!$B11) -> Jorus Marsgate | C809: =IF($A809="","",'Agences & Après-vente'!$C11) -> Montréal | D809: =IF($A809="","","Nouvelle compétence") -> Nouvelle compétence | E809: =IF($A809="","",'Agences & Après-vente'!$D11) -> Agences et Après-vente | F809: =IF($A809="","",'Agences & Après-vente'!$E11) -> 46151 | G809: =IF($A809="","",'Agences & Après-vente'!$F11) -> 46155 | H809: =IF($A809="","",IFERROR(MAX(0,NETWORKDAYS(TODAY(),'Agences & Après-vente'!$F11)),"")) -> 0 | I809: =IF($A809="","",'Agences & Après-vente'!$I11) -> DONE | K809: =IF(A809="",0,IF(IFERROR(VLOOKUP(A809,Skills!$A:$M,13,FALSE()),"")="COS",0,IF(OR(I809="En cours",I809="À venir",I809="À planifier"),IF(AND(OR($C$3="Tous",$C$3="",C809=$C$3),OR($E$3="Tous",$E$3="",I809=$E$3)),1,0),0))) -> 0 | L809: =L808+K809 -> 15
A810: =IF('Agences & Après-vente'!$A12="","",'Agences & Après-vente'!$A12) -> TR055 | B810: =IF($A810="","",'Agences & Après-vente'!$B12) -> Quillhaven Larkworth | C810: =IF($A810="","",'Agences & Après-vente'!$C12) -> Montréal | D810: =IF($A810="","","Nouvelle compétence") -> Nouvelle compétence | E810: =IF($A810="","",'Agences & Après-vente'!$D12) -> Agences et Après-vente | F810: =IF($A810="","",'Agences & Après-vente'!$E12) -> 46152 | G810: =IF($A810="","",'Agences & Après-vente'!$F12) -> 46155 | H810: =IF($A810="","",IFERROR(MAX(0,NETWORKDAYS(TODAY(),'Agences & Après-vente'!$F12)),"")) -> 0 | I810: =IF($A810="","",'Agences & Après-vente'!$I12) -> DONE | K810: =IF(A810="",0,IF(IFERROR(VLOOKUP(A810,Skills!$A:$M,13,FALSE()),"")="COS",0,IF(OR(I810="En cours",I810="À venir",I810="À planifier"),IF(AND(OR($C$3="Tous",$C$3="",C810=$C$3),OR($E$3="Tous",$E$3="",I810=$E$3)),1,0),0))) -> 0 | L810: =L809+K810 -> 15
A811: =IF('Agences & Après-vente'!$A13="","",'Agences & Après-vente'!$A13) -> TR144 | B811: =IF($A811="","",'Agences & Après-vente'!$B13) -> Yorol Ashbrook | C811: =IF($A811="","",'Agences & Après-vente'!$C13) -> Montréal | D811: =IF($A811="","","Nouvelle compétence") -> Nouvelle compétence | E811: =IF($A811="","",'Agences & Après-vente'!$D13) -> Agences | F811: =IF($A811="","",'Agences & Après-vente'!$E13) -> 46175 | G811: =IF($A811="","",'Agences & Après-vente'!$F13) -> 46178 | H811: =IF($A811="","",IFERROR(MAX(0,NETWORKDAYS(TODAY(),'Agences & Après-vente'!$F13)),"")) -> 0 | I811: =IF($A811="","",'Agences & Après-vente'!$I13) -> DONE | K811: =IF(A811="",0,IF(IFERROR(VLOOKUP(A811,Skills!$A:$M,13,FALSE()),"")="COS",0,IF(OR(I811="En cours",I811="À venir",I811="À planifier"),IF(AND(OR($C$3="Tous",$C$3="",C811=$C$3),OR($E$3="Tous",$E$3="",I811=$E$3)),1,0),0))) -> 0 | L811: =L810+K811 -> 15
... A1199: =IF('Agences & Après-vente'!$A401="","",'Agences & Après-vente'!$A401) | B1199: =IF($A1199="","",'Agences & Après-vente'!$B401) | C1199: =IF($A1199="","",'Agences & Après-vente'!$C401) | D1199: =IF($A1199="","","Nouvelle compétence") | E1199: =IF($A1199="","",'Agences & Après-vente'!$D401) | F1199: =IF($A1199="","",'Agences & Après-vente'!$E401) | G1199: =IF($A1199="","",'Agences & Après-vente'!$F401) | H1199: =IF($A1199="","",IFERROR(MAX(0,NETWORKDAYS(TODAY(),'Agences & Après-vente'!$F401)),"")) | I1199: =IF($A1199="","",'Agences & Après-vente'!$I401) | K1199: =IF(A1199="",0,IF(IFERROR(VLOOKUP(A1199,Skills!$A:$M,13,FALSE()),"")="COS",0,IF(OR(I1199="En cours",I1199="À venir",I1199="À planifier"),IF(AND(OR($C$3="Tous",$C$3="",C1199=$C$3),OR($E$3="Tous",$E$3="",I1199=$E$3)),1,0),0))) -> 0 | L1199: =L1198+K1199 -> 17
A1200: =IF(Evermont!$A2="","",Evermont!$A2) -> TR074 | B1200: =IF($A1200="","",Evermont!$B2) -> Marsridge Holtgate | C1200: =IF($A1200="","",Evermont!$C2) -> Montréal | D1200: =IF($A1200="","","Nouvelle compétence") -> Nouvelle compétence | E1200: =IF($A1200="","",Evermont!$D2) -> Evermont | F1200: =IF($A1200="","",Evermont!$F2) -> 46133 | G1200: =IF($A1200="","",Evermont!$G2) -> 46141 | H1200: =IF($A1200="","",Evermont!$K2) -> 0 | I1200: =IF($A1200="","",Evermont!$Q2) -> Terminé | K1200: =IF(A1200="",0,IF(IFERROR(VLOOKUP(A1200,Skills!$A:$M,13,FALSE()),"")="COS",0,IF(OR(I1200="En cours",I1200="À venir",I1200="À planifier"),IF(AND(OR($C$3="Tous",$C$3="",C1200=$C$3),OR($E$3="Tous",$E$3="",I1200=$E$3)),1,0),0))) -> 0 | L1200: =L1199+K1200 -> 17
A1201: =IF(Evermont!$A3="","",Evermont!$A3) -> TR007 | B1201: =IF($A1201="","",Evermont!$B3) -> Stelfield Dellmere Valegate | C1201: =IF($A1201="","",Evermont!$C3) -> Montréal | D1201: =IF($A1201="","","Nouvelle compétence") -> Nouvelle compétence | E1201: =IF($A1201="","",Evermont!$D3) -> Evermont | F1201: =IF($A1201="","",Evermont!$F3) -> 46128 | G1201: =IF($A1201="","",Evermont!$G3) -> 46136 | H1201: =IF($A1201="","",Evermont!$K3) -> 0 | I1201: =IF($A1201="","",Evermont!$Q3) -> Terminé | K1201: =IF(A1201="",0,IF(IFERROR(VLOOKUP(A1201,Skills!$A:$M,13,FALSE()),"")="COS",0,IF(OR(I1201="En cours",I1201="À venir",I1201="À planifier"),IF(AND(OR($C$3="Tous",$C$3="",C1201=$C$3),OR($E$3="Tous",$E$3="",I1201=$E$3)),1,0),0))) -> 0 | L1201: =L1200+K1201 -> 17
A1202: =IF(Evermont!$A4="","",Evermont!$A4) -> TR098 | B1202: =IF($A1202="","",Evermont!$B4) -> Holtstone Gilir | C1202: =IF($A1202="","",Evermont!$C4) -> Montréal | D1202: =IF($A1202="","","Nouvelle compétence") -> Nouvelle compétence | E1202: =IF($A1202="","",Evermont!$D4) -> Evermont | F1202: =IF($A1202="","",Evermont!$F4) -> 46115 | G1202: =IF($A1202="","",Evermont!$G4) -> 46125 | H1202: =IF($A1202="","",Evermont!$K4) -> 0 | I1202: =IF($A1202="","",Evermont!$Q4) -> Terminé | K1202: =IF(A1202="",0,IF(IFERROR(VLOOKUP(A1202,Skills!$A:$M,13,FALSE()),"")="COS",0,IF(OR(I1202="En cours",I1202="À venir",I1202="À planifier"),IF(AND(OR($C$3="Tous",$C$3="",C1202=$C$3),OR($E$3="Tous",$E$3="",I1202=$E$3)),1,0),0))) -> 0 | L1202: =L1201+K1202 -> 17
A1203: =IF(Evermont!$A5="","",Evermont!$A5) -> TR089 | B1203: =IF($A1203="","",Evermont!$B5) -> Doran Voren Voren | C1203: =IF($A1203="","",Evermont!$C5) -> Montréal | D1203: =IF($A1203="","","Nouvelle compétence") -> Nouvelle compétence | E1203: =IF($A1203="","",Evermont!$D5) -> Evermont | F1203: =IF($A1203="","",Evermont!$F5) -> 46126 | G1203: =IF($A1203="","",Evermont!$G5) -> 46134 | H1203: =IF($A1203="","",Evermont!$K5) -> 0 | I1203: =IF($A1203="","",Evermont!$Q5) -> Terminé | K1203: =IF(A1203="",0,IF(IFERROR(VLOOKUP(A1203,Skills!$A:$M,13,FALSE()),"")="COS",0,IF(OR(I1203="En cours",I1203="À venir",I1203="À planifier"),IF(AND(OR($C$3="Tous",$C$3="",C1203=$C$3),OR($E$3="Tous",$E$3="",I1203=$E$3)),1,0),0))) -> 0 | L1203: =L1202+K1203 -> 17
A1204: =IF(Evermont!$A6="","",Evermont!$A6) -> TR108 | B1204: =IF($A1204="","",Evermont!$B6) -> Bramdale Pelum | C1204: =IF($A1204="","",Evermont!$C6) -> Montréal | D1204: =IF($A1204="","","Nouvelle compétence") -> Nouvelle compétence | E1204: =IF($A1204="","",Evermont!$D6) -> Evermont | F1204: =IF($A1204="","",Evermont!$F6) -> 46128 | G1204: =IF($A1204="","",Evermont!$G6) -> 46136 | H1204: =IF($A1204="","",Evermont!$K6) -> 0 | I1204: =IF($A1204="","",Evermont!$Q6) -> Terminé | K1204: =IF(A1204="",0,IF(IFERROR(VLOOKUP(A1204,Skills!$A:$M,13,FALSE()),"")="COS",0,IF(OR(I1204="En cours",I1204="À venir",I1204="À planifier"),IF(AND(OR($C$3="Tous",$C$3="",C1204=$C$3),OR($E$3="Tous",$E$3="",I1204=$E$3)),1,0),0))) -> 0 | L1204: =L1203+K1204 -> 17
A1205: =IF(Evermont!$A7="","",Evermont!$A7) -> TR033 | B1205: =IF($A1205="","",Evermont!$B7) -> Fenith Calar | C1205: =IF($A1205="","",Evermont!$C7) -> Montréal | D1205: =IF($A1205="","","Nouvelle compétence") -> Nouvelle compétence | E1205: =IF($A1205="","",Evermont!$D7) -> Evermont | F1205: =IF($A1205="","",Evermont!$F7) -> 46132 | G1205: =IF($A1205="","",Evermont!$G7) -> 46140 | H1205: =IF($A1205="","",Evermont!$K7) -> 0 | I1205: =IF($A1205="","",Evermont!$Q7) -> Terminé | K1205: =IF(A1205="",0,IF(IFERROR(VLOOKUP(A1205,Skills!$A:$M,13,FALSE()),"")="COS",0,IF(OR(I1205="En cours",I1205="À venir",I1205="À planifier"),IF(AND(OR($C$3="Tous",$C$3="",C1205=$C$3),OR($E$3="Tous",$E$3="",I1205=$E$3)),1,0),0))) -> 0 | L1205: =L1204+K1205 -> 17
A1206: =IF(Evermont!$A8="","",Evermont!$A8) -> TR002 | B1206: =IF($A1206="","",Evermont!$B8) -> Rownvale Rownmere Fenon Doric | C1206: =IF($A1206="","",Evermont!$C8) -> Montréal | D1206: =IF($A1206="","","Nouvelle compétence") -> Nouvelle compétence | E1206: =IF($A1206="","",Evermont!$D8) -> Evermont | F1206: =IF($A1206="","",Evermont!$F8) -> 46122 | G1206: =IF($A1206="","",Evermont!$G8) -> 46132 | H1206: =IF($A1206="","",Evermont!$K8) -> 0 | I1206: =IF($A1206="","",Evermont!$Q8) -> Terminé | K1206: =IF(A1206="",0,IF(IFERROR(VLOOKUP(A1206,Skills!$A:$M,13,FALSE()),"")="COS",0,IF(OR(I1206="En cours",I1206="À venir",I1206="À planifier"),IF(AND(OR($C$3="Tous",$C$3="",C1206=$C$3),OR($E$3="Tous",$E$3="",I1206=$E$3)),1,0),0))) -> 0 | L1206: =L1205+K1206 -> 17
A1207: =IF(Evermont!$A9="","",Evermont!$A9) -> TR050 | B1207: =IF($A1207="","",Evermont!$B9) -> Kelor Stelwood | C1207: =IF($A1207="","",Evermont!$C9) -> Montréal | D1207: =IF($A1207="","","Nouvelle compétence") -> Nouvelle compétence | E1207: =IF($A1207="","",Evermont!$D9) -> Evermont | F1207: =IF($A1207="","",Evermont!$F9) -> 46132 | G1207: =IF($A1207="","",Evermont!$G9) -> 46140 | H1207: =IF($A1207="","",Evermont!$K9) -> 0 | I1207: =IF($A1207="","",Evermont!$Q9) -> Terminé | K1207: =IF(A1207="",0,IF(IFERROR(VLOOKUP(A1207,Skills!$A:$M,13,FALSE()),"")="COS",0,IF(OR(I1207="En cours",I1207="À venir",I1207="À planifier"),IF(AND(OR($C$3="Tous",$C$3="",C1207=$C$3),OR($E$3="Tous",$E$3="",I1207=$E$3)),1,0),0))) -> 0 | L1207: =L1206+K1207 -> 17
A1208: =IF(Evermont!$A10="","",Evermont!$A10) -> TR105 | B1208: =IF($A1208="","",Evermont!$B10) -> Dellridge Larkbrook | C1208: =IF($A1208="","",Evermont!$C10) -> Montréal | D1208: =IF($A1208="","","Nouvelle compétence") -> Nouvelle compétence | E1208: =IF($A1208="","",Evermont!$D10) -> Evermont | F1208: =IF($A1208="","",Evermont!$F10) -> 46121 | G1208: =IF($A1208="","",Evermont!$G10) -> 46129 | H1208: =IF($A1208="","",Evermont!$K10) -> 0 | I1208: =IF($A1208="","",Evermont!$Q10) -> Terminé | K1208: =IF(A1208="",0,IF(IFERROR(VLOOKUP(A1208,Skills!$A:$M,13,FALSE()),"")="COS",0,IF(OR(I1208="En cours",I1208="À venir",I1208="À planifier"),IF(AND(OR($C$3="Tous",$C$3="",C1208=$C$3),OR($E$3="Tous",$E$3="",I1208=$E$3)),1,0),0))) -> 0 | L1208: =L1207+K1208 -> 17
A1209: =IF(Evermont!$A11="","",Evermont!$A11) -> TR126 | B1209: =IF($A1209="","",Evermont!$B11) -> Pelea Yorir | C1209: =IF($A1209="","",Evermont!$C11) -> Montréal | D1209: =IF($A1209="","","Nouvelle compétence") -> Nouvelle compétence | E1209: =IF($A1209="","",Evermont!$D11) -> Evermont | F1209: =IF($A1209="","",Evermont!$F11) -> 46122 | G1209: =IF($A1209="","",Evermont!$G11) -> 46132 | H1209: =IF($A1209="","",Evermont!$K11) -> 0 | I1209: =IF($A1209="","",Evermont!$Q11) -> Terminé | K1209: =IF(A1209="",0,IF(IFERROR(VLOOKUP(A1209,Skills!$A:$M,13,FALSE()),"")="COS",0,IF(OR(I1209="En cours",I1209="À venir",I1209="À planifier"),IF(AND(OR($C$3="Tous",$C$3="",C1209=$C$3),OR($E$3="Tous",$E$3="",I1209=$E$3)),1,0),0))) -> 0 | L1209: =L1208+K1209 -> 17
A1210: =IF(Evermont!$A12="","",Evermont!$A12) -> TR133 | B1210: =IF($A1210="","",Evermont!$B12) -> Ulmith Larkvale | C1210: =IF($A1210="","",Evermont!$C12) -> Montréal | D1210: =IF($A1210="","","Nouvelle compétence") -> Nouvelle compétence | E1210: =IF($A1210="","",Evermont!$D12) -> Evermont | F1210: =IF($A1210="","",Evermont!$F12) -> 46111 | G1210: =IF($A1210="","",Evermont!$G12) -> 46119 | H1210: =IF($A1210="","",Evermont!$K12) -> 0 | I1210: =IF($A1210="","",Evermont!$Q12) -> Terminé | K1210: =IF(A1210="",0,IF(IFERROR(VLOOKUP(A1210,Skills!$A:$M,13,FALSE()),"")="COS",0,IF(OR(I1210="En cours",I1210="À venir",I1210="À planifier"),IF(AND(OR($C$3="Tous",$C$3="",C1210=$C$3),OR($E$3="Tous",$E$3="",I1210=$E$3)),1,0),0))) -> 0 | L1210: =L1209+K1210 -> 17
A1211: =IF(Evermont!$A13="","",Evermont!$A13) -> TR057 | B1211: =IF($A1211="","",Evermont!$B13) -> Ivercroft Corrmere | C1211: =IF($A1211="","",Evermont!$C13) -> Montréal | D1211: =IF($A1211="","","Nouvelle compétence") -> Nouvelle compétence | E1211: =IF($A1211="","",Evermont!$D13) -> Evermont | F1211: =IF($A1211="","",Evermont!$F13) -> 46106 | G1211: =IF($A1211="","",Evermont!$G13) -> 46114 | H1211: =IF($A1211="","",Evermont!$K13) -> 0 | I1211: =IF($A1211="","",Evermont!$Q13) -> Terminé | K1211: =IF(A1211="",0,IF(IFERROR(VLOOKUP(A1211,Skills!$A:$M,13,FALSE()),"")="COS",0,IF(OR(I1211="En cours",I1211="À venir",I1211="À planifier"),IF(AND(OR($C$3="Tous",$C$3="",C1211=$C$3),OR($E$3="Tous",$E$3="",I1211=$E$3)),1,0),0))) -> 0 | L1211: =L1210+K1211 -> 17
... A1599: =IF(Evermont!$A401="","",Evermont!$A401) | B1599: =IF($A1599="","",Evermont!$B401) | C1599: =IF($A1599="","",Evermont!$C401) | D1599: =IF($A1599="","","Nouvelle compétence") | E1599: =IF($A1599="","",Evermont!$D401) | F1599: =IF($A1599="","",Evermont!$F401) | G1599: =IF($A1599="","",Evermont!$G401) | H1599: =IF($A1599="","",Evermont!$K401) | I1599: =IF($A1599="","",Evermont!$Q401) | K1599: =IF(A1599="",0,IF(IFERROR(VLOOKUP(A1599,Skills!$A:$M,13,FALSE()),"")="COS",0,IF(OR(I1599="En cours",I1599="À venir",I1599="À planifier"),IF(AND(OR($C$3="Tous",$C$3="",C1599=$C$3),OR($E$3="Tous",$E$3="",I1599=$E$3)),1,0),0))) -> 0 | L1599: =L1598+K1599 -> 19
K1600: =IF(A1600="",0,IF(IFERROR(VLOOKUP(A1600,Skills!$A:$M,13,FALSE()),"")="COS",0,IF(OR(I1600="En cours",I1600="À venir",I1600="À planifier"),IF(AND(OR($C$3="Tous",$C$3="",C1600=$C$3),OR($E$3="Tous",$E$3="",I1600=$E$3)),1,0),0))) -> 0 | L1600: =L1599+K1600 -> 19
K1601: =IF(A1601="",0,IF(IFERROR(VLOOKUP(A1601,Skills!$A:$M,13,FALSE()),"")="COS",0,IF(OR(I1601="En cours",I1601="À venir",I1601="À planifier"),IF(AND(OR($C$3="Tous",$C$3="",C1601=$C$3),OR($E$3="Tous",$E$3="",I1601=$E$3)),1,0),0))) -> 0 | L1601: =L1600+K1601 -> 19
K1602: =IF(A1602="",0,IF(IFERROR(VLOOKUP(A1602,Skills!$A:$M,13,FALSE()),"")="COS",0,IF(OR(I1602="En cours",I1602="À venir",I1602="À planifier"),IF(AND(OR($C$3="Tous",$C$3="",C1602=$C$3),OR($E$3="Tous",$E$3="",I1602=$E$3)),1,0),0))) -> 0 | L1602: =L1601+K1602 -> 19
K1603: =IF(A1603="",0,IF(IFERROR(VLOOKUP(A1603,Skills!$A:$M,13,FALSE()),"")="COS",0,IF(OR(I1603="En cours",I1603="À venir",I1603="À planifier"),IF(AND(OR($C$3="Tous",$C$3="",C1603=$C$3),OR($E$3="Tous",$E$3="",I1603=$E$3)),1,0),0))) -> 0 | L1603: =L1602+K1603 -> 19
K1604: =IF(A1604="",0,IF(IFERROR(VLOOKUP(A1604,Skills!$A:$M,13,FALSE()),"")="COS",0,IF(OR(I1604="En cours",I1604="À venir",I1604="À planifier"),IF(AND(OR($C$3="Tous",$C$3="",C1604=$C$3),OR($E$3="Tous",$E$3="",I1604=$E$3)),1,0),0))) -> 0 | L1604: =L1603+K1604 -> 19
K1605: =IF(A1605="",0,IF(IFERROR(VLOOKUP(A1605,Skills!$A:$M,13,FALSE()),"")="COS",0,IF(OR(I1605="En cours",I1605="À venir",I1605="À planifier"),IF(AND(OR($C$3="Tous",$C$3="",C1605=$C$3),OR($E$3="Tous",$E$3="",I1605=$E$3)),1,0),0))) -> 0 | L1605: =L1604+K1605 -> 19
K1606: =IF(A1606="",0,IF(IFERROR(VLOOKUP(A1606,Skills!$A:$M,13,FALSE()),"")="COS",0,IF(OR(I1606="En cours",I1606="À venir",I1606="À planifier"),IF(AND(OR($C$3="Tous",$C$3="",C1606=$C$3),OR($E$3="Tous",$E$3="",I1606=$E$3)),1,0),0))) -> 0 | L1606: =L1605+K1606 -> 19
K1607: =IF(A1607="",0,IF(IFERROR(VLOOKUP(A1607,Skills!$A:$M,13,FALSE()),"")="COS",0,IF(OR(I1607="En cours",I1607="À venir",I1607="À planifier"),IF(AND(OR($C$3="Tous",$C$3="",C1607=$C$3),OR($E$3="Tous",$E$3="",I1607=$E$3)),1,0),0))) -> 0 | L1607: =L1606+K1607 -> 19
K1608: =IF(A1608="",0,IF(IFERROR(VLOOKUP(A1608,Skills!$A:$M,13,FALSE()),"")="COS",0,IF(OR(I1608="En cours",I1608="À venir",I1608="À planifier"),IF(AND(OR($C$3="Tous",$C$3="",C1608=$C$3),OR($E$3="Tous",$E$3="",I1608=$E$3)),1,0),0))) -> 0 | L1608: =L1607+K1608 -> 19
K1609: =IF(A1609="",0,IF(IFERROR(VLOOKUP(A1609,Skills!$A:$M,13,FALSE()),"")="COS",0,IF(OR(I1609="En cours",I1609="À venir",I1609="À planifier"),IF(AND(OR($C$3="Tous",$C$3="",C1609=$C$3),OR($E$3="Tous",$E$3="",I1609=$E$3)),1,0),0))) -> 0 | L1609: =L1608+K1609 -> 19
K1610: =IF(A1610="",0,IF(IFERROR(VLOOKUP(A1610,Skills!$A:$M,13,FALSE()),"")="COS",0,IF(OR(I1610="En cours",I1610="À venir",I1610="À planifier"),IF(AND(OR($C$3="Tous",$C$3="",C1610=$C$3),OR($E$3="Tous",$E$3="",I1610=$E$3)),1,0),0))) -> 0 | L1610: =L1609+K1610 -> 19
K1611: =IF(A1611="",0,IF(IFERROR(VLOOKUP(A1611,Skills!$A:$M,13,FALSE()),"")="COS",0,IF(OR(I1611="En cours",I1611="À venir",I1611="À planifier"),IF(AND(OR($C$3="Tous",$C$3="",C1611=$C$3),OR($E$3="Tous",$E$3="",I1611=$E$3)),1,0),0))) -> 0 | L1611: =L1610+K1611 -> 19
... K4395: =IF(A4395="",0,IF(IFERROR(VLOOKUP(A4395,Skills!$A:$M,13,FALSE()),"")="COS",0,IF(OR(I4395="En cours",I4395="À venir",I4395="À planifier"),IF(AND(OR($C$3="Tous",$C$3="",C4395=$C$3),OR($E$3="Tous",$E$3="",I4395=$E$3)),1,0),0))) -> 0 | L4395: =L4394+K4395 -> 19

Sheet Skills
A1: ID Agent | B1: Prénom | C1: Nom | D1: Lieu | E1: B2C | F1: B2B | G1: Agences B2C | H1: Agences B2B | I1: Après-vente B2C | J1: Après-vente B2B | K1: Loisirs | L1: Nb compétences | M1: Statut | N1: =HYPERLINK("#Accueil!A1","⌂ Accueil") -> ⌂ Accueil | O1: Quillridge B2C | P1: Quillridge B2B | Q1: Quillridge Agences B2C | R1: Quillridge Agences B2B | S1: Quillridge Après-vente B2C | T1: Quillridge Après-vente B2B | U1: Quillridge Evermont | W1: Groupe | X1: Groupe (saisie)
A2: TR001 | B2: Lumus | C2: Fenel Valeridge | D2: Montréal | E2: =IF($O2="✓","✓",IF(ISNUMBER($O2),TEXT($O2,"yyyy-mm-dd"),IF($A2="","",IF(SUMPRODUCT(('Formation Initiale'!$A$2:$A$999=$A2)*('Formation Initiale'!$R$2:$R$999="Terminé"))>0,"✓",IF(SUMPRODUCT(MAX(('Formation Initiale'!$A$2:$A$999=$A2)*'Formation Initiale'!$G$2:$G$999))>0,TEXT(SUMPRODUCT(MAX(('Formation Initiale'!$A$2:$A$999=$A2)*'Formation Initiale'!$G$2:$G$999)),"yyyy-mm-dd"),""))))) -> ✓ | F2: =IF($P2="✓","✓",IF(ISNUMBER($P2),TEXT($P2,"yyyy-mm-dd"),IF($A2="","",IF($D2="Lisbonne","",IF(SUMPRODUCT(('Formation Initiale'!$A$2:$A$999=$A2)*('Formation Initiale'!$R$2:$R$999="Terminé"))>0,"✓",IF(SUMPRODUCT(MAX(('Formation Initiale'!$A$2:$A$999=$A2)*'Formation Initiale'!$G$2:$G$999))>0,TEXT(SUMPRODUCT(MAX(('Formation Initiale'!$A$2:$A$999=$A2)*'Formation Initiale'!$G$2:$G$999)),"yyyy-mm-dd"),"")))))) -> ✓ | G2: =IF($Q2="✓","✓",IF(ISNUMBER($Q2),TEXT($Q2,"yyyy-mm-dd"),IF($A2="","",IF(SUMPRODUCT(('Agences & Après-vente'!$A$2:$A$1000=$A2)*(('Agences & Après-vente'!$D$2:$D$1000="Agences")+('Agences & Après-vente'!$D$2:$D$1000="Agences et Après-vente"))*('Agences & Après-vente'!$I$2:$I$1000="DONE"))>0,"✓",IF(SUMPRODUCT(MAX(('Agences & Après-vente'!$A$2:$A$1000=$A2)*(('Agences & Après-vente'!$D$2:$D$1000="Agences")+('Agences & Après-vente'!$D$2:$D$1000="Agences et Après-vente"))*'Agences & Après-vente'!$E$2:$E$1000))>0,TEXT(SUMPRODUCT(MAX(('Agences & Après-vente'!$A$2:$A$1000=$A2)*(('Agences & Après-vente'!$D$2:$D$1000="Agences")+('Agences & Après-vente'!$D$2:$D$1000="Agences et Après-vente"))*'Agences & Après-vente'!$E$2:$E$1000)),"yyyy-mm-dd"),""))))) -> ✓ | H2: =IF($R2="✓","✓",IF(ISNUMBER($R2),TEXT($R2,"yyyy-mm-dd"),IF($A2="","",IF($D2="Lisbonne","",IF(SUMPRODUCT(('Agences & Après-vente'!$A$2:$A$1000=$A2)*(('Agences & Après-vente'!$D$2:$D$1000="Agences")+('Agences & Après-vente'!$D$2:$D$1000="Agences et Après-vente"))*('Agences & Après-vente'!$I$2:$I$1000="DONE"))>0,"✓",IF(SUMPRODUCT(MAX(('Agences & Après-vente'!$A$2:$A$1000=$A2)*(('Agences & Après-vente'!$D$2:$D$1000="Agences")+('Agences & Après-vente'!$D$2:$D$1000="Agences et Après-vente"))*'Agences & Après-vente'!$E$2:$E$1000))>0,TEXT(SUMPRODUCT(MAX(('Agences & Après-vente'!$A$2:$A$1000=$A2)*(('Agences & Après-vente'!$D$2:$D$1000="Agences")+('Agences & Après-vente'!$D$2:$D$1000="Agences et Après-vente"))*'Agences & Après-vente'!$E$2:$E$1000)),"yyyy-mm-dd"),"")))))) -> ✓ | I2: =IF($S2="✓","✓",IF(ISNUMBER($S2),TEXT($S2,"yyyy-mm-dd"),IF($A2="","",IF(SUMPRODUCT(('Agences & Après-vente'!$A$2:$A$1000=$A2)*(('Agences & Après-vente'!$D$2:$D$1000="Après-vente")+('Agences & Après-vente'!$D$2:$D$1000="Agences et Après-vente"))*('Agences & Après-vente'!$I$2:$I$1000="DONE"))>0,"✓",IF(SUMPRODUCT(MAX(('Agences & Après-vente'!$A$2:$A$1000=$A2)*(('Agences & Après-vente'!$D$2:$D$1000="Après-vente")+('Agences & Après-vente'!$D$2:$D$1000="Agences et Après-vente"))*'Agences & Après-vente'!$E$2:$E$1000))>0,TEXT(SUMPRODUCT(MAX(('Agences & Après-vente'!$A$2:$A$1000=$A2)*(('Agences & Après-vente'!$D$2:$D$1000="Après-vente")+('Agences & Après-vente'!$D$2:$D$1000="Agences et Après-vente"))*'Agences & Après-vente'!$E$2:$E$1000)),"yyyy-mm-dd"),""))))) -> ✓ | J2: =IF($T2="✓","✓",IF(ISNUMBER($T2),TEXT($T2,"yyyy-mm-dd"),IF($A2="","",IF($D2="Lisbonne","",IF(SUMPRODUCT(('Agences & Après-vente'!$A$2:$A$1000=$A2)*(('Agences & Après-vente'!$D$2:$D$1000="Après-vente")+('Agences & Après-vente'!$D$2:$D$1000="Agences et Après-vente"))*('Agences & Après-vente'!$I$2:$I$1000="DONE"))>0,"✓",IF(SUMPRODUCT(MAX(('Agences & Après-vente'!$A$2:$A$1000=$A2)*(('Agences & Après-vente'!$D$2:$D$1000="Après-vente")+('Agences & Après-vente'!$D$2:$D$1000="Agences et Après-vente"))*'Agences & Après-vente'!$E$2:$E$1000))>0,TEXT(SUMPRODUCT(MAX(('Agences & Après-vente'!$A$2:$A$1000=$A2)*(('Agences & Après-vente'!$D$2:$D$1000="Après-vente")+('Agences & Après-vente'!$D$2:$D$1000="Agences et Après-vente"))*'Agences & Après-vente'!$E$2:$E$1000)),"yyyy-mm-dd"),"")))))) -> ✓ | K2: =IF($U2="✓","✓",IF(ISNUMBER($U2),TEXT($U2,"yyyy-mm-dd"),IF($D2="Lisbonne","",IF($A2="","",IF(SUMPRODUCT((Evermont!$A$2:$A$1000=$A2)*(Evermont!$Q$2:$Q$1000="Terminé"))>0,"✓",IF(SUMPRODUCT(MAX((Evermont!$A$2:$A$1000=$A2)*Evermont!$F$2:$F$1000))>0,TEXT(SUMPRODUCT(MAX((Evermont!$A$2:$A$1000=$A2)*Evermont!$F$2:$F$1000)),"yyyy-mm-dd"),"")))))) | L2: =IF($A2="","",COUNTIF(E2:K2,"✓")) -> 6 | M2: Active | O2: ✓ | P2: ✓ | Q2: ✓ | R2: ✓ | S2: ✓ | T2: ✓ | W2: =IF($A2="","",IF($X2<>"",$X2,IFERROR(INDEX('Formation Initiale'!$B$2:$B$999,MATCH($A2,'Formation Initiale'!$A$2:$A$999,0)),"Général"))) -> Général
A3: TR002 | B3: Rownvale | C3: Rownmere Fenon Doric | D3: Montréal | E3: =IF($O3="✓","✓",IF(ISNUMBER($O3),TEXT($O3,"yyyy-mm-dd"),IF($A3="","",IF(SUMPRODUCT(('Formation Initiale'!$A$2:$A$999=$A3)*('Formation Initiale'!$R$2:$R$999="Terminé"))>0,"✓",IF(SUMPRODUCT(MAX(('Formation Initiale'!$A$2:$A$999=$A3)*'Formation Initiale'!$G$2:$G$999))>0,TEXT(SUMPRODUCT(MAX(('Formation Initiale'!$A$2:$A$999=$A3)*'Formation Initiale'!$G$2:$G$999)),"yyyy-mm-dd"),""))))) -> ✓ | F3: =IF($P3="✓","✓",IF(ISNUMBER($P3),TEXT($P3,"yyyy-mm-dd"),IF($A3="","",IF($D3="Lisbonne","",IF(SUMPRODUCT(('Formation Initiale'!$A$2:$A$999=$A3)*('Formation Initiale'!$R$2:$R$999="Terminé"))>0,"✓",IF(SUMPRODUCT(MAX(('Formation Initiale'!$A$2:$A$999=$A3)*'Formation Initiale'!$G$2:$G$999))>0,TEXT(SUMPRODUCT(MAX(('Formation Initiale'!$A$2:$A$999=$A3)*'Formation Initiale'!$G$2:$G$999)),"yyyy-mm-dd"),"")))))) -> ✓ | G3: =IF($Q3="✓","✓",IF(ISNUMBER($Q3),TEXT($Q3,"yyyy-mm-dd"),IF($A3="","",IF(SUMPRODUCT(('Agences & Après-vente'!$A$2:$A$1000=$A3)*(('Agences & Après-vente'!$D$2:$D$1000="Agences")+('Agences & Après-vente'!$D$2:$D$1000="Agences et Après-vente"))*('Agences & Après-vente'!$I$2:$I$1000="DONE"))>0,"✓",IF(SUMPRODUCT(MAX(('Agences & Après-vente'!$A$2:$A$1000=$A3)*(('Agences & Après-vente'!$D$2:$D$1000="Agences")+('Agences & Après-vente'!$D$2:$D$1000="Agences et Après-vente"))*'Agences & Après-vente'!$E$2:$E$1000))>0,TEXT(SUMPRODUCT(MAX(('Agences & Après-vente'!$A$2:$A$1000=$A3)*(('Agences & Après-vente'!$D$2:$D$1000="Agences")+('Agences & Après-vente'!$D$2:$D$1000="Agences et Après-vente"))*'Agences & Après-vente'!$E$2:$E$1000)),"yyyy-mm-dd"),""))))) -> ✓ | H3: =IF($R3="✓","✓",IF(ISNUMBER($R3),TEXT($R3,"yyyy-mm-dd"),IF($A3="","",IF($D3="Lisbonne","",IF(SUMPRODUCT(('Agences & Après-vente'!$A$2:$A$1000=$A3)*(('Agences & Après-vente'!$D$2:$D$1000="Agences")+('Agences & Après-vente'!$D$2:$D$1000="Agences et Après-vente"))*('Agences & Après-vente'!$I$2:$I$1000="DONE"))>0,"✓",IF(SUMPRODUCT(MAX(('Agences & Après-vente'!$A$2:$A$1000=$A3)*(('Agences & Après-vente'!$D$2:$D$1000="Agences")+('Agences & Après-vente'!$D$2:$D$1000="Agences et Après-vente"))*'Agences & Après-vente'!$E$2:$E$1000))>0,TEXT(SUMPRODUCT(MAX(('Agences & Après-vente'!$A$2:$A$1000=$A3)*(('Agences & Après-vente'!$D$2:$D$1000="Agences")+('Agences & Après-vente'!$D$2:$D$1000="Agences et Après-vente"))*'Agences & Après-vente'!$E$2:$E$1000)),"yyyy-mm-dd"),"")))))) -> ✓ | I3: =IF($S3="✓","✓",IF(ISNUMBER($S3),TEXT($S3,"yyyy-mm-dd"),IF($A3="","",IF(SUMPRODUCT(('Agences & Après-vente'!$A$2:$A$1000=$A3)*(('Agences & Après-vente'!$D$2:$D$1000="Après-vente")+('Agences & Après-vente'!$D$2:$D$1000="Agences et Après-vente"))*('Agences & Après-vente'!$I$2:$I$1000="DONE"))>0,"✓",IF(SUMPRODUCT(MAX(('Agences & Après-vente'!$A$2:$A$1000=$A3)*(('Agences & Après-vente'!$D$2:$D$1000="Après-vente")+('Agences & Après-vente'!$D$2:$D$1000="Agences et Après-vente"))*'Agences & Après-vente'!$E$2:$E$1000))>0,TEXT(SUMPRODUCT(MAX(('Agences & Après-vente'!$A$2:$A$1000=$A3)*(('Agences & Après-vente'!$D$2:$D$1000="Après-vente")+('Agences & Après-vente'!$D$2:$D$1000="Agences et Après-vente"))*'Agences & Après-vente'!$E$2:$E$1000)),"yyyy-mm-dd"),""))))) -> ✓ | J3: =IF($T3="✓","✓",IF(ISNUMBER($T3),TEXT($T3,"yyyy-mm-dd"),IF($A3="","",IF($D3="Lisbonne","",IF(SUMPRODUCT(('Agences & Après-vente'!$A$2:$A$1000=$A3)*(('Agences & Après-vente'!$D$2:$D$1000="Après-vente")+('Agences & Après-vente'!$D$2:$D$1000="Agences et Après-vente"))*('Agences & Après-vente'!$I$2:$I$1000="DONE"))>0,"✓",IF(SUMPRODUCT(MAX(('Agences & Après-vente'!$A$2:$A$1000=$A3)*(('Agences & Après-vente'!$D$2:$D$1000="Après-vente")+('Agences & Après-vente'!$D$2:$D$1000="Agences et Après-vente"))*'Agences & Après-vente'!$E$2:$E$1000))>0,TEXT(SUMPRODUCT(MAX(('Agences & Après-vente'!$A$2:$A$1000=$A3)*(('Agences & Après-vente'!$D$2:$D$1000="Après-vente")+('Agences & Après-vente'!$D$2:$D$1000="Agences et Après-vente"))*'Agences & Après-vente'!$E$2:$E$1000)),"yyyy-mm-dd"),"")))))) -> ✓ | K3: =IF($U3="✓","✓",IF(ISNUMBER($U3),TEXT($U3,"yyyy-mm-dd"),IF($D3="Lisbonne","",IF($A3="","",IF(SUMPRODUCT((Evermont!$A$2:$A$1000=$A3)*(Evermont!$Q$2:$Q$1000="Terminé"))>0,"✓",IF(SUMPRODUCT(MAX((Evermont!$A$2:$A$1000=$A3)*Evermont!$F$2:$F$1000))>0,TEXT(SUMPRODUCT(MAX((Evermont!$A$2:$A$1000=$A3)*Evermont!$F$2:$F$1000)),"yyyy-mm-dd"),"")))))) -> ✓ | L3: =IF($A3="","",COUNTIF(E3:K3,"✓")) -> 7 | M3: Active | O3: ✓ | P3: ✓ | Q3: ✓ | R3: ✓ | S3: ✓ | T3: ✓ | U3: ✓ | W3: =IF($A3="","",IF($X3<>"",$X3,IFERROR(INDEX('Formation Initiale'!$B$2:$B$999,MATCH($A3,'Formation Initiale'!$A$2:$A$999,0)),"Général"))) -> Général
A4: TR003 | B4: Kendfield | C4: Moran Lumith | D4: Montréal | E4: =IF($O4="✓","✓",IF(ISNUMBER($O4),TEXT($O4,"yyyy-mm-dd"),IF($A4="","",IF(SUMPRODUCT(('Formation Initiale'!$A$2:$A$999=$A4)*('Formation Initiale'!$R$2:$R$999="Terminé"))>0,"✓",IF(SUMPRODUCT(MAX(('Formation Initiale'!$A$2:$A$999=$A4)*'Formation Initiale'!$G$2:$G$999))>0,TEXT(SUMPRODUCT(MAX(('Formation Initiale'!$A$2:$A$999=$A4)*'Formation Initiale'!$G$2:$G$999)),"yyyy-mm-dd"),""))))) -> ✓ | F4: =IF($P4="✓","✓",IF(ISNUMBER($P4),TEXT($P4,"yyyy-mm-dd"),IF($A4="","",IF($D4="Lisbonne","",IF(SUMPRODUCT(('Formation Initiale'!$A$2:$A$999=$A4)*('Formation Initiale'!$R$2:$R$999="Terminé"))>0,"✓",IF(SUMPRODUCT(MAX(('Formation Initiale'!$A$2:$A$999=$A4)*'Formation Initiale'!$G$2:$G$999))>0,TEXT(SUMPRODUCT(MAX(('Formation Initiale'!$A$2:$A$999=$A4)*'Formation Initiale'!$G$2:$G$999)),"yyyy-mm-dd"),"")))))) -> ✓ | G4: =IF($Q4="✓","✓",IF(ISNUMBER($Q4),TEXT($Q4,"yyyy-mm-dd"),IF($A4="","",IF(SUMPRODUCT(('Agences & Après-vente'!$A$2:$A$1000=$A4)*(('Agences & Après-vente'!$D$2:$D$1000="Agences")+('Agences & Après-vente'!$D$2:$D$1000="Agences et Après-vente"))*('Agences & Après-vente'!$I$2:$I$1000="DONE"))>0,"✓",IF(SUMPRODUCT(MAX(('Agences & Après-vente'!$A$2:$A$1000=$A4)*(('Agences & Après-vente'!$D$2:$D$1000="Agences")+('Agences & Après-vente'!$D$2:$D$1000="Agences et Après-vente"))*'Agences & Après-vente'!$E$2:$E$1000))>0,TEXT(SUMPRODUCT(MAX(('Agences & Après-vente'!$A$2:$A$1000=$A4)*(('Agences & Après-vente'!$D$2:$D$1000="Agences")+('Agences & Après-vente'!$D$2:$D$1000="Agences et Après-vente"))*'Agences & Après-vente'!$E$2:$E$1000)),"yyyy-mm-dd"),""))))) -> ✓ | H4: =IF($R4="✓","✓",IF(ISNUMBER($R4),TEXT($R4,"yyyy-mm-dd"),IF($A4="","",IF($D4="Lisbonne","",IF(SUMPRODUCT(('Agences & Après-vente'!$A$2:$A$1000=$A4)*(('Agences & Après-vente'!$D$2:$D$1000="Agences")+('Agences & Après-vente'!$D$2:$D$1000="Agences et Après-vente"))*('Agences & Après-vente'!$I$2:$I$1000="DONE"))>0,"✓",IF(SUMPRODUCT(MAX(('Agences & Après-vente'!$A$2:$A$1000=$A4)*(('Agences & Après-vente'!$D$2:$D$1000="Agences")+('Agences & Après-vente'!$D$2:$D$1000="Agences et Après-vente"))*'Agences & Après-vente'!$E$2:$E$1000))>0,TEXT(SUMPRODUCT(MAX(('Agences & Après-vente'!$A$2:$A$1000=$A4)*(('Agences & Après-vente'!$D$2:$D$1000="Agences")+('Agences & Après-vente'!$D$2:$D$1000="Agences et Après-vente"))*'Agences & Après-vente'!$E$2:$E$1000)),"yyyy-mm-dd"),"")))))) -> ✓ | I4: =IF($S4="✓","✓",IF(ISNUMBER($S4),TEXT($S4,"yyyy-mm-dd"),IF($A4="","",IF(SUMPRODUCT(('Agences & Après-vente'!$A$2:$A$1000=$A4)*(('Agences & Après-vente'!$D$2:$D$1000="Après-vente")+('Agences & Après-vente'!$D$2:$D$1000="Agences et Après-vente"))*('Agences & Après-vente'!$I$2:$I$1000="DONE"))>0,"✓",IF(SUMPRODUCT(MAX(('Agences & Après-vente'!$A$2:$A$1000=$A4)*(('Agences & Après-vente'!$D$2:$D$1000="Après-vente")+('Agences & Après-vente'!$D$2:$D$1000="Agences et Après-vente"))*'Agences & Après-vente'!$E$2:$E$1000))>0,TEXT(SUMPRODUCT(MAX(('Agences & Après-vente'!$A$2:$A$1000=$A4)*(('Agences & Après-vente'!$D$2:$D$1000="Après-vente")+('Agences & Après-vente'!$D$2:$D$1000="Agences et Après-vente"))*'Agences & Après-vente'!$E$2:$E$1000)),"yyyy-mm-dd"),""))))) -> ✓ | J4: =IF($T4="✓","✓",IF(ISNUMBER($T4),TEXT($T4,"yyyy-mm-dd"),IF($A4="","",IF($D4="Lisbonne","",IF(SUMPRODUCT(('Agences & Après-vente'!$A$2:$A$1000=$A4)*(('Agences & Après-vente'!$D$2:$D$1000="Après-vente")+('Agences & Après-vente'!$D$2:$D$1000="Agences et Après-vente"))*('Agences & Après-vente'!$I$2:$I$1000="DONE"))>0,"✓",IF(SUMPRODUCT(MAX(('Agences & Après-vente'!$A$2:$A$1000=$A4)*(('Agences & Après-vente'!$D$2:$D$1000="Après-vente")+('Agences & Après-vente'!$D$2:$D$1000="Agences et Après-vente"))*'Agences & Après-vente'!$E$2:$E$1000))>0,TEXT(SUMPRODUCT(MAX(('Agences & Après-vente'!$A$2:$A$1000=$A4)*(('Agences & Après-vente'!$D$2:$D$1000="Après-vente")+('Agences & Après-vente'!$D$2:$D$1000="Agences et Après-vente"))*'Agences & Après-vente'!$E$2:$E$1000)),"yyyy-mm-dd"),"")))))) -> ✓ | K4: =IF($U4="✓","✓",IF(ISNUMBER($U4),TEXT($U4,"yyyy-mm-dd"),IF($D4="Lisbonne","",IF($A4="","",IF(SUMPRODUCT((Evermont!$A$2:$A$1000=$A4)*(Evermont!$Q$2:$Q$1000="Terminé"))>0,"✓",IF(SUMPRODUCT(MAX((Evermont!$A$2:$A$1000=$A4)*Evermont!$F$2:$F$1000))>0,TEXT(SUMPRODUCT(MAX((Evermont!$A$2:$A$1000=$A4)*Evermont!$F$2:$F$1000)),"yyyy-mm-dd"),"")))))) -> ✓ | L4: =IF($A4="","",COUNTIF(E4:K4,"✓")) -> 7 | M4: Active | O4: ✓ | P4: ✓ | W4: =IF($A4="","",IF($X4<>"",$X4,IFERROR(INDEX('Formation Initiale'!$B$2:$B$999,MATCH($A4,'Formation Initiale'!$A$2:$A$999,0)),"Général"))) -> Général
A5: TR004 | B5: Brambrook Holtfield | C5: Marsfield | D5: Montréal | E5: =IF($O5="✓","✓",IF(ISNUMBER($O5),TEXT($O5,"yyyy-mm-dd"),IF($A5="","",IF(SUMPRODUCT(('Formation Initiale'!$A$2:$A$999=$A5)*('Formation Initiale'!$R$2:$R$999="Terminé"))>0,"✓",IF(SUMPRODUCT(MAX(('Formation Initiale'!$A$2:$A$999=$A5)*'Formation Initiale'!$G$2:$G$999))>0,TEXT(SUMPRODUCT(MAX(('Formation Initiale'!$A$2:$A$999=$A5)*'Formation Initiale'!$G$2:$G$999)),"yyyy-mm-dd"),""))))) -> ✓ | F5: =IF($P5="✓","✓",IF(ISNUMBER($P5),TEXT($P5,"yyyy-mm-dd"),IF($A5="","",IF($D5="Lisbonne","",IF(SUMPRODUCT(('Formation Initiale'!$A$2:$A$999=$A5)*('Formation Initiale'!$R$2:$R$999="Terminé"))>0,"✓",IF(SUMPRODUCT(MAX(('Formation Initiale'!$A$2:$A$999=$A5)*'Formation Initiale'!$G$2:$G$999))>0,TEXT(SUMPRODUCT(MAX(('Formation Initiale'!$A$2:$A$999=$A5)*'Formation Initiale'!$G$2:$G$999)),"yyyy-mm-dd"),"")))))) -> ✓ | G5: =IF($Q5="✓","✓",IF(ISNUMBER($Q5),TEXT($Q5,"yyyy-mm-dd"),IF($A5="","",IF(SUMPRODUCT(('Agences & Après-vente'!$A$2:$A$1000=$A5)*(('Agences & Après-vente'!$D$2:$D$1000="Agences")+('Agences & Après-vente'!$D$2:$D$1000="Agences et Après-vente"))*('Agences & Après-vente'!$I$2:$I$1000="DONE"))>0,"✓",IF(SUMPRODUCT(MAX(('Agences & Après-vente'!$A$2:$A$1000=$A5)*(('Agences & Après-vente'!$D$2:$D$1000="Agences")+('Agences & Après-vente'!$D$2:$D$1000="Agences et Après-vente"))*'Agences & Après-vente'!$E$2:$E$1000))>0,TEXT(SUMPRODUCT(MAX(('Agences & Après-vente'!$A$2:$A$1000=$A5)*(('Agences & Après-vente'!$D$2:$D$1000="Agences")+('Agences & Après-vente'!$D$2:$D$1000="Agences et Après-vente"))*'Agences & Après-vente'!$E$2:$E$1000)),"yyyy-mm-dd"),""))))) -> ✓ | H5: =IF($R5="✓","✓",IF(ISNUMBER($R5),TEXT($R5,"yyyy-mm-dd"),IF($A5="","",IF($D5="Lisbonne","",IF(SUMPRODUCT(('Agences & Après-vente'!$A$2:$A$1000=$A5)*(('Agences & Après-vente'!$D$2:$D$1000="Agences")+('Agences & Après-vente'!$D$2:$D$1000="Agences et Après-vente"))*('Agences & Après-vente'!$I$2:$I$1000="DONE"))>0,"✓",IF(SUMPRODUCT(MAX(('Agences & Après-vente'!$A$2:$A$1000=$A5)*(('Agences & Après-vente'!$D$2:$D$1000="Agences")+('Agences & Après-vente'!$D$2:$D$1000="Agences et Après-vente"))*'Agences & Après-vente'!$E$2:$E$1000))>0,TEXT(SUMPRODUCT(MAX(('Agences & Après-vente'!$A$2:$A$1000=$A5)*(('Agences & Après-vente'!$D$2:$D$1000="Agences")+('Agences & Après-vente'!$D$2:$D$1000="Agences et Après-vente"))*'Agences & Après-vente'!$E$2:$E$1000)),"yyyy-mm-dd"),"")))))) -> ✓ | I5: =IF($S5="✓","✓",IF(ISNUMBER($S5),TEXT($S5,"yyyy-mm-dd"),IF($A5="","",IF(SUMPRODUCT(('Agences & Après-vente'!$A$2:$A$1000=$A5)*(('Agences & Après-vente'!$D$2:$D$1000="Après-vente")+('Agences & Après-vente'!$D$2:$D$1000="Agences et Après-vente"))*('Agences & Après-vente'!$I$2:$I$1000="DONE"))>0,"✓",IF(SUMPRODUCT(MAX(('Agences & Après-vente'!$A$2:$A$1000=$A5)*(('Agences & Après-vente'!$D$2:$D$1000="Après-vente")+('Agences & Après-vente'!$D$2:$D$1000="Agences et Après-vente"))*'Agences & Après-vente'!$E$2:$E$1000))>0,TEXT(SUMPRODUCT(MAX(('Agences & Après-vente'!$A$2:$A$1000=$A5)*(('Agences & Après-vente'!$D$2:$D$1000="Après-vente")+('Agences & Après-vente'!$D$2:$D$1000="Agences et Après-vente"))*'Agences & Après-vente'!$E$2:$E$1000)),"yyyy-mm-dd"),""))))) -> ✓ | J5: =IF($T5="✓","✓",IF(ISNUMBER($T5),TEXT($T5,"yyyy-mm-dd"),IF($A5="","",IF($D5="Lisbonne","",IF(SUMPRODUCT(('Agences & Après-vente'!$A$2:$A$1000=$A5)*(('Agences & Après-vente'!$D$2:$D$1000="Après-vente")+('Agences & Après-vente'!$D$2:$D$1000="Agences et Après-vente"))*('Agences & Après-vente'!$I$2:$I$1000="DONE"))>0,"✓",IF(SUMPRODUCT(MAX(('Agences & Après-vente'!$A$2:$A$1000=$A5)*(('Agences & Après-vente'!$D$2:$D$1000="Après-vente")+('Agences & Après-vente'!$D$2:$D$1000="Agences et Après-vente"))*'Agences & Après-vente'!$E$2:$E$1000))>0,TEXT(SUMPRODUCT(MAX(('Agences & Après-vente'!$A$2:$A$1000=$A5)*(('Agences & Après-vente'!$D$2:$D$1000="Après-vente")+('Agences & Après-vente'!$D$2:$D$1000="Agences et Après-vente"))*'Agences & Après-vente'!$E$2:$E$1000)),"yyyy-mm-dd"),"")))))) -> ✓ | K5: =IF($U5="✓","✓",IF(ISNUMBER($U5),TEXT($U5,"yyyy-mm-dd"),IF($D5="Lisbonne","",IF($A5="","",IF(SUMPRODUCT((Evermont!$A$2:$A$1000=$A5)*(Evermont!$Q$2:$Q$1000="Terminé"))>0,"✓",IF(SUMPRODUCT(MAX((Evermont!$A$2:$A$1000=$A5)*Evermont!$F$2:$F$1000))>0,TEXT(SUMPRODUCT(MAX((Evermont!$A$2:$A$1000=$A5)*Evermont!$F$2:$F$1000)),"yyyy-mm-dd"),"")))))) -> ✓ | L5: =IF($A5="","",COUNTIF(E5:K5,"✓")) -> 7 | M5: Active | O5: ✓ | P5: ✓ | Q5: ✓ | R5: ✓ | S5: ✓ | T5: ✓ | U5: ✓ | W5: =IF($A5="","",IF($X5<>"",$X5,IFERROR(INDEX('Formation Initiale'!$B$2:$B$999,MATCH($A5,'Formation Initiale'!$A$2:$A$999,0)),"Général"))) -> Général
A6: TR005 | B6: Dellshaw | C6: Gilith | D6: Lisbonne | E6: =IF($O6="✓","✓",IF(ISNUMBER($O6),TEXT($O6,"yyyy-mm-dd"),IF($A6="","",IF(SUMPRODUCT(('Formation Initiale'!$A$2:$A$999=$A6)*('Formation Initiale'!$R$2:$R$999="Terminé"))>0,"✓",IF(SUMPRODUCT(MAX(('Formation Initiale'!$A$2:$A$999=$A6)*'Formation Initiale'!$G$2:$G$999))>0,TEXT(SUMPRODUCT(MAX(('Formation Initiale'!$A$2:$A$999=$A6)*'Formation Initiale'!$G$2:$G$999)),"yyyy-mm-dd"),""))))) -> ✓ | F6: =IF($P6="✓","✓",IF(ISNUMBER($P6),TEXT($P6,"yyyy-mm-dd"),IF($A6="","",IF($D6="Lisbonne","",IF(SUMPRODUCT(('Formation Initiale'!$A$2:$A$999=$A6)*('Formation Initiale'!$R$2:$R$999="Terminé"))>0,"✓",IF(SUMPRODUCT(MAX(('Formation Initiale'!$A$2:$A$999=$A6)*'Formation Initiale'!$G$2:$G$999))>0,TEXT(SUMPRODUCT(MAX(('Formation Initiale'!$A$2:$A$999=$A6)*'Formation Initiale'!$G$2:$G$999)),"yyyy-mm-dd"),"")))))) | G6: =IF($Q6="✓","✓",IF(ISNUMBER($Q6),TEXT($Q6,"yyyy-mm-dd"),IF($A6="","",IF(SUMPRODUCT(('Agences & Après-vente'!$A$2:$A$1000=$A6)*(('Agences & Après-vente'!$D$2:$D$1000="Agences")+('Agences & Après-vente'!$D$2:$D$1000="Agences et Après-vente"))*('Agences & Après-vente'!$I$2:$I$1000="DONE"))>0,"✓",IF(SUMPRODUCT(MAX(('Agences & Après-vente'!$A$2:$A$1000=$A6)*(('Agences & Après-vente'!$D$2:$D$1000="Agences")+('Agences & Après-vente'!$D$2:$D$1000="Agences et Après-vente"))*'Agences & Après-vente'!$E$2:$E$1000))>0,TEXT(SUMPRODUCT(MAX(('Agences & Après-vente'!$A$2:$A$1000=$A6)*(('Agences & Après-vente'!$D$2:$D$1000="Agences")+('Agences & Après-vente'!$D$2:$D$1000="Agences et Après-vente"))*'Agences & Après-vente'!$E$2:$E$1000)),"yyyy-mm-dd"),""))))) | H6: =IF($R6="✓","✓",IF(ISNUMBER($R6),TEXT($R6,"yyyy-mm-dd"),IF($A6="","",IF($D6="Lisbonne","",IF(SUMPRODUCT(('Agences & Après-vente'!$A$2:$A$1000=$A6)*(('Agences & Après-vente'!$D$2:$D$1000="Agences")+('Agences & Après-vente'!$D$2:$D$1000="Agences et Après-vente"))*('Agences & Après-vente'!$I$2:$I$1000="DONE"))>0,"✓",IF(SUMPRODUCT(MAX(('Agences & Après-vente'!$A$2:$A$1000=$A6)*(('Agences & Après-vente'!$D$2:$D$1000="Agences")+('Agences & Après-vente'!$D$2:$D$1000="Agences et Après-vente"))*'Agences & Après-vente'!$E$2:$E$1000))>0,TEXT(SUMPRODUCT(MAX(('Agences & Après-vente'!$A$2:$A$1000=$A6)*(('Agences & Après-vente'!$D$2:$D$1000="Agences")+('Agences & Après-vente'!$D$2:$D$1000="Agences et Après-vente"))*'Agences & Après-vente'!$E$2:$E$1000)),"yyyy-mm-dd"),"")))))) | I6: =IF($S6="✓","✓",IF(ISNUMBER($S6),TEXT($S6,"yyyy-mm-dd"),IF($A6="","",IF(SUMPRODUCT(('Agences & Après-vente'!$A$2:$A$1000=$A6)*(('Agences & Après-vente'!$D$2:$D$1000="Après-vente")+('Agences & Après-vente'!$D$2:$D$1000="Agences et Après-vente"))*('Agences & Après-vente'!$I$2:$I$1000="DONE"))>0,"✓",IF(SUMPRODUCT(MAX(('Agences & Après-vente'!$A$2:$A$1000=$A6)*(('Agences & Après-vente'!$D$2:$D$1000="Après-vente")+('Agences & Après-vente'!$D$2:$D$1000="Agences et Après-vente"))*'Agences & Après-vente'!$E$2:$E$1000))>0,TEXT(SUMPRODUCT(MAX(('Agences & Après-vente'!$A$2:$A$1000=$A6)*(('Agences & Après-vente'!$D$2:$D$1000="Après-vente")+('Agences & Après-vente'!$D$2:$D$1000="Agences et Après-vente"))*'Agences & Après-vente'!$E$2:$E$1000)),"yyyy-mm-dd"),""))))) | J6: =IF($T6="✓","✓",IF(ISNUMBER($T6),TEXT($T6,"yyyy-mm-dd"),IF($A6="","",IF($D6="Lisbonne","",IF(SUMPRODUCT(('Agences & Après-vente'!$A$2:$A$1000=$A6)*(('Agences & Après-vente'!$D$2:$D$1000="Après-vente")+('Agences & Après-vente'!$D$2:$D$1000="Agences et Après-vente"))*('Agences & Après-vente'!$I$2:$I$1000="DONE"))>0,"✓",IF(SUMPRODUCT(MAX(('Agences & Après-vente'!$A$2:$A$1000=$A6)*(('Agences & Après-vente'!$D$2:$D$1000="Après-vente")+('Agences & Après-vente'!$D$2:$D$1000="Agences et Après-vente"))*'Agences & Après-vente'!$E$2:$E$1000))>0,TEXT(SUMPRODUCT(MAX(('Agences & Après-vente'!$A$2:$A$1000=$A6)*(('Agences & Après-vente'!$D$2:$D$1000="Après-vente")+('Agences & Après-vente'!$D$2:$D$1000="Agences et Après-vente"))*'Agences & Après-vente'!$E$2:$E$1000)),"yyyy-mm-dd"),"")))))) | K6: =IF($U6="✓","✓",IF(ISNUMBER($U6),TEXT($U6,"yyyy-mm-dd"),IF($D6="Lisbonne","",IF($A6="","",IF(SUMPRODUCT((Evermont!$A$2:$A$1000=$A6)*(Evermont!$Q$2:$Q$1000="Terminé"))>0,"✓",IF(SUMPRODUCT(MAX((Evermont!$A$2:$A$1000=$A6)*Evermont!$F$2:$F$1000))>0,TEXT(SUMPRODUCT(MAX((Evermont!$A$2:$A$1000=$A6)*Evermont!$F$2:$F$1000)),"yyyy-mm-dd"),"")))))) | L6: =IF($A6="","",COUNTIF(E6:K6,"✓")) -> 1 | M6: Active | O6: ✓ | W6: =IF($A6="","",IF($X6<>"",$X6,IFERROR(INDEX('Formation Initiale'!$B$2:$B$999,MATCH($A6,'Formation Initiale'!$A$2:$A$999,0)),"Général"))) -> OS7
A7: TR006 | B7: Quillbrook | C7: Iverfield | D7: Montréal | E7: =IF($O7="✓","✓",IF(ISNUMBER($O7),TEXT($O7,"yyyy-mm-dd"),IF($A7="","",IF(SUMPRODUCT(('Formation Initiale'!$A$2:$A$999=$A7)*('Formation Initiale'!$R$2:$R$999="Terminé"))>0,"✓",IF(SUMPRODUCT(MAX(('Formation Initiale'!$A$2:$A$999=$A7)*'Formation Initiale'!$G$2:$G$999))>0,TEXT(SUMPRODUCT(MAX(('Formation Initiale'!$A$2:$A$999=$A7)*'Formation Initiale'!$G$2:$G$999)),"yyyy-mm-dd"),""))))) -> ✓ | F7: =IF($P7="✓","✓",IF(ISNUMBER($P7),TEXT($P7,"yyyy-mm-dd"),IF($A7="","",IF($D7="Lisbonne","",IF(SUMPRODUCT(('Formation Initiale'!$A$2:$A$999=$A7)*('Formation Initiale'!$R$2:$R$999="Terminé"))>0,"✓",IF(SUMPRODUCT(MAX(('Formation Initiale'!$A$2:$A$999=$A7)*'Formation Initiale'!$G$2:$G$999))>0,TEXT(SUMPRODUCT(MAX(('Formation Initiale'!$A$2:$A$999=$A7)*'Formation Initiale'!$G$2:$G$999)),"yyyy-mm-dd"),"")))))) -> ✓ | G7: =IF($Q7="✓","✓",IF(ISNUMBER($Q7),TEXT($Q7,"yyyy-mm-dd"),IF($A7="","",IF(SUMPRODUCT(('Agences & Après-vente'!$A$2:$A$1000=$A7)*(('Agences & Après-vente'!$D$2:$D$1000="Agences")+('Agences & Après-vente'!$D$2:$D$1000="Agences et Après-vente"))*('Agences & Après-vente'!$I$2:$I$1000="DONE"))>0,"✓",IF(SUMPRODUCT(MAX(('Agences & Après-vente'!$A$2:$A$1000=$A7)*(('Agences & Après-vente'!$D$2:$D$1000="Agences")+('Agences & Après-vente'!$D$2:$D$1000="Agences et Après-vente"))*'Agences & Après-vente'!$E$2:$E$1000))>0,TEXT(SUMPRODUCT(MAX(('Agences & Après-vente'!$A$2:$A$1000=$A7)*(('Agences & Après-vente'!$D$2:$D$1000="Agences")+('Agences & Après-vente'!$D$2:$D$1000="Agences et Après-vente"))*'Agences & Après-vente'!$E$2:$E$1000)),"yyyy-mm-dd"),""))))) -> ✓ | H7: =IF($R7="✓","✓",IF(ISNUMBER($R7),TEXT($R7,"yyyy-mm-dd"),IF($A7="","",IF($D7="Lisbonne","",IF(SUMPRODUCT(('Agences & Après-vente'!$A$2:$A$1000=$A7)*(('Agences & Après-vente'!$D$2:$D$1000="Agences")+('Agences & Après-vente'!$D$2:$D$1000="Agences et Après-vente"))*('Agences & Après-vente'!$I$2:$I$1000="DONE"))>0,"✓",IF(SUMPRODUCT(MAX(('Agences & Après-vente'!$A$2:$A$1000=$A7)*(('Agences & Après-vente'!$D$2:$D$1000="Agences")+('Agences & Après-vente'!$D$2:$D$1000="Agences et Après-vente"))*'Agences & Après-vente'!$E$2:$E$1000))>0,TEXT(SUMPRODUCT(MAX(('Agences & Après-vente'!$A$2:$A$1000=$A7)*(('Agences & Après-vente'!$D$2:$D$1000="Agences")+('Agences & Après-vente'!$D$2:$D$1000="Agences et Après-vente"))*'Agences & Après-vente'!$E$2:$E$1000)),"yyyy-mm-dd"),"")))))) -> ✓ | I7: =IF($S7="✓","✓",IF(ISNUMBER($S7),TEXT($S7,"yyyy-mm-dd"),IF($A7="","",IF(SUMPRODUCT(('Agences & Après-vente'!$A$2:$A$1000=$A7)*(('Agences & Après-vente'!$D$2:$D$1000="Après-vente")+('Agences & Après-vente'!$D$2:$D$1000="Agences et Après-vente"))*('Agences & Après-vente'!$I$2:$I$1000="DONE"))>0,"✓",IF(SUMPRODUCT(MAX(('Agences & Après-vente'!$A$2:$A$1000=$A7)*(('Agences & Après-vente'!$D$2:$D$1000="Après-vente")+('Agences & Après-vente'!$D$2:$D$1000="Agences et Après-vente"))*'Agences & Après-vente'!$E$2:$E$1000))>0,TEXT(SUMPRODUCT(MAX(('Agences & Après-vente'!$A$2:$A$1000=$A7)*(('Agences & Après-vente'!$D$2:$D$1000="Après-vente")+('Agences & Après-vente'!$D$2:$D$1000="Agences et Après-vente"))*'Agences & Après-vente'!$E$2:$E$1000)),"yyyy-mm-dd"),""))))) -> ✓ | J7: =IF($T7="✓","✓",IF(ISNUMBER($T7),TEXT($T7,"yyyy-mm-dd"),IF($A7="","",IF($D7="Lisbonne","",IF(SUMPRODUCT(('Agences & Après-vente'!$A$2:$A$1000=$A7)*(('Agences & Après-vente'!$D$2:$D$1000="Après-vente")+('Agences & Après-vente'!$D$2:$D$1000="Agences et Après-vente"))*('Agences & Après-vente'!$I$2:$I$1000="DONE"))>0,"✓",IF(SUMPRODUCT(MAX(('Agences & Après-vente'!$A$2:$A$1000=$A7)*(('Agences & Après-vente'!$D$2:$D$1000="Après-vente")+('Agences & Après-vente'!$D$2:$D$1000="Agences et Après-vente"))*'Agences & Après-vente'!$E$2:$E$1000))>0,TEXT(SUMPRODUCT(MAX(('Agences & Après-vente'!$A$2:$A$1000=$A7)*(('Agences & Après-vente'!$D$2:$D$1000="Après-vente")+('Agences & Après-vente'!$D$2:$D$1000="Agences et Après-vente"))*'Agences & Après-vente'!$E$2:$E$1000)),"yyyy-mm-dd"),"")))))) -> ✓ | K7: =IF($U7="✓","✓",IF(ISNUMBER($U7),TEXT($U7,"yyyy-mm-dd"),IF($D7="Lisbonne","",IF($A7="","",IF(SUMPRODUCT((Evermont!$A$2:$A$1000=$A7)*(Evermont!$Q$2:$Q$1000="Terminé"))>0,"✓",IF(SUMPRODUCT(MAX((Evermont!$A$2:$A$1000=$A7)*Evermont!$F$2:$F$1000))>0,TEXT(SUMPRODUCT(MAX((Evermont!$A$2:$A$1000=$A7)*Evermont!$F$2:$F$1000)),"yyyy-mm-dd"),"")))))) -> ✓ | L7: =IF($A7="","",COUNTIF(E7:K7,"✓")) -> 7 | M7: Active | O7: ✓ | P7: ✓ | Q7: ✓ | R7: ✓ | S7: ✓ | T7: ✓ | U7: ✓ | W7: =IF($A7="","",IF($X7<>"",$X7,IFERROR(INDEX('Formation Initiale'!$B$2:$B$999,MATCH($A7,'Formation Initiale'!$A$2:$A$999,0)),"Général"))) -> Général
A8: TR007 | B8: Stelfield | C8: Dellmere Valegate | D8: Montréal | E8: =IF($O8="✓","✓",IF(ISNUMBER($O8),TEXT($O8,"yyyy-mm-dd"),IF($A8="","",IF(SUMPRODUCT(('Formation Initiale'!$A$2:$A$999=$A8)*('Formation Initiale'!$R$2:$R$999="Terminé"))>0,"✓",IF(SUMPRODUCT(MAX(('Formation Initiale'!$A$2:$A$999=$A8)*'Formation Initiale'!$G$2:$G$999))>0,TEXT(SUMPRODUCT(MAX(('Formation Initiale'!$A$2:$A$999=$A8)*'Formation Initiale'!$G$2:$G$999)),"yyyy-mm-dd"),""))))) -> ✓ | F8: =IF($P8="✓","✓",IF(ISNUMBER($P8),TEXT($P8,"yyyy-mm-dd"),IF($A8="","",IF($D8="Lisbonne","",IF(SUMPRODUCT(('Formation Initiale'!$A$2:$A$999=$A8)*('Formation Initiale'!$R$2:$R$999="Terminé"))>0,"✓",IF(SUMPRODUCT(MAX(('Formation Initiale'!$A$2:$A$999=$A8)*'Formation Initiale'!$G$2:$G$999))>0,TEXT(SUMPRODUCT(MAX(('Formation Initiale'!$A$2:$A$999=$A8)*'Formation Initiale'!$G$2:$G$999)),"yyyy-mm-dd"),"")))))) -> ✓ | G8: =IF($Q8="✓","✓",IF(ISNUMBER($Q8),TEXT($Q8,"yyyy-mm-dd"),IF($A8="","",IF(SUMPRODUCT(('Agences & Après-vente'!$A$2:$A$1000=$A8)*(('Agences & Après-vente'!$D$2:$D$1000="Agences")+('Agences & Après-vente'!$D$2:$D$1000="Agences et Après-vente"))*('Agences & Après-vente'!$I$2:$I$1000="DONE"))>0,"✓",IF(SUMPRODUCT(MAX(('Agences & Après-vente'!$A$2:$A$1000=$A8)*(('Agences & Après-vente'!$D$2:$D$1000="Agences")+('Agences & Après-vente'!$D$2:$D$1000="Agences et Après-vente"))*'Agences & Après-vente'!$E$2:$E$1000))>0,TEXT(SUMPRODUCT(MAX(('Agences & Après-vente'!$A$2:$A$1000=$A8)*(('Agences & Après-vente'!$D$2:$D$1000="Agences")+('Agences & Après-vente'!$D$2:$D$1000="Agences et Après-vente"))*'Agences & Après-vente'!$E$2:$E$1000)),"yyyy-mm-dd"),""))))) -> ✓ | H8: =IF($R8="✓","✓",IF(ISNUMBER($R8),TEXT($R8,"yyyy-mm-dd"),IF($A8="","",IF($D8="Lisbonne","",IF(SUMPRODUCT(('Agences & Après-vente'!$A$2:$A$1000=$A8)*(('Agences & Après-vente'!$D$2:$D$1000="Agences")+('Agences & Après-vente'!$D$2:$D$1000="Agences et Après-vente"))*('Agences & Après-vente'!$I$2:$I$1000="DONE"))>0,"✓",IF(SUMPRODUCT(MAX(('Agences & Après-vente'!$A$2:$A$1000=$A8)*(('Agences & Après-vente'!$D$2:$D$1000="Agences")+('Agences & Après-vente'!$D$2:$D$1000="Agences et Après-vente"))*'Agences & Après-vente'!$E$2:$E$1000))>0,TEXT(SUMPRODUCT(MAX(('Agences & Après-vente'!$A$2:$A$1000=$A8)*(('Agences & Après-vente'!$D$2:$D$1000="Agences")+('Agences & Après-vente'!$D$2:$D$1000="Agences et Après-vente"))*'Agences & Après-vente'!$E$2:$E$1000)),"yyyy-mm-dd"),"")))))) -> ✓ | I8: =IF($S8="✓","✓",IF(ISNUMBER($S8),TEXT($S8,"yyyy-mm-dd"),IF($A8="","",IF(SUMPRODUCT(('Agences & Après-vente'!$A$2:$A$1000=$A8)*(('Agences & Après-vente'!$D$2:$D$1000="Après-vente")+('Agences & Après-vente'!$D$2:$D$1000="Agences et Après-vente"))*('Agences & Après-vente'!$I$2:$I$1000="DONE"))>0,"✓",IF(SUMPRODUCT(MAX(('Agences & Après-vente'!$A$2:$A$1000=$A8)*(('Agences & Après-vente'!$D$2:$D$1000="Après-vente")+('Agences & Après-vente'!$D$2:$D$1000="Agences et Après-vente"))*'Agences & Après-vente'!$E$2:$E$1000))>0,TEXT(SUMPRODUCT(MAX(('Agences & Après-vente'!$A$2:$A$1000=$A8)*(('Agences & Après-vente'!$D$2:$D$1000="Après-vente")+('Agences & Après-vente'!$D$2:$D$1000="Agences et Après-vente"))*'Agences & Après-vente'!$E$2:$E$1000)),"yyyy-mm-dd"),""))))) -> ✓ | J8: =IF($T8="✓","✓",IF(ISNUMBER($T8),TEXT($T8,"yyyy-mm-dd"),IF($A8="","",IF($D8="Lisbonne","",IF(SUMPRODUCT(('Agences & Après-vente'!$A$2:$A$1000=$A8)*(('Agences & Après-vente'!$D$2:$D$1000="Après-vente")+('Agences & Après-vente'!$D$2:$D$1000="Agences et Après-vente"))*('Agences & Après-vente'!$I$2:$I$1000="DONE"))>0,"✓",IF(SUMPRODUCT(MAX(('Agences & Après-vente'!$A$2:$A$1000=$A8)*(('Agences & Après-vente'!$D$2:$D$1000="Après-vente")+('Agences & Après-vente'!$D$2:$D$1000="Agences et Après-vente"))*'Agences & Après-vente'!$E$2:$E$1000))>0,TEXT(SUMPRODUCT(MAX(('Agences & Après-vente'!$A$2:$A$1000=$A8)*(('Agences & Après-vente'!$D$2:$D$1000="Après-vente")+('Agences & Après-vente'!$D$2:$D$1000="Agences et Après-vente"))*'Agences & Après-vente'!$E$2:$E$1000)),"yyyy-mm-dd"),"")))))) -> ✓ | K8: =IF($U8="✓","✓",IF(ISNUMBER($U8),TEXT($U8,"yyyy-mm-dd"),IF($D8="Lisbonne","",IF($A8="","",IF(SUMPRODUCT((Evermont!$A$2:$A$1000=$A8)*(Evermont!$Q$2:$Q$1000="Terminé"))>0,"✓",IF(SUMPRODUCT(MAX((Evermont!$A$2:$A$1000=$A8)*Evermont!$F$2:$F$1000))>0,TEXT(SUMPRODUCT(MAX((Evermont!$A$2:$A$1000=$A8)*Evermont!$F$2:$F$1000)),"yyyy-mm-dd"),"")))))) -> ✓ | L8: =IF($A8="","",COUNTIF(E8:K8,"✓")) -> 7 | M8: Active | O8: ✓ | P8: ✓ | Q8: ✓ | R8: ✓ | S8: ✓ | T8: ✓ | U8: ✓ | W8: =IF($A8="","",IF($X8<>"",$X8,IFERROR(INDEX('Formation Initiale'!$B$2:$B$999,MATCH($A8,'Formation Initiale'!$A$2:$A$999,0)),"Général"))) -> Général
A9: TR008 | B9: Corrfield | C9: Doric Ulmel | D9: Lisbonne | E9: =IF($O9="✓","✓",IF(ISNUMBER($O9),TEXT($O9,"yyyy-mm-dd"),IF($A9="","",IF(SUMPRODUCT(('Formation Initiale'!$A$2:$A$999=$A9)*('Formation Initiale'!$R$2:$R$999="Terminé"))>0,"✓",IF(SUMPRODUCT(MAX(('Formation Initiale'!$A$2:$A$999=$A9)*'Formation Initiale'!$G$2:$G$999))>0,TEXT(SUMPRODUCT(MAX(('Formation Initiale'!$A$2:$A$999=$A9)*'Formation Initiale'!$G$2:$G$999)),"yyyy-mm-dd"),""))))) -> ✓ | F9: =IF($P9="✓","✓",IF(ISNUMBER($P9),TEXT($P9,"yyyy-mm-dd"),IF($A9="","",IF($D9="Lisbonne","",IF(SUMPRODUCT(('Formation Initiale'!$A$2:$A$999=$A9)*('Formation Initiale'!$R$2:$R$999="Terminé"))>0,"✓",IF(SUMPRODUCT(MAX(('Formation Initiale'!$A$2:$A$999=$A9)*'Formation Initiale'!$G$2:$G$999))>0,TEXT(SUMPRODUCT(MAX(('Formation Initiale'!$A$2:$A$999=$A9)*'Formation Initiale'!$G$2:$G$999)),"yyyy-mm-dd"),"")))))) | G9: =IF($Q9="✓","✓",IF(ISNUMBER($Q9),TEXT($Q9,"yyyy-mm-dd"),IF($A9="","",IF(SUMPRODUCT(('Agences & Après-vente'!$A$2:$A$1000=$A9)*(('Agences & Après-vente'!$D$2:$D$1000="Agences")+('Agences & Après-vente'!$D$2:$D$1000="Agences et Après-vente"))*('Agences & Après-vente'!$I$2:$I$1000="DONE"))>0,"✓",IF(SUMPRODUCT(MAX(('Agences & Après-vente'!$A$2:$A$1000=$A9)*(('Agences & Après-vente'!$D$2:$D$1000="Agences")+('Agences & Après-vente'!$D$2:$D$1000="Agences et Après-vente"))*'Agences & Après-vente'!$E$2:$E$1000))>0,TEXT(SUMPRODUCT(MAX(('Agences & Après-vente'!$A$2:$A$1000=$A9)*(('Agences & Après-vente'!$D$2:$D$1000="Agences")+('Agences & Après-vente'!$D$2:$D$1000="Agences et Après-vente"))*'Agences & Après-vente'!$E$2:$E$1000)),"yyyy-mm-dd"),""))))) | H9: =IF($R9="✓","✓",IF(ISNUMBER($R9),TEXT($R9,"yyyy-mm-dd"),IF($A9="","",IF($D9="Lisbonne","",IF(SUMPRODUCT(('Agences & Après-vente'!$A$2:$A$1000=$A9)*(('Agences & Après-vente'!$D$2:$D$1000="Agences")+('Agences & Après-vente'!$D$2:$D$1000="Agences et Après-vente"))*('Agences & Après-vente'!$I$2:$I$1000="DONE"))>0,"✓",IF(SUMPRODUCT(MAX(('Agences & Après-vente'!$A$2:$A$1000=$A9)*(('Agences & Après-vente'!$D$2:$D$1000="Agences")+('Agences & Après-vente'!$D$2:$D$1000="Agences et Après-vente"))*'Agences & Après-vente'!$E$2:$E$1000))>0,TEXT(SUMPRODUCT(MAX(('Agences & Après-vente'!$A$2:$A$1000=$A9)*(('Agences & Après-vente'!$D$2:$D$1000="Agences")+('Agences & Après-vente'!$D$2:$D$1000="Agences et Après-vente"))*'Agences & Après-vente'!$E$2:$E$1000)),"yyyy-mm-dd"),"")))))) | I9: =IF($S9="✓","✓",IF(ISNUMBER($S9),TEXT($S9,"yyyy-mm-dd"),IF($A9="","",IF(SUMPRODUCT(('Agences & Après-vente'!$A$2:$A$1000=$A9)*(('Agences & Après-vente'!$D$2:$D$1000="Après-vente")+('Agences & Après-vente'!$D$2:$D$1000="Agences et Après-vente"))*('Agences & Après-vente'!$I$2:$I$1000="DONE"))>0,"✓",IF(SUMPRODUCT(MAX(('Agences & Après-vente'!$A$2:$A$1000=$A9)*(('Agences & Après-vente'!$D$2:$D$1000="Après-vente")+('Agences & Après-vente'!$D$2:$D$1000="Agences et Après-vente"))*'Agences & Après-vente'!$E$2:$E$1000))>0,TEXT(SUMPRODUCT(MAX(('Agences & Après-vente'!$A$2:$A$1000=$A9)*(('Agences & Après-vente'!$D$2:$D$1000="Après-vente")+('Agences & Après-vente'!$D$2:$D$1000="Agences et Après-vente"))*'Agences & Après-vente'!$E$2:$E$1000)),"yyyy-mm-dd"),""))))) | J9: =IF($T9="✓","✓",IF(ISNUMBER($T9),TEXT($T9,"yyyy-mm-dd"),IF($A9="","",IF($D9="Lisbonne","",IF(SUMPRODUCT(('Agences & Après-vente'!$A$2:$A$1000=$A9)*(('Agences & Après-vente'!$D$2:$D$1000="Après-vente")+('Agences & Après-vente'!$D$2:$D$1000="Agences et Après-vente"))*('Agences & Après-vente'!$I$2:$I$1000="DONE"))>0,"✓",IF(SUMPRODUCT(MAX(('Agences & Après-vente'!$A$2:$A$1000=$A9)*(('Agences & Après-vente'!$D$2:$D$1000="Après-vente")+('Agences & Après-vente'!$D$2:$D$1000="Agences et Après-vente"))*'Agences & Après-vente'!$E$2:$E$1000))>0,TEXT(SUMPRODUCT(MAX(('Agences & Après-vente'!$A$2:$A$1000=$A9)*(('Agences & Après-vente'!$D$2:$D$1000="Après-vente")+('Agences & Après-vente'!$D$2:$D$1000="Agences et Après-vente"))*'Agences & Après-vente'!$E$2:$E$1000)),"yyyy-mm-dd"),"")))))) | K9: =IF($U9="✓","✓",IF(ISNUMBER($U9),TEXT($U9,"yyyy-mm-dd"),IF($D9="Lisbonne","",IF($A9="","",IF(SUMPRODUCT((Evermont!$A$2:$A$1000=$A9)*(Evermont!$Q$2:$Q$1000="Terminé"))>0,"✓",IF(SUMPRODUCT(MAX((Evermont!$A$2:$A$1000=$A9)*Evermont!$F$2:$F$1000))>0,TEXT(SUMPRODUCT(MAX((Evermont!$A$2:$A$1000=$A9)*Evermont!$F$2:$F$1000)),"yyyy-mm-dd"),"")))))) | L9: =IF($A9="","",COUNTIF(E9:K9,"✓")) -> 1 | M9: COS | W9: =IF($A9="","",IF($X9<>"",$X9,IFERROR(INDEX('Formation Initiale'!$B$2:$B$999,MATCH($A9,'Formation Initiale'!$A$2:$A$999,0)),"Général"))) -> OS1
A10: TR009 | B10: Ashgate | C10: Fairgate | D10: Montréal | E10: =IF($O10="✓","✓",IF(ISNUMBER($O10),TEXT($O10,"yyyy-mm-dd"),IF($A10="","",IF(SUMPRODUCT(('Formation Initiale'!$A$2:$A$999=$A10)*('Formation Initiale'!$R$2:$R$999="Terminé"))>0,"✓",IF(SUMPRODUCT(MAX(('Formation Initiale'!$A$2:$A$999=$A10)*'Formation Initiale'!$G$2:$G$999))>0,TEXT(SUMPRODUCT(MAX(('Formation Initiale'!$A$2:$A$999=$A10)*'Formation Initiale'!$G$2:$G$999)),"yyyy-mm-dd"),""))))) -> ✓ | F10: =IF($P10="✓","✓",IF(ISNUMBER($P10),TEXT($P10,"yyyy-mm-dd"),IF($A10="","",IF($D10="Lisbonne","",IF(SUMPRODUCT(('Formation Initiale'!$A$2:$A$999=$A10)*('Formation Initiale'!$R$2:$R$999="Terminé"))>0,"✓",IF(SUMPRODUCT(MAX(('Formation Initiale'!$A$2:$A$999=$A10)*'Formation Initiale'!$G$2:$G$999))>0,TEXT(SUMPRODUCT(MAX(('Formation Initiale'!$A$2:$A$999=$A10)*'Formation Initiale'!$G$2:$G$999)),"yyyy-mm-dd"),"")))))) -> ✓ | G10: =IF($Q10="✓","✓",IF(ISNUMBER($Q10),TEXT($Q10,"yyyy-mm-dd"),IF($A10="","",IF(SUMPRODUCT(('Agences & Après-vente'!$A$2:$A$1000=$A10)*(('Agences & Après-vente'!$D$2:$D$1000="Agences")+('Agences & Après-vente'!$D$2:$D$1000="Agences et Après-vente"))*('Agences & Après-vente'!$I$2:$I$1000="DONE"))>0,"✓",IF(SUMPRODUCT(MAX(('Agences & Après-vente'!$A$2:$A$1000=$A10)*(('Agences & Après-vente'!$D$2:$D$1000="Agences")+('Agences & Après-vente'!$D$2:$D$1000="Agences et Après-vente"))*'Agences & Après-vente'!$E$2:$E$1000))>0,TEXT(SUMPRODUCT(MAX(('Agences & Après-vente'!$A$2:$A$1000=$A10)*(('Agences & Après-vente'!$D$2:$D$1000="Agences")+('Agences & Après-vente'!$D$2:$D$1000="Agences et Après-vente"))*'Agences & Après-vente'!$E$2:$E$1000)),"yyyy-mm-dd"),""))))) -> ✓ | H10: =IF($R10="✓","✓",IF(ISNUMBER($R10),TEXT($R10,"yyyy-mm-dd"),IF($A10="","",IF($D10="Lisbonne","",IF(SUMPRODUCT(('Agences & Après-vente'!$A$2:$A$1000=$A10)*(('Agences & Après-vente'!$D$2:$D$1000="Agences")+('Agences & Après-vente'!$D$2:$D$1000="Agences et Après-vente"))*('Agences & Après-vente'!$I$2:$I$1000="DONE"))>0,"✓",IF(SUMPRODUCT(MAX(('Agences & Après-vente'!$A$2:$A$1000=$A10)*(('Agences & Après-vente'!$D$2:$D$1000="Agences")+('Agences & Après-vente'!$D$2:$D$1000="Agences et Après-vente"))*'Agences & Après-vente'!$E$2:$E$1000))>0,TEXT(SUMPRODUCT(MAX(('Agences & Après-vente'!$A$2:$A$1000=$A10)*(('Agences & Après-vente'!$D$2:$D$1000="Agences")+('Agences & Après-vente'!$D$2:$D$1000="Agences et Après-vente"))*'Agences & Après-vente'!$E$2:$E$1000)),"yyyy-mm-dd"),"")))))) -> ✓ | I10: =IF($S10="✓","✓",IF(ISNUMBER($S10),TEXT($S10,"yyyy-mm-dd"),IF($A10="","",IF(SUMPRODUCT(('Agences & Après-vente'!$A$2:$A$1000=$A10)*(('Agences & Après-vente'!$D$2:$D$1000="Après-vente")+('Agences & Après-vente'!$D$2:$D$1000="Agences et Après-vente"))*('Agences & Après-vente'!$I$2:$I$1000="DONE"))>0,"✓",IF(SUMPRODUCT(MAX(('Agences & Après-vente'!$A$2:$A$1000=$A10)*(('Agences & Après-vente'!$D$2:$D$1000="Après-vente")+('Agences & Après-vente'!$D$2:$D$1000="Agences et Après-vente"))*'Agences & Après-vente'!$E$2:$E$1000))>0,TEXT(SUMPRODUCT(MAX(('Agences & Après-vente'!$A$2:$A$1000=$A10)*(('Agences & Après-vente'!$D$2:$D$1000="Après-vente")+('Agences & Après-vente'!$D$2:$D$1000="Agences et Après-vente"))*'Agences & Après-vente'!$E$2:$E$1000)),"yyyy-mm-dd"),""))))) -> ✓ | J10: =IF($T10="✓","✓",IF(ISNUMBER($T10),TEXT($T10,"yyyy-mm-dd"),IF($A10="","",IF($D10="Lisbonne","",IF(SUMPRODUCT(('Agences & Après-vente'!$A$2:$A$1000=$A10)*(('Agences & Après-vente'!$D$2:$D$1000="Après-vente")+('Agences & Après-vente'!$D$2:$D$1000="Agences et Après-vente"))*('Agences & Après-vente'!$I$2:$I$1000="DONE"))>0,"✓",IF(SUMPRODUCT(MAX(('Agences & Après-vente'!$A$2:$A$1000=$A10)*(('Agences & Après-vente'!$D$2:$D$1000="Après-vente")+('Agences & Après-vente'!$D$2:$D$1000="Agences et Après-vente"))*'Agences & Après-vente'!$E$2:$E$1000))>0,TEXT(SUMPRODUCT(MAX(('Agences & Après-vente'!$A$2:$A$1000=$A10)*(('Agences & Après-vente'!$D$2:$D$1000="Après-vente")+('Agences & Après-vente'!$D$2:$D$1000="Agences et Après-vente"))*'Agences & Après-vente'!$E$2:$E$1000)),"yyyy-mm-dd"),"")))))) -> ✓ | K10: =IF($U10="✓","✓",IF(ISNUMBER($U10),TEXT($U10,"yyyy-mm-dd"),IF($D10="Lisbonne","",IF($A10="","",IF(SUMPRODUCT((Evermont!$A$2:$A$1000=$A10)*(Evermont!$Q$2:$Q$1000="Terminé"))>0,"✓",IF(SUMPRODUCT(MAX((Evermont!$A$2:$A$1000=$A10)*Evermont!$F$2:$F$1000))>0,TEXT(SUMPRODUCT(MAX((Evermont!$A$2:$A$1000=$A10)*Evermont!$F$2:$F$1000)),"yyyy-mm-dd"),"")))))) -> ✓ | L10: =IF($A10="","",COUNTIF(E10:K10,"✓")) -> 7 | M10: Active | O10: ✓ | P10: ✓ | Q10: ✓ | R10: ✓ | S10: ✓ | T10: ✓ | U10: ✓ | W10: =IF($A10="","",IF($X10<>"",$X10,IFERROR(INDEX('Formation Initiale'!$B$2:$B$999,MATCH($A10,'Formation Initiale'!$A$2:$A$999,0)),"Général"))) -> Général
A11: TR010 | B11: Corrfield | C11: Haxay Morys | D11: Lisbonne | E11: =IF($O11="✓","✓",IF(ISNUMBER($O11),TEXT($O11,"yyyy-mm-dd"),IF($A11="","",IF(SUMPRODUCT(('Formation Initiale'!$A$2:$A$999=$A11)*('Formation Initiale'!$R$2:$R$999="Terminé"))>0,"✓",IF(SUMPRODUCT(MAX(('Formation Initiale'!$A$2:$A$999=$A11)*'Formation Initiale'!$G$2:$G$999))>0,TEXT(SUMPRODUCT(MAX(('Formation Initiale'!$A$2:$A$999=$A11)*'Formation Initiale'!$G$2:$G$999)),"yyyy-mm-dd"),""))))) -> ✓ | F11: =IF($P11="✓","✓",IF(ISNUMBER($P11),TEXT($P11,"yyyy-mm-dd"),IF($A11="","",IF($D11="Lisbonne","",IF(SUMPRODUCT(('Formation Initiale'!$A$2:$A$999=$A11)*('Formation Initiale'!$R$2:$R$999="Terminé"))>0,"✓",IF(SUMPRODUCT(MAX(('Formation Initiale'!$A$2:$A$999=$A11)*'Formation Initiale'!$G$2:$G$999))>0,TEXT(SUMPRODUCT(MAX(('Formation Initiale'!$A$2:$A$999=$A11)*'Formation Initiale'!$G$2:$G$999)),"yyyy-mm-dd"),"")))))) | G11: =IF($Q11="✓","✓",IF(ISNUMBER($Q11),TEXT($Q11,"yyyy-mm-dd"),IF($A11="","",IF(SUMPRODUCT(('Agences & Après-vente'!$A$2:$A$1000=$A11)*(('Agences & Après-vente'!$D$2:$D$1000="Agences")+('Agences & Après-vente'!$D$2:$D$1000="Agences et Après-vente"))*('Agences & Après-vente'!$I$2:$I$1000="DONE"))>0,"✓",IF(SUMPRODUCT(MAX(('Agences & Après-vente'!$A$2:$A$1000=$A11)*(('Agences & Après-vente'!$D$2:$D$1000="Agences")+('Agences & Après-vente'!$D$2:$D$1000="Agences et Après-vente"))*'Agences & Après-vente'!$E$2:$E$1000))>0,TEXT(SUMPRODUCT(MAX(('Agences & Après-vente'!$A$2:$A$1000=$A11)*(('Agences & Après-vente'!$D$2:$D$1000="Agences")+('Agences & Après-vente'!$D$2:$D$1000="Agences et Après-vente"))*'Agences & Après-vente'!$E$2:$E$1000)),"yyyy-mm-dd"),""))))) | H11: =IF($R11="✓","✓",IF(ISNUMBER($R11),TEXT($R11,"yyyy-mm-dd"),IF($A11="","",IF($D11="Lisbonne","",IF(SUMPRODUCT(('Agences & Après-vente'!$A$2:$A$1000=$A11)*(('Agences & Après-vente'!$D$2:$D$1000="Agences")+('Agences & Après-vente'!$D$2:$D$1000="Agences et Après-vente"))*('Agences & Après-vente'!$I$2:$I$1000="DONE"))>0,"✓",IF(SUMPRODUCT(MAX(('Agences & Après-vente'!$A$2:$A$1000=$A11)*(('Agences & Après-vente'!$D$2:$D$1000="Agences")+('Agences & Après-vente'!$D$2:$D$1000="Agences et Après-vente"))*'Agences & Après-vente'!$E$2:$E$1000))>0,TEXT(SUMPRODUCT(MAX(('Agences & Après-vente'!$A$2:$A$1000=$A11)*(('Agences & Après-vente'!$D$2:$D$1000="Agences")+('Agences & Après-vente'!$D$2:$D$1000="Agences et Après-vente"))*'Agences & Après-vente'!$E$2:$E$1000)),"yyyy-mm-dd"),"")))))) | I11: =IF($S11="✓","✓",IF(ISNUMBER($S11),TEXT($S11,"yyyy-mm-dd"),IF($A11="","",IF(SUMPRODUCT(('Agences & Après-vente'!$A$2:$A$1000=$A11)*(('Agences & Après-vente'!$D$2:$D$1000="Après-vente")+('Agences & Après-vente'!$D$2:$D$1000="Agences et Après-vente"))*('Agences & Après-vente'!$I$2:$I$1000="DONE"))>0,"✓",IF(SUMPRODUCT(MAX(('Agences & Après-vente'!$A$2:$A$1000=$A11)*(('Agences & Après-vente'!$D$2:$D$1000="Après-vente")+('Agences & Après-vente'!$D$2:$D$1000="Agences et Après-vente"))*'Agences & Après-vente'!$E$2:$E$1000))>0,TEXT(SUMPRODUCT(MAX(('Agences & Après-vente'!$A$2:$A$1000=$A11)*(('Agences & Après-vente'!$D$2:$D$1000="Après-vente")+('Agences & Après-vente'!$D$2:$D$1000="Agences et Après-vente"))*'Agences & Après-vente'!$E$2:$E$1000)),"yyyy-mm-dd"),""))))) | J11: =IF($T11="✓","✓",IF(ISNUMBER($T11),TEXT($T11,"yyyy-mm-dd"),IF($A11="","",IF($D11="Lisbonne","",IF(SUMPRODUCT(('Agences & Après-vente'!$A$2:$A$1000=$A11)*(('Agences & Après-vente'!$D$2:$D$1000="Après-vente")+('Agences & Après-vente'!$D$2:$D$1000="Agences et Après-vente"))*('Agences & Après-vente'!$I$2:$I$1000="DONE"))>0,"✓",IF(SUMPRODUCT(MAX(('Agences & Après-vente'!$A$2:$A$1000=$A11)*(('Agences & Après-vente'!$D$2:$D$1000="Après-vente")+('Agences & Après-vente'!$D$2:$D$1000="Agences et Après-vente"))*'Agences & Après-vente'!$E$2:$E$1000))>0,TEXT(SUMPRODUCT(MAX(('Agences & Après-vente'!$A$2:$A$1000=$A11)*(('Agences & Après-vente'!$D$2:$D$1000="Après-vente")+('Agences & Après-vente'!$D$2:$D$1000="Agences et Après-vente"))*'Agences & Après-vente'!$E$2:$E$1000)),"yyyy-mm-dd"),"")))))) | K11: =IF($U11="✓","✓",IF(ISNUMBER($U11),TEXT($U11,"yyyy-mm-dd"),IF($D11="Lisbonne","",IF($A11="","",IF(SUMPRODUCT((Evermont!$A$2:$A$1000=$A11)*(Evermont!$Q$2:$Q$1000="Terminé"))>0,"✓",IF(SUMPRODUCT(MAX((Evermont!$A$2:$A$1000=$A11)*Evermont!$F$2:$F$1000))>0,TEXT(SUMPRODUCT(MAX((Evermont!$A$2:$A$1000=$A11)*Evermont!$F$2:$F$1000)),"yyyy-mm-dd"),"")))))) | L11: =IF($A11="","",COUNTIF(E11:K11,"✓")) -> 1 | M11: COS | W11: =IF($A11="","",IF($X11<>"",$X11,IFERROR(INDEX('Formation Initiale'!$B$2:$B$999,MATCH($A11,'Formation Initiale'!$A$2:$A$999,0)),"Général"))) -> OS3
A12: TR011 | B12: Kelys Torea | C12: Corrmont | D12: Montréal | E12: =IF($O12="✓","✓",IF(ISNUMBER($O12),TEXT($O12,"yyyy-mm-dd"),IF($A12="","",IF(SUMPRODUCT(('Formation Initiale'!$A$2:$A$999=$A12)*('Formation Initiale'!$R$2:$R$999="Terminé"))>0,"✓",IF(SUMPRODUCT(MAX(('Formation Initiale'!$A$2:$A$999=$A12)*'Formation Initiale'!$G$2:$G$999))>0,TEXT(SUMPRODUCT(MAX(('Formation Initiale'!$A$2:$A$999=$A12)*'Formation Initiale'!$G$2:$G$999)),"yyyy-mm-dd"),""))))) -> ✓ | F12: =IF($P12="✓","✓",IF(ISNUMBER($P12),TEXT($P12,"yyyy-mm-dd"),IF($A12="","",IF($D12="Lisbonne","",IF(SUMPRODUCT(('Formation Initiale'!$A$2:$A$999=$A12)*('Formation Initiale'!$R$2:$R$999="Terminé"))>0,"✓",IF(SUMPRODUCT(MAX(('Formation Initiale'!$A$2:$A$999=$A12)*'Formation Initiale'!$G$2:$G$999))>0,TEXT(SUMPRODUCT(MAX(('Formation Initiale'!$A$2:$A$999=$A12)*'Formation Initiale'!$G$2:$G$999)),"yyyy-mm-dd"),"")))))) -> ✓ | G12: =IF($Q12="✓","✓",IF(ISNUMBER($Q12),TEXT($Q12,"yyyy-mm-dd"),IF($A12="","",IF(SUMPRODUCT(('Agences & Après-vente'!$A$2:$A$1000=$A12)*(('Agences & Après-vente'!$D$2:$D$1000="Agences")+('Agences & Après-vente'!$D$2:$D$1000="Agences et Après-vente"))*('Agences & Après-vente'!$I$2:$I$1000="DONE"))>0,"✓",IF(SUMPRODUCT(MAX(('Agences & Après-vente'!$A$2:$A$1000=$A12)*(('Agences & Après-vente'!$D$2:$D$1000="Agences")+('Agences & Après-vente'!$D$2:$D$1000="Agences et Après-vente"))*'Agences & Après-vente'!$E$2:$E$1000))>0,TEXT(SUMPRODUCT(MAX(('Agences & Après-vente'!$A$2:$A$1000=$A12)*(('Agences & Après-vente'!$D$2:$D$1000="Agences")+('Agences & Après-vente'!$D$2:$D$1000="Agences et Après-vente"))*'Agences & Après-vente'!$E$2:$E$1000)),"yyyy-mm-dd"),""))))) -> ✓ | H12: =IF($R12="✓","✓",IF(ISNUMBER($R12),TEXT($R12,"yyyy-mm-dd"),IF($A12="","",IF($D12="Lisbonne","",IF(SUMPRODUCT(('Agences & Après-vente'!$A$2:$A$1000=$A12)*(('Agences & Après-vente'!$D$2:$D$1000="Agences")+('Agences & Après-vente'!$D$2:$D$1000="Agences et Après-vente"))*('Agences & Après-vente'!$I$2:$I$1000="DONE"))>0,"✓",IF(SUMPRODUCT(MAX(('Agences & Après-vente'!$A$2:$A$1000=$A12)*(('Agences & Après-vente'!$D$2:$D$1000="Agences")+('Agences & Après-vente'!$D$2:$D$1000="Agences et Après-vente"))*'Agences & Après-vente'!$E$2:$E$1000))>0,TEXT(SUMPRODUCT(MAX(('Agences & Après-vente'!$A$2:$A$1000=$A12)*(('Agences & Après-vente'!$D$2:$D$1000="Agences")+('Agences & Après-vente'!$D$2:$D$1000="Agences et Après-vente"))*'Agences & Après-vente'!$E$2:$E$1000)),"yyyy-mm-dd"),"")))))) -> ✓ | I12: =IF($S12="✓","✓",IF(ISNUMBER($S12),TEXT($S12,"yyyy-mm-dd"),IF($A12="","",IF(SUMPRODUCT(('Agences & Après-vente'!$A$2:$A$1000=$A12)*(('Agences & Après-vente'!$D$2:$D$1000="Après-vente")+('Agences & Après-vente'!$D$2:$D$1000="Agences et Après-vente"))*('Agences & Après-vente'!$I$2:$I$1000="DONE"))>0,"✓",IF(SUMPRODUCT(MAX(('Agences & Après-vente'!$A$2:$A$1000=$A12)*(('Agences & Après-vente'!$D$2:$D$1000="Après-vente")+('Agences & Après-vente'!$D$2:$D$1000="Agences et Après-vente"))*'Agences & Après-vente'!$E$2:$E$1000))>0,TEXT(SUMPRODUCT(MAX(('Agences & Après-vente'!$A$2:$A$1000=$A12)*(('Agences & Après-vente'!$D$2:$D$1000="Après-vente")+('Agences & Après-vente'!$D$2:$D$1000="Agences et Après-vente"))*'Agences & Après-vente'!$E$2:$E$1000)),"yyyy-mm-dd"),""))))) -> ✓ | J12: =IF($T12="✓","✓",IF(ISNUMBER($T12),TEXT($T12,"yyyy-mm-dd"),IF($A12="","",IF($D12="Lisbonne","",IF(SUMPRODUCT(('Agences & Après-vente'!$A$2:$A$1000=$A12)*(('Agences & Après-vente'!$D$2:$D$1000="Après-vente")+('Agences & Après-vente'!$D$2:$D$1000="Agences et Après-vente"))*('Agences & Après-vente'!$I$2:$I$1000="DONE"))>0,"✓",IF(SUMPRODUCT(MAX(('Agences & Après-vente'!$A$2:$A$1000=$A12)*(('Agences & Après-vente'!$D$2:$D$1000="Après-vente")+('Agences & Après-vente'!$D$2:$D$1000="Agences et Après-vente"))*'Agences & Après-vente'!$E$2:$E$1000))>0,TEXT(SUMPRODUCT(MAX(('Agences & Après-vente'!$A$2:$A$1000=$A12)*(('Agences & Après-vente'!$D$2:$D$1000="Après-vente")+('Agences & Après-vente'!$D$2:$D$1000="Agences et Après-vente"))*'Agences & Après-vente'!$E$2:$E$1000)),"yyyy-mm-dd"),"")))))) -> ✓ | K12: =IF($U12="✓","✓",IF(ISNUMBER($U12),TEXT($U12,"yyyy-mm-dd"),IF($D12="Lisbonne","",IF($A12="","",IF(SUMPRODUCT((Evermont!$A$2:$A$1000=$A12)*(Evermont!$Q$2:$Q$1000="Terminé"))>0,"✓",IF(SUMPRODUCT(MAX((Evermont!$A$2:$A$1000=$A12)*Evermont!$F$2:$F$1000))>0,TEXT(SUMPRODUCT(MAX((Evermont!$A$2:$A$1000=$A12)*Evermont!$F$2:$F$1000)),"yyyy-mm-dd"),"")))))) -> ✓ | L12: =IF($A12="","",COUNTIF(E12:K12,"✓")) -> 7 | M12: Active | O12: ✓ | P12: ✓ | Q12: ✓ | R12: ✓ | S12: ✓ | T12: ✓ | U12: ✓ | W12: =IF($A12="","",IF($X12<>"",$X12,IFERROR(INDEX('Formation Initiale'!$B$2:$B$999,MATCH($A12,'Formation Initiale'!$A$2:$A$999,0)),"Général"))) -> Général
A13: TR012 | B13: Marshaven | C13: Kendgate | D13: Montréal | E13: =IF($O13="✓","✓",IF(ISNUMBER($O13),TEXT($O13,"yyyy-mm-dd"),IF($A13="","",IF(SUMPRODUCT(('Formation Initiale'!$A$2:$A$999=$A13)*('Formation Initiale'!$R$2:$R$999="Terminé"))>0,"✓",IF(SUMPRODUCT(MAX(('Formation Initiale'!$A$2:$A$999=$A13)*'Formation Initiale'!$G$2:$G$999))>0,TEXT(SUMPRODUCT(MAX(('Formation Initiale'!$A$2:$A$999=$A13)*'Formation Initiale'!$G$2:$G$999)),"yyyy-mm-dd"),""))))) -> ✓ | F13: =IF($P13="✓","✓",IF(ISNUMBER($P13),TEXT($P13,"yyyy-mm-dd"),IF($A13="","",IF($D13="Lisbonne","",IF(SUMPRODUCT(('Formation Initiale'!$A$2:$A$999=$A13)*('Formation Initiale'!$R$2:$R$999="Terminé"))>0,"✓",IF(SUMPRODUCT(MAX(('Formation Initiale'!$A$2:$A$999=$A13)*'Formation Initiale'!$G$2:$G$999))>0,TEXT(SUMPRODUCT(MAX(('Formation Initiale'!$A$2:$A$999=$A13)*'Formation Initiale'!$G$2:$G$999)),"yyyy-mm-dd"),"")))))) -> ✓ | G13: =IF($Q13="✓","✓",IF(ISNUMBER($Q13),TEXT($Q13,"yyyy-mm-dd"),IF($A13="","",IF(SUMPRODUCT(('Agences & Après-vente'!$A$2:$A$1000=$A13)*(('Agences & Après-vente'!$D$2:$D$1000="Agences")+('Agences & Après-vente'!$D$2:$D$1000="Agences et Après-vente"))*('Agences & Après-vente'!$I$2:$I$1000="DONE"))>0,"✓",IF(SUMPRODUCT(MAX(('Agences & Après-vente'!$A$2:$A$1000=$A13)*(('Agences & Après-vente'!$D$2:$D$1000="Agences")+('Agences & Après-vente'!$D$2:$D$1000="Agences et Après-vente"))*'Agences & Après-vente'!$E$2:$E$1000))>0,TEXT(SUMPRODUCT(MAX(('Agences & Après-vente'!$A$2:$A$1000=$A13)*(('Agences & Après-vente'!$D$2:$D$1000="Agences")+('Agences & Après-vente'!$D$2:$D$1000="Agences et Après-vente"))*'Agences & Après-vente'!$E$2:$E$1000)),"yyyy-mm-dd"),""))))) -> ✓ | H13: =IF($R13="✓","✓",IF(ISNUMBER($R13),TEXT($R13,"yyyy-mm-dd"),IF($A13="","",IF($D13="Lisbonne","",IF(SUMPRODUCT(('Agences & Après-vente'!$A$2:$A$1000=$A13)*(('Agences & Après-vente'!$D$2:$D$1000="Agences")+('Agences & Après-vente'!$D$2:$D$1000="Agences et Après-vente"))*('Agences & Après-vente'!$I$2:$I$1000="DONE"))>0,"✓",IF(SUMPRODUCT(MAX(('Agences & Après-vente'!$A$2:$A$1000=$A13)*(('Agences & Après-vente'!$D$2:$D$1000="Agences")+('Agences & Après-vente'!$D$2:$D$1000="Agences et Après-vente"))*'Agences & Après-vente'!$E$2:$E$1000))>0,TEXT(SUMPRODUCT(MAX(('Agences & Après-vente'!$A$2:$A$1000=$A13)*(('Agences & Après-vente'!$D$2:$D$1000="Agences")+('Agences & Après-vente'!$D$2:$D$1000="Agences et Après-vente"))*'Agences & Après-vente'!$E$2:$E$1000)),"yyyy-mm-dd"),"")))))) -> ✓ | I13: =IF($S13="✓","✓",IF(ISNUMBER($S13),TEXT($S13,"yyyy-mm-dd"),IF($A13="","",IF(SUMPRODUCT(('Agences & Après-vente'!$A$2:$A$1000=$A13)*(('Agences & Après-vente'!$D$2:$D$1000="Après-vente")+('Agences & Après-vente'!$D$2:$D$1000="Agences et Après-vente"))*('Agences & Après-vente'!$I$2:$I$1000="DONE"))>0,"✓",IF(SUMPRODUCT(MAX(('Agences & Après-vente'!$A$2:$A$1000=$A13)*(('Agences & Après-vente'!$D$2:$D$1000="Après-vente")+('Agences & Après-vente'!$D$2:$D$1000="Agences et Après-vente"))*'Agences & Après-vente'!$E$2:$E$1000))>0,TEXT(SUMPRODUCT(MAX(('Agences & Après-vente'!$A$2:$A$1000=$A13)*(('Agences & Après-vente'!$D$2:$D$1000="Après-vente")+('Agences & Après-vente'!$D$2:$D$1000="Agences et Après-vente"))*'Agences & Après-vente'!$E$2:$E$1000)),"yyyy-mm-dd"),""))))) -> ✓ | J13: =IF($T13="✓","✓",IF(ISNUMBER($T13),TEXT($T13,"yyyy-mm-dd"),IF($A13="","",IF($D13="Lisbonne","",IF(SUMPRODUCT(('Agences & Après-vente'!$A$2:$A$1000=$A13)*(('Agences & Après-vente'!$D$2:$D$1000="Après-vente")+('Agences & Après-vente'!$D$2:$D$1000="Agences et Après-vente"))*('Agences & Après-vente'!$I$2:$I$1000="DONE"))>0,"✓",IF(SUMPRODUCT(MAX(('Agences & Après-vente'!$A$2:$A$1000=$A13)*(('Agences & Après-vente'!$D$2:$D$1000="Après-vente")+('Agences & Après-vente'!$D$2:$D$1000="Agences et Après-vente"))*'Agences & Après-vente'!$E$2:$E$1000))>0,TEXT(SUMPRODUCT(MAX(('Agences & Après-vente'!$A$2:$A$1000=$A13)*(('Agences & Après-vente'!$D$2:$D$1000="Après-vente")+('Agences & Après-vente'!$D$2:$D$1000="Agences et Après-vente"))*'Agences & Après-vente'!$E$2:$E$1000)),"yyyy-mm-dd"),"")))))) -> ✓ | K13: =IF($U13="✓","✓",IF(ISNUMBER($U13),TEXT($U13,"yyyy-mm-dd"),IF($D13="Lisbonne","",IF($A13="","",IF(SUMPRODUCT((Evermont!$A$2:$A$1000=$A13)*(Evermont!$Q$2:$Q$1000="Terminé"))>0,"✓",IF(SUMPRODUCT(MAX((Evermont!$A$2:$A$1000=$A13)*Evermont!$F$2:$F$1000))>0,TEXT(SUMPRODUCT(MAX((Evermont!$A$2:$A$1000=$A13)*Evermont!$F$2:$F$1000)),"yyyy-mm-dd"),"")))))) -> ✓ | L13: =IF($A13="","",COUNTIF(E13:K13,"✓")) -> 7 | M13: Active | O13: ✓ | P13: ✓ | Q13: ✓ | R13: ✓ | S13: ✓ | T13: ✓ | U13: ✓ | W13: =IF($A13="","",IF($X13<>"",$X13,IFERROR(INDEX('Formation Initiale'!$B$2:$B$999,MATCH($A13,'Formation Initiale'!$A$2:$A$999,0)),"Général"))) -> Général
A14: TR013 | B14: Torus | C14: Joror | D14: Montréal | E14: =IF($O14="✓","✓",IF(ISNUMBER($O14),TEXT($O14,"yyyy-mm-dd"),IF($A14="","",IF(SUMPRODUCT(('Formation Initiale'!$A$2:$A$999=$A14)*('Formation Initiale'!$R$2:$R$999="Terminé"))>0,"✓",IF(SUMPRODUCT(MAX(('Formation Initiale'!$A$2:$A$999=$A14)*'Formation Initiale'!$G$2:$G$999))>0,TEXT(SUMPRODUCT(MAX(('Formation Initiale'!$A$2:$A$999=$A14)*'Formation Initiale'!$G$2:$G$999)),"yyyy-mm-dd"),""))))) -> ✓ | F14: =IF($P14="✓","✓",IF(ISNUMBER($P14),TEXT($P14,"yyyy-mm-dd"),IF($A14="","",IF($D14="Lisbonne","",IF(SUMPRODUCT(('Formation Initiale'!$A$2:$A$999=$A14)*('Formation Initiale'!$R$2:$R$999="Terminé"))>0,"✓",IF(SUMPRODUCT(MAX(('Formation Initiale'!$A$2:$A$999=$A14)*'Formation Initiale'!$G$2:$G$999))>0,TEXT(SUMPRODUCT(MAX(('Formation Initiale'!$A$2:$A$999=$A14)*'Formation Initiale'!$G$2:$G$999)),"yyyy-mm-dd"),"")))))) -> ✓ | G14: =IF($Q14="✓","✓",IF(ISNUMBER($Q14),TEXT($Q14,"yyyy-mm-dd"),IF($A14="","",IF(SUMPRODUCT(('Agences & Après-vente'!$A$2:$A$1000=$A14)*(('Agences & Après-vente'!$D$2:$D$1000="Agences")+('Agences & Après-vente'!$D$2:$D$1000="Agences et Après-vente"))*('Agences & Après-vente'!$I$2:$I$1000="DONE"))>0,"✓",IF(SUMPRODUCT(MAX(('Agences & Après-vente'!$A$2:$A$1000=$A14)*(('Agences & Après-vente'!$D$2:$D$1000="Agences")+('Agences & Après-vente'!$D$2:$D$1000="Agences et Après-vente"))*'Agences & Après-vente'!$E$2:$E$1000))>0,TEXT(SUMPRODUCT(MAX(('Agences & Après-vente'!$A$2:$A$1000=$A14)*(('Agences & Après-vente'!$D$2:$D$1000="Agences")+('Agences & Après-vente'!$D$2:$D$1000="Agences et Après-vente"))*'Agences & Après-vente'!$E$2:$E$1000)),"yyyy-mm-dd"),""))))) -> ✓ | H14: =IF($R14="✓","✓",IF(ISNUMBER($R14),TEXT($R14,"yyyy-mm-dd"),IF($A14="","",IF($D14="Lisbonne","",IF(SUMPRODUCT(('Agences & Après-vente'!$A$2:$A$1000=$A14)*(('Agences & Après-vente'!$D$2:$D$1000="Agences")+('Agences & Après-vente'!$D$2:$D$1000="Agences et Après-vente"))*('Agences & Après-vente'!$I$2:$I$1000="DONE"))>0,"✓",IF(SUMPRODUCT(MAX(('Agences & Après-vente'!$A$2:$A$1000=$A14)*(('Agences & Après-vente'!$D$2:$D$1000="Agences")+('Agences & Après-vente'!$D$2:$D$1000="Agences et Après-vente"))*'Agences & Après-vente'!$E$2:$E$1000))>0,TEXT(SUMPRODUCT(MAX(('Agences & Après-vente'!$A$2:$A$1000=$A14)*(('Agences & Après-vente'!$D$2:$D$1000="Agences")+('Agences & Après-vente'!$D$2:$D$1000="Agences et Après-vente"))*'Agences & Après-vente'!$E$2:$E$1000)),"yyyy-mm-dd"),"")))))) -> ✓ | I14: =IF($S14="✓","✓",IF(ISNUMBER($S14),TEXT($S14,"yyyy-mm-dd"),IF($A14="","",IF(SUMPRODUCT(('Agences & Après-vente'!$A$2:$A$1000=$A14)*(('Agences & Après-vente'!$D$2:$D$1000="Après-vente")+('Agences & Après-vente'!$D$2:$D$1000="Agences et Après-vente"))*('Agences & Après-vente'!$I$2:$I$1000="DONE"))>0,"✓",IF(SUMPRODUCT(MAX(('Agences & Après-vente'!$A$2:$A$1000=$A14)*(('Agences & Après-vente'!$D$2:$D$1000="Après-vente")+('Agences & Après-vente'!$D$2:$D$1000="Agences et Après-vente"))*'Agences & Après-vente'!$E$2:$E$1000))>0,TEXT(SUMPRODUCT(MAX(('Agences & Après-vente'!$A$2:$A$1000=$A14)*(('Agences & Après-vente'!$D$2:$D$1000="Après-vente")+('Agences & Après-vente'!$D$2:$D$1000="Agences et Après-vente"))*'Agences & Après-vente'!$E$2:$E$1000)),"yyyy-mm-dd"),""))))) -> ✓ | J14: =IF($T14="✓","✓",IF(ISNUMBER($T14),TEXT($T14,"yyyy-mm-dd"),IF($A14="","",IF($D14="Lisbonne","",IF(SUMPRODUCT(('Agences & Après-vente'!$A$2:$A$1000=$A14)*(('Agences & Après-vente'!$D$2:$D$1000="Après-vente")+('Agences & Après-vente'!$D$2:$D$1000="Agences et Après-vente"))*('Agences & Après-vente'!$I$2:$I$1000="DONE"))>0,"✓",IF(SUMPRODUCT(MAX(('Agences & Après-vente'!$A$2:$A$1000=$A14)*(('Agences & Après-vente'!$D$2:$D$1000="Après-vente")+('Agences & Après-vente'!$D$2:$D$1000="Agences et Après-vente"))*'Agences & Après-vente'!$E$2:$E$1000))>0,TEXT(SUMPRODUCT(MAX(('Agences & Après-vente'!$A$2:$A$1000=$A14)*(('Agences & Après-vente'!$D$2:$D$1000="Après-vente")+('Agences & Après-vente'!$D$2:$D$1000="Agences et Après-vente"))*'Agences & Après-vente'!$E$2:$E$1000)),"yyyy-mm-dd"),"")))))) -> ✓ | K14: =IF($U14="✓","✓",IF(ISNUMBER($U14),TEXT($U14,"yyyy-mm-dd"),IF($D14="Lisbonne","",IF($A14="","",IF(SUMPRODUCT((Evermont!$A$2:$A$1000=$A14)*(Evermont!$Q$2:$Q$1000="Terminé"))>0,"✓",IF(SUMPRODUCT(MAX((Evermont!$A$2:$A$1000=$A14)*Evermont!$F$2:$F$1000))>0,TEXT(SUMPRODUCT(MAX((Evermont!$A$2:$A$1000=$A14)*Evermont!$F$2:$F$1000)),"yyyy-mm-dd"),"")))))) -> ✓ | L14: =IF($A14="","",COUNTIF(E14:K14,"✓")) -> 7 | M14: Active | O14: ✓ | P14: ✓ | Q14: ✓ | R14: ✓ | S14: ✓ | T14: ✓ | U14: ✓ | W14: =IF($A14="","",IF($X14<>"",$X14,IFERROR(INDEX('Formation Initiale'!$B$2:$B$999,MATCH($A14,'Formation Initiale'!$A$2:$A$999,0)),"Général"))) -> Général
A15: TR014 | B15: Selel | C15: Fairwood | D15: Lisbonne | E15: =IF($O15="✓","✓",IF(ISNUMBER($O15),TEXT($O15,"yyyy-mm-dd"),IF($A15="","",IF(SUMPRODUCT(('Formation Initiale'!$A$2:$A$999=$A15)*('Formation Initiale'!$R$2:$R$999="Terminé"))>0,"✓",IF(SUMPRODUCT(MAX(('Formation Initiale'!$A$2:$A$999=$A15)*'Formation Initiale'!$G$2:$G$999))>0,TEXT(SUMPRODUCT(MAX(('Formation Initiale'!$A$2:$A$999=$A15)*'Formation Initiale'!$G$2:$G$999)),"yyyy-mm-dd"),""))))) -> ✓ | F15: =IF($P15="✓","✓",IF(ISNUMBER($P15),TEXT($P15,"yyyy-mm-dd"),IF($A15="","",IF($D15="Lisbonne","",IF(SUMPRODUCT(('Formation Initiale'!$A$2:$A$999=$A15)*('Formation Initiale'!$R$2:$R$999="Terminé"))>0,"✓",IF(SUMPRODUCT(MAX(('Formation Initiale'!$A$2:$A$999=$A15)*'Formation Initiale'!$G$2:$G$999))>0,TEXT(SUMPRODUCT(MAX(('Formation Initiale'!$A$2:$A$999=$A15)*'Formation Initiale'!$G$2:$G$999)),"yyyy-mm-dd"),"")))))) | G15: =IF($Q15="✓","✓",IF(ISNUMBER($Q15),TEXT($Q15,"yyyy-mm-dd"),IF($A15="","",IF(SUMPRODUCT(('Agences & Après-vente'!$A$2:$A$1000=$A15)*(('Agences & Après-vente'!$D$2:$D$1000="Agences")+('Agences & Après-vente'!$D$2:$D$1000="Agences et Après-vente"))*('Agences & Après-vente'!$I$2:$I$1000="DONE"))>0,"✓",IF(SUMPRODUCT(MAX(('Agences & Après-vente'!$A$2:$A$1000=$A15)*(('Agences & Après-vente'!$D$2:$D$1000="Agences")+('Agences & Après-vente'!$D$2:$D$1000="Agences et Après-vente"))*'Agences & Après-vente'!$E$2:$E$1000))>0,TEXT(SUMPRODUCT(MAX(('Agences & Après-vente'!$A$2:$A$1000=$A15)*(('Agences & Après-vente'!$D$2:$D$1000="Agences")+('Agences & Après-vente'!$D$2:$D$1000="Agences et Après-vente"))*'Agences & Après-vente'!$E$2:$E$1000)),"yyyy-mm-dd"),""))))) | H15: =IF($R15="✓","✓",IF(ISNUMBER($R15),TEXT($R15,"yyyy-mm-dd"),IF($A15="","",IF($D15="Lisbonne","",IF(SUMPRODUCT(('Agences & Après-vente'!$A$2:$A$1000=$A15)*(('Agences & Après-vente'!$D$2:$D$1000="Agences")+('Agences & Après-vente'!$D$2:$D$1000="Agences et Après-vente"))*('Agences & Après-vente'!$I$2:$I$1000="DONE"))>0,"✓",IF(SUMPRODUCT(MAX(('Agences & Après-vente'!$A$2:$A$1000=$A15)*(('Agences & Après-vente'!$D$2:$D$1000="Agences")+('Agences & Après-vente'!$D$2:$D$1000="Agences et Après-vente"))*'Agences & Après-vente'!$E$2:$E$1000))>0,TEXT(SUMPRODUCT(MAX(('Agences & Après-vente'!$A$2:$A$1000=$A15)*(('Agences & Après-vente'!$D$2:$D$1000="Agences")+('Agences & Après-vente'!$D$2:$D$1000="Agences et Après-vente"))*'Agences & Après-vente'!$E$2:$E$1000)),"yyyy-mm-dd"),"")))))) | I15: =IF($S15="✓","✓",IF(ISNUMBER($S15),TEXT($S15,"yyyy-mm-dd"),IF($A15="","",IF(SUMPRODUCT(('Agences & Après-vente'!$A$2:$A$1000=$A15)*(('Agences & Après-vente'!$D$2:$D$1000="Après-vente")+('Agences & Après-vente'!$D$2:$D$1000="Agences et Après-vente"))*('Agences & Après-vente'!$I$2:$I$1000="DONE"))>0,"✓",IF(SUMPRODUCT(MAX(('Agences & Après-vente'!$A$2:$A$1000=$A15)*(('Agences & Après-vente'!$D$2:$D$1000="Après-vente")+('Agences & Après-vente'!$D$2:$D$1000="Agences et Après-vente"))*'Agences & Après-vente'!$E$2:$E$1000))>0,TEXT(SUMPRODUCT(MAX(('Agences & Après-vente'!$A$2:$A$1000=$A15)*(('Agences & Après-vente'!$D$2:$D$1000="Après-vente")+('Agences & Après-vente'!$D$2:$D$1000="Agences et Après-vente"))*'Agences & Après-vente'!$E$2:$E$1000)),"yyyy-mm-dd"),""))))) | J15: =IF($T15="✓","✓",IF(ISNUMBER($T15),TEXT($T15,"yyyy-mm-dd"),IF($A15="","",IF($D15="Lisbonne","",IF(SUMPRODUCT(('Agences & Après-vente'!$A$2:$A$1000=$A15)*(('Agences & Après-vente'!$D$2:$D$1000="Après-vente")+('Agences & Après-vente'!$D$2:$D$1000="Agences et Après-vente"))*('Agences & Après-vente'!$I$2:$I$1000="DONE"))>0,"✓",IF(SUMPRODUCT(MAX(('Agences & Après-vente'!$A$2:$A$1000=$A15)*(('Agences & Après-vente'!$D$2:$D$1000="Après-vente")+('Agences & Après-vente'!$D$2:$D$1000="Agences et Après-vente"))*'Agences & Après-vente'!$E$2:$E$1000))>0,TEXT(SUMPRODUCT(MAX(('Agences & Après-vente'!$A$2:$A$1000=$A15)*(('Agences & Après-vente'!$D$2:$D$1000="Après-vente")+('Agences & Après-vente'!$D$2:$D$1000="Agences et Après-vente"))*'Agences & Après-vente'!$E$2:$E$1000)),"yyyy-mm-dd"),"")))))) | K15: =IF($U15="✓","✓",IF(ISNUMBER($U15),TEXT($U15,"yyyy-mm-dd"),IF($D15="Lisbonne","",IF($A15="","",IF(SUMPRODUCT((Evermont!$A$2:$A$1000=$A15)*(Evermont!$Q$2:$Q$1000="Terminé"))>0,"✓",IF(SUMPRODUCT(MAX((Evermont!$A$2:$A$1000=$A15)*Evermont!$F$2:$F$1000))>0,TEXT(SUMPRODUCT(MAX((Evermont!$A$2:$A$1000=$A15)*Evermont!$F$2:$F$1000)),"yyyy-mm-dd"),"")))))) | L15: =IF($A15="","",COUNTIF(E15:K15,"✓")) -> 1 | M15: Active | O15: ✓ | W15: =IF($A15="","",IF($X15<>"",$X15,IFERROR(INDEX('Formation Initiale'!$B$2:$B$999,MATCH($A15,'Formation Initiale'!$A$2:$A$999,0)),"Général"))) -> OS7
A16: TR015 | B16: Zanol | C16: Granshaw | D16: Lisbonne | E16: =IF($O16="✓","✓",IF(ISNUMBER($O16),TEXT($O16,"yyyy-mm-dd"),IF($A16="","",IF(SUMPRODUCT(('Formation Initiale'!$A$2:$A$999=$A16)*('Formation Initiale'!$R$2:$R$999="Terminé"))>0,"✓",IF(SUMPRODUCT(MAX(('Formation Initiale'!$A$2:$A$999=$A16)*'Formation Initiale'!$G$2:$G$999))>0,TEXT(SUMPRODUCT(MAX(('Formation Initiale'!$A$2:$A$999=$A16)*'Formation Initiale'!$G$2:$G$999)),"yyyy-mm-dd"),""))))) -> ✓ | F16: =IF($P16="✓","✓",IF(ISNUMBER($P16),TEXT($P16,"yyyy-mm-dd"),IF($A16="","",IF($D16="Lisbonne","",IF(SUMPRODUCT(('Formation Initiale'!$A$2:$A$999=$A16)*('Formation Initiale'!$R$2:$R$999="Terminé"))>0,"✓",IF(SUMPRODUCT(MAX(('Formation Initiale'!$A$2:$A$999=$A16)*'Formation Initiale'!$G$2:$G$999))>0,TEXT(SUMPRODUCT(MAX(('Formation Initiale'!$A$2:$A$999=$A16)*'Formation Initiale'!$G$2:$G$999)),"yyyy-mm-dd"),"")))))) | G16: {=IF($Q16="✓","✓",IF(ISNUMBER($Q16),TEXT($Q16,"yyyy-mm-dd"),IF($A16="","",IF(SUMPRODUCT(('Agences & Après-vente'!$A$2:$A$199=$A16)*(('Agences & Après-vente'!$D$2:$D$199="Agences")+('Agences & Après-vente'!$D$2:$D$199="Agences et Après-vente"))*('Agences & Après-vente'!$I$2:$I$199="DONE"))>0,"✓",IF(SUMPRODUCT(MAX(('Agences & Après-vente'!$A$2:$A$199=$A16)*(('Agences & Après-vente'!$D$2:$D$199="Agences")+('Agences & Après-vente'!$D$2:$D$199="Agences et Après-vente"))*'Agences & Après-vente'!$E$2:$E$199))>0,TEXT(SUMPRODUCT(MAX(('Agences & Après-vente'!$A$2:$A$199=$A16)*(('Agences & Après-vente'!$D$2:$D$199="Agences")+('Agences & Après-vente'!$D$2:$D$199="Agences et Après-vente"))*'Agences & Après-vente'!$E$2:$E$199)),"yyyy-mm-dd"),"")))))} | H16: =IF($R16="✓","✓",IF(ISNUMBER($R16),TEXT($R16,"yyyy-mm-dd"),IF($A16="","",IF($D16="Lisbonne","",IF(SUMPRODUCT(('Agences & Après-vente'!$A$2:$A$1000=$A16)*(('Agences & Après-vente'!$D$2:$D$1000="Agences")+('Agences & Après-vente'!$D$2:$D$1000="Agences et Après-vente"))*('Agences & Après-vente'!$I$2:$I$1000="DONE"))>0,"✓",IF(SUMPRODUCT(MAX(('Agences & Après-vente'!$A$2:$A$1000=$A16)*(('Agences & Après-vente'!$D$2:$D$1000="Agences")+('Agences & Après-vente'!$D$2:$D$1000="Agences et Après-vente"))*'Agences & Après-vente'!$E$2:$E$1000))>0,TEXT(SUMPRODUCT(MAX(('Agences & Après-vente'!$A$2:$A$1000=$A16)*(('Agences & Après-vente'!$D$2:$D$1000="Agences")+('Agences & Après-vente'!$D$2:$D$1000="Agences et Après-vente"))*'Agences & Après-vente'!$E$2:$E$1000)),"yyyy-mm-dd"),"")))))) | I16: =IF($S16="✓","✓",IF(ISNUMBER($S16),TEXT($S16,"yyyy-mm-dd"),IF($A16="","",IF(SUMPRODUCT(('Agences & Après-vente'!$A$2:$A$1000=$A16)*(('Agences & Après-vente'!$D$2:$D$1000="Après-vente")+('Agences & Après-vente'!$D$2:$D$1000="Agences et Après-vente"))*('Agences & Après-vente'!$I$2:$I$1000="DONE"))>0,"✓",IF(SUMPRODUCT(MAX(('Agences & Après-vente'!$A$2:$A$1000=$A16)*(('Agences & Après-vente'!$D$2:$D$1000="Après-vente")+('Agences & Après-vente'!$D$2:$D$1000="Agences et Après-vente"))*'Agences & Après-vente'!$E$2:$E$1000))>0,TEXT(SUMPRODUCT(MAX(('Agences & Après-vente'!$A$2:$A$1000=$A16)*(('Agences & Après-vente'!$D$2:$D$1000="Après-vente")+('Agences & Après-vente'!$D$2:$D$1000="Agences et Après-vente"))*'Agences & Après-vente'!$E$2:$E$1000)),"yyyy-mm-dd"),""))))) | J16: =IF($T16="✓","✓",IF(ISNUMBER($T16),TEXT($T16,"yyyy-mm-dd"),IF($A16="","",IF($D16="Lisbonne","",IF(SUMPRODUCT(('Agences & Après-vente'!$A$2:$A$1000=$A16)*(('Agences & Après-vente'!$D$2:$D$1000="Après-vente")+('Agences & Après-vente'!$D$2:$D$1000="Agences et Après-vente"))*('Agences & Après-vente'!$I$2:$I$1000="DONE"))>0,"✓",IF(SUMPRODUCT(MAX(('Agences & Après-vente'!$A$2:$A$1000=$A16)*(('Agences & Après-vente'!$D$2:$D$1000="Après-vente")+('Agences & Après-vente'!$D$2:$D$1000="Agences et Après-vente"))*'Agences & Après-vente'!$E$2:$E$1000))>0,TEXT(SUMPRODUCT(MAX(('Agences & Après-vente'!$A$2:$A$1000=$A16)*(('Agences & Après-vente'!$D$2:$D$1000="Après-vente")+('Agences & Après-vente'!$D$2:$D$1000="Agences et Après-vente"))*'Agences & Après-vente'!$E$2:$E$1000)),"yyyy-mm-dd"),"")))))) | K16: =IF($U16="✓","✓",IF(ISNUMBER($U16),TEXT($U16,"yyyy-mm-dd"),IF($D16="Lisbonne","",IF($A16="","",IF(SUMPRODUCT((Evermont!$A$2:$A$1000=$A16)*(Evermont!$Q$2:$Q$1000="Terminé"))>0,"✓",IF(SUMPRODUCT(MAX((Evermont!$A$2:$A$1000=$A16)*Evermont!$F$2:$F$1000))>0,TEXT(SUMPRODUCT(MAX((Evermont!$A$2:$A$1000=$A16)*Evermont!$F$2:$F$1000)),"yyyy-mm-dd"),"")))))) | L16: =IF($A16="","",COUNTIF(E16:K16,"✓")) -> 1 | M16: COS | W16: =IF($A16="","",IF($X16<>"",$X16,IFERROR(INDEX('Formation Initiale'!$B$2:$B$999,MATCH($A16,'Formation Initiale'!$A$2:$A$999,0)),"Général"))) -> OS4
A17: TR016 | B17: Gilum | C17: Larkfield | D17: Montréal | E17: =IF($O17="✓","✓",IF(ISNUMBER($O17),TEXT($O17,"yyyy-mm-dd"),IF($A17="","",IF(SUMPRODUCT(('Formation Initiale'!$A$2:$A$999=$A17)*('Formation Initiale'!$R$2:$R$999="Terminé"))>0,"✓",IF(SUMPRODUCT(MAX(('Formation Initiale'!$A$2:$A$999=$A17)*'Formation Initiale'!$G$2:$G$999))>0,TEXT(SUMPRODUCT(MAX(('Formation Initiale'!$A$2:$A$999=$A17)*'Formation Initiale'!$G$2:$G$999)),"yyyy-mm-dd"),""))))) -> ✓ | F17: =IF($P17="✓","✓",IF(ISNUMBER($P17),TEXT($P17,"yyyy-mm-dd"),IF($A17="","",IF($D17="Lisbonne","",IF(SUMPRODUCT(('Formation Initiale'!$A$2:$A$999=$A17)*('Formation Initiale'!$R$2:$R$999="Terminé"))>0,"✓",IF(SUMPRODUCT(MAX(('Formation Initiale'!$A$2:$A$999=$A17)*'Formation Initiale'!$G$2:$G$999))>0,TEXT(SUMPRODUCT(MAX(('Formation Initiale'!$A$2:$A$999=$A17)*'Formation Initiale'!$G$2:$G$999)),"yyyy-mm-dd"),"")))))) -> ✓ | G17: =IF($Q17="✓","✓",IF(ISNUMBER($Q17),TEXT($Q17,"yyyy-mm-dd"),IF($A17="","",IF(SUMPRODUCT(('Agences & Après-vente'!$A$2:$A$1000=$A17)*(('Agences & Après-vente'!$D$2:$D$1000="Agences")+('Agences & Après-vente'!$D$2:$D$1000="Agences et Après-vente"))*('Agences & Après-vente'!$I$2:$I$1000="DONE"))>0,"✓",IF(SUMPRODUCT(MAX(('Agences & Après-vente'!$A$2:$A$1000=$A17)*(('Agences & Après-vente'!$D$2:$D$1000="Agences")+('Agences & Après-vente'!$D$2:$D$1000="Agences et Après-vente"))*'Agences & Après-vente'!$E$2:$E$1000))>0,TEXT(SUMPRODUCT(MAX(('Agences & Après-vente'!$A$2:$A$1000=$A17)*(('Agences & Après-vente'!$D$2:$D$1000="Agences")+('Agences & Après-vente'!$D$2:$D$1000="Agences et Après-vente"))*'Agences & Après-vente'!$E$2:$E$1000)),"yyyy-mm-dd"),""))))) -> ✓ | H17: =IF($R17="✓","✓",IF(ISNUMBER($R17),TEXT($R17,"yyyy-mm-dd"),IF($A17="","",IF($D17="Lisbonne","",IF(SUMPRODUCT(('Agences & Après-vente'!$A$2:$A$1000=$A17)*(('Agences & Après-vente'!$D$2:$D$1000="Agences")+('Agences & Après-vente'!$D$2:$D$1000="Agences et Après-vente"))*('Agences & Après-vente'!$I$2:$I$1000="DONE"))>0,"✓",IF(SUMPRODUCT(MAX(('Agences & Après-vente'!$A$2:$A$1000=$A17)*(('Agences & Après-vente'!$D$2:$D$1000="Agences")+('Agences & Après-vente'!$D$2:$D$1000="Agences et Après-vente"))*'Agences & Après-vente'!$E$2:$E$1000))>0,TEXT(SUMPRODUCT(MAX(('Agences & Après-vente'!$A$2:$A$1000=$A17)*(('Agences & Après-vente'!$D$2:$D$1000="Agences")+('Agences & Après-vente'!$D$2:$D$1000="Agences et Après-vente"))*'Agences & Après-vente'!$E$2:$E$1000)),"yyyy-mm-dd"),"")))))) -> ✓ | I17: =IF($S17="✓","✓",IF(ISNUMBER($S17),TEXT($S17,"yyyy-mm-dd"),IF($A17="","",IF(SUMPRODUCT(('Agences & Après-vente'!$A$2:$A$1000=$A17)*(('Agences & Après-vente'!$D$2:$D$1000="Après-vente")+('Agences & Après-vente'!$D$2:$D$1000="Agences et Après-vente"))*('Agences & Après-vente'!$I$2:$I$1000="DONE"))>0,"✓",IF(SUMPRODUCT(MAX(('Agences & Après-vente'!$A$2:$A$1000=$A17)*(('Agences & Après-vente'!$D$2:$D$1000="Après-vente")+('Agences & Après-vente'!$D$2:$D$1000="Agences et Après-vente"))*'Agences & Après-vente'!$E$2:$E$1000))>0,TEXT(SUMPRODUCT(MAX(('Agences & Après-vente'!$A$2:$A$1000=$A17)*(('Agences & Après-vente'!$D$2:$D$1000="Après-vente")+('Agences & Après-vente'!$D$2:$D$1000="Agences et Après-vente"))*'Agences & Après-vente'!$E$2:$E$1000)),"yyyy-mm-dd"),""))))) -> ✓ | J17: =IF($T17="✓","✓",IF(ISNUMBER($T17),TEXT($T17,"yyyy-mm-dd"),IF($A17="","",IF($D17="Lisbonne","",IF(SUMPRODUCT(('Agences & Après-vente'!$A$2:$A$1000=$A17)*(('Agences & Après-vente'!$D$2:$D$1000="Après-vente")+('Agences & Après-vente'!$D$2:$D$1000="Agences et Après-vente"))*('Agences & Après-vente'!$I$2:$I$1000="DONE"))>0,"✓",IF(SUMPRODUCT(MAX(('Agences & Après-vente'!$A$2:$A$1000=$A17)*(('Agences & Après-vente'!$D$2:$D$1000="Après-vente")+('Agences & Après-vente'!$D$2:$D$1000="Agences et Après-vente"))*'Agences & Après-vente'!$E$2:$E$1000))>0,TEXT(SUMPRODUCT(MAX(('Agences & Après-vente'!$A$2:$A$1000=$A17)*(('Agences & Après-vente'!$D$2:$D$1000="Après-vente")+('Agences & Après-vente'!$D$2:$D$1000="Agences et Après-vente"))*'Agences & Après-vente'!$E$2:$E$1000)),"yyyy-mm-dd"),"")))))) -> ✓ | K17: =IF($U17="✓","✓",IF(ISNUMBER($U17),TEXT($U17,"yyyy-mm-dd"),IF($D17="Lisbonne","",IF($A17="","",IF(SUMPRODUCT((Evermont!$A$2:$A$1000=$A17)*(Evermont!$Q$2:$Q$1000="Terminé"))>0,"✓",IF(SUMPRODUCT(MAX((Evermont!$A$2:$A$1000=$A17)*Evermont!$F$2:$F$1000))>0,TEXT(SUMPRODUCT(MAX((Evermont!$A$2:$A$1000=$A17)*Evermont!$F$2:$F$1000)),"yyyy-mm-dd"),"")))))) -> ✓ | L17: =IF($A17="","",COUNTIF(E17:K17,"✓")) -> 7 | M17: COS | O17: ✓ | P17: ✓ | S17: ✓ | T17: ✓ | U17: ✓ | W17: =IF($A17="","",IF($X17<>"",$X17,IFERROR(INDEX('Formation Initiale'!$B$2:$B$999,MATCH($A17,'Formation Initiale'!$A$2:$A$999,0)),"Général"))) -> Général
A18: TR017 | B18: Larkmont | C18: Yoran | D18: Lisbonne | E18: =IF($O18="✓","✓",IF(ISNUMBER($O18),TEXT($O18,"yyyy-mm-dd"),IF($A18="","",IF(SUMPRODUCT(('Formation Initiale'!$A$2:$A$999=$A18)*('Formation Initiale'!$R$2:$R$999="Terminé"))>0,"✓",IF(SUMPRODUCT(MAX(('Formation Initiale'!$A$2:$A$999=$A18)*'Formation Initiale'!$G$2:$G$999))>0,TEXT(SUMPRODUCT(MAX(('Formation Initiale'!$A$2:$A$999=$A18)*'Formation Initiale'!$G$2:$G$999)),"yyyy-mm-dd"),""))))) -> ✓ | F18: =IF($P18="✓","✓",IF(ISNUMBER($P18),TEXT($P18,"yyyy-mm-dd"),IF($A18="","",IF($D18="Lisbonne","",IF(SUMPRODUCT(('Formation Initiale'!$A$2:$A$999=$A18)*('Formation Initiale'!$R$2:$R$999="Terminé"))>0,"✓",IF(SUMPRODUCT(MAX(('Formation Initiale'!$A$2:$A$999=$A18)*'Formation Initiale'!$G$2:$G$999))>0,TEXT(SUMPRODUCT(MAX(('Formation Initiale'!$A$2:$A$999=$A18)*'Formation Initiale'!$G$2:$G$999)),"yyyy-mm-dd"),"")))))) | G18: =IF($Q18="✓","✓",IF(ISNUMBER($Q18),TEXT($Q18,"yyyy-mm-dd"),IF($A18="","",IF(SUMPRODUCT(('Agences & Après-vente'!$A$2:$A$1000=$A18)*(('Agences & Après-vente'!$D$2:$D$1000="Agences")+('Agences & Après-vente'!$D$2:$D$1000="Agences et Après-vente"))*('Agences & Après-vente'!$I$2:$I$1000="DONE"))>0,"✓",IF(SUMPRODUCT(MAX(('Agences & Après-vente'!$A$2:$A$1000=$A18)*(('Agences & Après-vente'!$D$2:$D$1000="Agences")+('Agences & Après-vente'!$D$2:$D$1000="Agences et Après-vente"))*'Agences & Après-vente'!$E$2:$E$1000))>0,TEXT(SUMPRODUCT(MAX(('Agences & Après-vente'!$A$2:$A$1000=$A18)*(('Agences & Après-vente'!$D$2:$D$1000="Agences")+('Agences & Après-vente'!$D$2:$D$1000="Agences et Après-vente"))*'Agences & Après-vente'!$E$2:$E$1000)),"yyyy-mm-dd"),""))))) -> ✓ | H18: =IF($R18="✓","✓",IF(ISNUMBER($R18),TEXT($R18,"yyyy-mm-dd"),IF($A18="","",IF($D18="Lisbonne","",IF(SUMPRODUCT(('Agences & Après-vente'!$A$2:$A$1000=$A18)*(('Agences & Après-vente'!$D$2:$D$1000="Agences")+('Agences & Après-vente'!$D$2:$D$1000="Agences et Après-vente"))*('Agences & Après-vente'!$I$2:$I$1000="DONE"))>0,"✓",IF(SUMPRODUCT(MAX(('Agences & Après-vente'!$A$2:$A$1000=$A18)*(('Agences & Après-vente'!$D$2:$D$1000="Agences")+('Agences & Après-vente'!$D$2:$D$1000="Agences et Après-vente"))*'Agences & Après-vente'!$E$2:$E$1000))>0,TEXT(SUMPRODUCT(MAX(('Agences & Après-vente'!$A$2:$A$1000=$A18)*(('Agences & Après-vente'!$D$2:$D$1000="Agences")+('Agences & Après-vente'!$D$2:$D$1000="Agences et Après-vente"))*'Agences & Après-vente'!$E$2:$E$1000)),"yyyy-mm-dd"),"")))))) | I18: =IF($S18="✓","✓",IF(ISNUMBER($S18),TEXT($S18,"yyyy-mm-dd"),IF($A18="","",IF(SUMPRODUCT(('Agences & Après-vente'!$A$2:$A$1000=$A18)*(('Agences & Après-vente'!$D$2:$D$1000="Après-vente")+('Agences & Après-vente'!$D$2:$D$1000="Agences et Après-vente"))*('Agences & Après-vente'!$I$2:$I$1000="DONE"))>0,"✓",IF(SUMPRODUCT(MAX(('Agences & Après-vente'!$A$2:$A$1000=$A18)*(('Agences & Après-vente'!$D$2:$D$1000="Après-vente")+('Agences & Après-vente'!$D$2:$D$1000="Agences et Après-vente"))*'Agences & Après-vente'!$E$2:$E$1000))>0,TEXT(SUMPRODUCT(MAX(('Agences & Après-vente'!$A$2:$A$1000=$A18)*(('Agences & Après-vente'!$D$2:$D$1000="Après-vente")+('Agences & Après-vente'!$D$2:$D$1000="Agences et Après-vente"))*'Agences & Après-vente'!$E$2:$E$1000)),"yyyy-mm-dd"),""))))) -> ✓ | J18: =IF($T18="✓","✓",IF(ISNUMBER($T18),TEXT($T18,"yyyy-mm-dd"),IF($A18="","",IF($D18="Lisbonne","",IF(SUMPRODUCT(('Agences & Après-vente'!$A$2:$A$1000=$A18)*(('Agences & Après-vente'!$D$2:$D$1000="Après-vente")+('Agences & Après-vente'!$D$2:$D$1000="Agences et Après-vente"))*('Agences & Après-vente'!$I$2:$I$1000="DONE"))>0,"✓",IF(SUMPRODUCT(MAX(('Agences & Après-vente'!$A$2:$A$1000=$A18)*(('Agences & Après-vente'!$D$2:$D$1000="Après-vente")+('Agences & Après-vente'!$D$2:$D$1000="Agences et Après-vente"))*'Agences & Après-vente'!$E$2:$E$1000))>0,TEXT(SUMPRODUCT(MAX(('Agences & Après-vente'!$A$2:$A$1000=$A18)*(('Agences & Après-vente'!$D$2:$D$1000="Après-vente")+('Agences & Après-vente'!$D$2:$D$1000="Agences et Après-vente"))*'Agences & Après-vente'!$E$2:$E$1000)),"yyyy-mm-dd"),"")))))) | K18: =IF($U18="✓","✓",IF(ISNUMBER($U18),TEXT($U18,"yyyy-mm-dd"),IF($D18="Lisbonne","",IF($A18="","",IF(SUMPRODUCT((Evermont!$A$2:$A$1000=$A18)*(Evermont!$Q$2:$Q$1000="Terminé"))>0,"✓",IF(SUMPRODUCT(MAX((Evermont!$A$2:$A$1000=$A18)*Evermont!$F$2:$F$1000))>0,TEXT(SUMPRODUCT(MAX((Evermont!$A$2:$A$1000=$A18)*Evermont!$F$2:$F$1000)),"yyyy-mm-dd"),"")))))) | L18: =IF($A18="","",COUNTIF(E18:K18,"✓")) -> 3 | M18: Active | W18: =IF($A18="","",IF($X18<>"",$X18,IFERROR(INDEX('Formation Initiale'!$B$2:$B$999,MATCH($A18,'Formation Initiale'!$A$2:$A$999,0)),"Général"))) -> OS4
A19: TR018 | B19: Granbrook | C19: Yoril Corrfield | D19: Lisbonne | E19: =IF($O19="✓","✓",IF(ISNUMBER($O19),TEXT($O19,"yyyy-mm-dd"),IF($A19="","",IF(SUMPRODUCT(('Formation Initiale'!$A$2:$A$999=$A19)*('Formation Initiale'!$R$2:$R$999="Terminé"))>0,"✓",IF(SUMPRODUCT(MAX(('Formation Initiale'!$A$2:$A$999=$A19)*'Formation Initiale'!$G$2:$G$999))>0,TEXT(SUMPRODUCT(MAX(('Formation Initiale'!$A$2:$A$999=$A19)*'Formation Initiale'!$G$2:$G$999)),"yyyy-mm-dd"),""))))) -> ✓ | F19: =IF($P19="✓","✓",IF(ISNUMBER($P19),TEXT($P19,"yyyy-mm-dd"),IF($A19="","",IF($D19="Lisbonne","",IF(SUMPRODUCT(('Formation Initiale'!$A$2:$A$999=$A19)*('Formation Initiale'!$R$2:$R$999="Terminé"))>0,"✓",IF(SUMPRODUCT(MAX(('Formation Initiale'!$A$2:$A$999=$A19)*'Formation Initiale'!$G$2:$G$999))>0,TEXT(SUMPRODUCT(MAX(('Formation Initiale'!$A$2:$A$999=$A19)*'Formation Initiale'!$G$2:$G$999)),"yyyy-mm-dd"),"")))))) | G19: =IF($Q19="✓","✓",IF(ISNUMBER($Q19),TEXT($Q19,"yyyy-mm-dd"),IF($A19="","",IF(SUMPRODUCT(('Agences & Après-vente'!$A$2:$A$1000=$A19)*(('Agences & Après-vente'!$D$2:$D$1000="Agences")+('Agences & Après-vente'!$D$2:$D$1000="Agences et Après-vente"))*('Agences & Après-vente'!$I$2:$I$1000="DONE"))>0,"✓",IF(SUMPRODUCT(MAX(('Agences & Après-vente'!$A$2:$A$1000=$A19)*(('Agences & Après-vente'!$D$2:$D$1000="Agences")+('Agences & Après-vente'!$D$2:$D$1000="Agences et Après-vente"))*'Agences & Après-vente'!$E$2:$E$1000))>0,TEXT(SUMPRODUCT(MAX(('Agences & Après-vente'!$A$2:$A$1000=$A19)*(('Agences & Après-vente'!$D$2:$D$1000="Agences")+('Agences & Après-vente'!$D$2:$D$1000="Agences et Après-vente"))*'Agences & Après-vente'!$E$2:$E$1000)),"yyyy-mm-dd"),""))))) -> ✓ | H19: =IF($R19="✓","✓",IF(ISNUMBER($R19),TEXT($R19,"yyyy-mm-dd"),IF($A19="","",IF($D19="Lisbonne","",IF(SUMPRODUCT(('Agences & Après-vente'!$A$2:$A$1000=$A19)*(('Agences & Après-vente'!$D$2:$D$1000="Agences")+('Agences & Après-vente'!$D$2:$D$1000="Agences et Après-vente"))*('Agences & Après-vente'!$I$2:$I$1000="DONE"))>0,"✓",IF(SUMPRODUCT(MAX(('Agences & Après-vente'!$A$2:$A$1000=$A19)*(('Agences & Après-vente'!$D$2:$D$1000="Agences")+('Agences & Après-vente'!$D$2:$D$1000="Agences et Après-vente"))*'Agences & Après-vente'!$E$2:$E$1000))>0,TEXT(SUMPRODUCT(MAX(('Agences & Après-vente'!$A$2:$A$1000=$A19)*(('Agences & Après-vente'!$D$2:$D$1000="Agences")+('Agences & Après-vente'!$D$2:$D$1000="Agences et Après-vente"))*'Agences & Après-vente'!$E$2:$E$1000)),"yyyy-mm-dd"),"")))))) | I19: =IF($S19="✓","✓",IF(ISNUMBER($S19),TEXT($S19,"yyyy-mm-dd"),IF($A19="","",IF(SUMPRODUCT(('Agences & Après-vente'!$A$2:$A$1000=$A19)*(('Agences & Après-vente'!$D$2:$D$1000="Après-vente")+('Agences & Après-vente'!$D$2:$D$1000="Agences et Après-vente"))*('Agences & Après-vente'!$I$2:$I$1000="DONE"))>0,"✓",IF(SUMPRODUCT(MAX(('Agences & Après-vente'!$A$2:$A$1000=$A19)*(('Agences & Après-vente'!$D$2:$D$1000="Après-vente")+('Agences & Après-vente'!$D$2:$D$1000="Agences et Après-vente"))*'Agences & Après-vente'!$E$2:$E$1000))>0,TEXT(SUMPRODUCT(MAX(('Agences & Après-vente'!$A$2:$A$1000=$A19)*(('Agences & Après-vente'!$D$2:$D$1000="Après-vente")+('Agences & Après-vente'!$D$2:$D$1000="Agences et Après-vente"))*'Agences & Après-vente'!$E$2:$E$1000)),"yyyy-mm-dd"),""))))) -> ✓ | J19: =IF($T19="✓","✓",IF(ISNUMBER($T19),TEXT($T19,"yyyy-mm-dd"),IF($A19="","",IF($D19="Lisbonne","",IF(SUMPRODUCT(('Agences & Après-vente'!$A$2:$A$1000=$A19)*(('Agences & Après-vente'!$D$2:$D$1000="Après-vente")+('Agences & Après-vente'!$D$2:$D$1000="Agences et Après-vente"))*('Agences & Après-vente'!$I$2:$I$1000="DONE"))>0,"✓",IF(SUMPRODUCT(MAX(('Agences & Après-vente'!$A$2:$A$1000=$A19)*(('Agences & Après-vente'!$D$2:$D$1000="Après-vente")+('Agences & Après-vente'!$D$2:$D$1000="Agences et Après-vente"))*'Agences & Après-vente'!$E$2:$E$1000))>0,TEXT(SUMPRODUCT(MAX(('Agences & Après-vente'!$A$2:$A$1000=$A19)*(('Agences & Après-vente'!$D$2:$D$1000="Après-vente")+('Agences & Après-vente'!$D$2:$D$1000="Agences et Après-vente"))*'Agences & Après-vente'!$E$2:$E$1000)),"yyyy-mm-dd"),"")))))) | K19: =IF($U19="✓","✓",IF(ISNUMBER($U19),TEXT($U19,"yyyy-mm-dd"),IF($D19="Lisbonne","",IF($A19="","",IF(SUMPRODUCT((Evermont!$A$2:$A$1000=$A19)*(Evermont!$Q$2:$Q$1000="Terminé"))>0,"✓",IF(SUMPRODUCT(MAX((Evermont!$A$2:$A$1000=$A19)*Evermont!$F$2:$F$1000))>0,TEXT(SUMPRODUCT(MAX((Evermont!$A$2:$A$1000=$A19)*Evermont!$F$2:$F$1000)),"yyyy-mm-dd"),"")))))) | L19: =IF($A19="","",COUNTIF(E19:K19,"✓")) -> 3 | M19: Active | O19: ✓ | W19: =IF($A19="","",IF($X19<>"",$X19,IFERROR(INDEX('Formation Initiale'!$B$2:$B$999,MATCH($A19,'Formation Initiale'!$A$2:$A$999,0)),"Général"))) -> OS1
A20: TR019 | B20: Kelar | C20: Dellbrook | D20: Montréal | E20: =IF($O20="✓","✓",IF(ISNUMBER($O20),TEXT($O20,"yyyy-mm-dd"),IF($A20="","",IF(SUMPRODUCT(('Formation Initiale'!$A$2:$A$999=$A20)*('Formation Initiale'!$R$2:$R$999="Terminé"))>0,"✓",IF(SUMPRODUCT(MAX(('Formation Initiale'!$A$2:$A$999=$A20)*'Formation Initiale'!$G$2:$G$999))>0,TEXT(SUMPRODUCT(MAX(('Formation Initiale'!$A$2:$A$999=$A20)*'Formation Initiale'!$G$2:$G$999)),"yyyy-mm-dd"),""))))) -> ✓ | F20: =IF($P20="✓","✓",IF(ISNUMBER($P20),TEXT($P20,"yyyy-mm-dd"),IF($A20="","",IF($D20="Lisbonne","",IF(SUMPRODUCT(('Formation Initiale'!$A$2:$A$999=$A20)*('Formation Initiale'!$R$2:$R$999="Terminé"))>0,"✓",IF(SUMPRODUCT(MAX(('Formation Initiale'!$A$2:$A$999=$A20)*'Formation Initiale'!$G$2:$G$999))>0,TEXT(SUMPRODUCT(MAX(('Formation Initiale'!$A$2:$A$999=$A20)*'Formation Initiale'!$G$2:$G$999)),"yyyy-mm-dd"),"")))))) -> ✓ | G20: =IF($Q20="✓","✓",IF(ISNUMBER($Q20),TEXT($Q20,"yyyy-mm-dd"),IF($A20="","",IF(SUMPRODUCT(('Agences & Après-vente'!$A$2:$A$1000=$A20)*(('Agences & Après-vente'!$D$2:$D$1000="Agences")+('Agences & Après-vente'!$D$2:$D$1000="Agences et Après-vente"))*('Agences & Après-vente'!$I$2:$I$1000="DONE"))>0,"✓",IF(SUMPRODUCT(MAX(('Agences & Après-vente'!$A$2:$A$1000=$A20)*(('Agences & Après-vente'!$D$2:$D$1000="Agences")+('Agences & Après-vente'!$D$2:$D$1000="Agences et Après-vente"))*'Agences & Après-vente'!$E$2:$E$1000))>0,TEXT(SUMPRODUCT(MAX(('Agences & Après-vente'!$A$2:$A$1000=$A20)*(('Agences & Après-vente'!$D$2:$D$1000="Agences")+('Agences & Après-vente'!$D$2:$D$1000="Agences et Après-vente"))*'Agences & Après-vente'!$E$2:$E$1000)),"yyyy-mm-dd"),""))))) -> ✓ | H20: =IF($R20="✓","✓",IF(ISNUMBER($R20),TEXT($R20,"yyyy-mm-dd"),IF($A20="","",IF($D20="Lisbonne","",IF(SUMPRODUCT(('Agences & Après-vente'!$A$2:$A$1000=$A20)*(('Agences & Après-vente'!$D$2:$D$1000="Agences")+('Agences & Après-vente'!$D$2:$D$1000="Agences et Après-vente"))*('Agences & Après-vente'!$I$2:$I$1000="DONE"))>0,"✓",IF(SUMPRODUCT(MAX(('Agences & Après-vente'!$A$2:$A$1000=$A20)*(('Agences & Après-vente'!$D$2:$D$1000="Agences")+('Agences & Après-vente'!$D$2:$D$1000="Agences et Après-vente"))*'Agences & Après-vente'!$E$2:$E$1000))>0,TEXT(SUMPRODUCT(MAX(('Agences & Après-vente'!$A$2:$A$1000=$A20)*(('Agences & Après-vente'!$D$2:$D$1000="Agences")+('Agences & Après-vente'!$D$2:$D$1000="Agences et Après-vente"))*'Agences & Après-vente'!$E$2:$E$1000)),"yyyy-mm-dd"),"")))))) -> ✓ | I20: =IF($S20="✓","✓",IF(ISNUMBER($S20),TEXT($S20,"yyyy-mm-dd"),IF($A20="","",IF(SUMPRODUCT(('Agences & Après-vente'!$A$2:$A$1000=$A20)*(('Agences & Après-vente'!$D$2:$D$1000="Après-vente")+('Agences & Après-vente'!$D$2:$D$1000="Agences et Après-vente"))*('Agences & Après-vente'!$I$2:$I$1000="DONE"))>0,"✓",IF(SUMPRODUCT(MAX(('Agences & Après-vente'!$A$2:$A$1000=$A20)*(('Agences & Après-vente'!$D$2:$D$1000="Après-vente")+('Agences & Après-vente'!$D$2:$D$1000="Agences et Après-vente"))*'Agences & Après-vente'!$E$2:$E$1000))>0,TEXT(SUMPRODUCT(MAX(('Agences & Après-vente'!$A$2:$A$1000=$A20)*(('Agences & Après-vente'!$D$2:$D$1000="Après-vente")+('Agences & Après-vente'!$D$2:$D$1000="Agences et Après-vente"))*'Agences & Après-vente'!$E$2:$E$1000)),"yyyy-mm-dd"),""))))) -> ✓ | J20: =IF($T20="✓","✓",IF(ISNUMBER($T20),TEXT($T20,"yyyy-mm-dd"),IF($A20="","",IF($D20="Lisbonne","",IF(SUMPRODUCT(('Agences & Après-vente'!$A$2:$A$1000=$A20)*(('Agences & Après-vente'!$D$2:$D$1000="Après-vente")+('Agences & Après-vente'!$D$2:$D$1000="Agences et Après-vente"))*('Agences & Après-vente'!$I$2:$I$1000="DONE"))>0,"✓",IF(SUMPRODUCT(MAX(('Agences & Après-vente'!$A$2:$A$1000=$A20)*(('Agences & Après-vente'!$D$2:$D$1000="Après-vente")+('Agences & Après-vente'!$D$2:$D$1000="Agences et Après-vente"))*'Agences & Après-vente'!$E$2:$E$1000))>0,TEXT(SUMPRODUCT(MAX(('Agences & Après-vente'!$A$2:$A$1000=$A20)*(('Agences & Après-vente'!$D$2:$D$1000="Après-vente")+('Agences & Après-vente'!$D$2:$D$1000="Agences et Après-vente"))*'Agences & Après-vente'!$E$2:$E$1000)),"yyyy-mm-dd"),"")))))) -> ✓ | K20: =IF($U20="✓","✓",IF(ISNUMBER($U20),TEXT($U20,"yyyy-mm-dd"),IF($D20="Lisbonne","",IF($A20="","",IF(SUMPRODUCT((Evermont!$A$2:$A$1000=$A20)*(Evermont!$Q$2:$Q$1000="Terminé"))>0,"✓",IF(SUMPRODUCT(MAX((Evermont!$A$2:$A$1000=$A20)*Evermont!$F$2:$F$1000))>0,TEXT(SUMPRODUCT(MAX((Evermont!$A$2:$A$1000=$A20)*Evermont!$F$2:$F$1000)),"yyyy-mm-dd"),"")))))) -> ✓ | L20: =IF($A20="","",COUNTIF(E20:K20,"✓")) -> 7 | M20: Active | O20: ✓ | P20: ✓ | Q20: ✓ | R20: ✓ | S20: ✓ | T20: ✓ | U20: ✓ | W20: =IF($A20="","",IF($X20<>"",$X20,IFERROR(INDEX('Formation Initiale'!$B$2:$B$999,MATCH($A20,'Formation Initiale'!$A$2:$A$999,0)),"Général"))) -> Général
A21: TR020 | B21: Selan | C21: Dellgate | D21: Montréal | E21: =IF($O21="✓","✓",IF(ISNUMBER($O21),TEXT($O21,"yyyy-mm-dd"),IF($A21="","",IF(SUMPRODUCT(('Formation Initiale'!$A$2:$A$999=$A21)*('Formation Initiale'!$R$2:$R$999="Terminé"))>0,"✓",IF(SUMPRODUCT(MAX(('Formation Initiale'!$A$2:$A$999=$A21)*'Formation Initiale'!$G$2:$G$999))>0,TEXT(SUMPRODUCT(MAX(('Formation Initiale'!$A$2:$A$999=$A21)*'Formation Initiale'!$G$2:$G$999)),"yyyy-mm-dd"),""))))) -> ✓ | F21: =IF($P21="✓","✓",IF(ISNUMBER($P21),TEXT($P21,"yyyy-mm-dd"),IF($A21="","",IF($D21="Lisbonne","",IF(SUMPRODUCT(('Formation Initiale'!$A$2:$A$999=$A21)*('Formation Initiale'!$R$2:$R$999="Terminé"))>0,"✓",IF(SUMPRODUCT(MAX(('Formation Initiale'!$A$2:$A$999=$A21)*'Formation Initiale'!$G$2:$G$999))>0,TEXT(SUMPRODUCT(MAX(('Formation Initiale'!$A$2:$A$999=$A21)*'Formation Initiale'!$G$2:$G$999)),"yyyy-mm-dd"),"")))))) -> ✓ | G21: =IF($Q21="✓","✓",IF(ISNUMBER($Q21),TEXT($Q21,"yyyy-mm-dd"),IF($A21="","",IF(SUMPRODUCT(('Agences & Après-vente'!$A$2:$A$1000=$A21)*(('Agences & Après-vente'!$D$2:$D$1000="Agences")+('Agences & Après-vente'!$D$2:$D$1000="Agences et Après-vente"))*('Agences & Après-vente'!$I$2:$I$1000="DONE"))>0,"✓",IF(SUMPRODUCT(MAX(('Agences & Après-vente'!$A$2:$A$1000=$A21)*(('Agences & Après-vente'!$D$2:$D$1000="Agences")+('Agences & Après-vente'!$D$2:$D$1000="Agences et Après-vente"))*'Agences & Après-vente'!$E$2:$E$1000))>0,TEXT(SUMPRODUCT(MAX(('Agences & Après-vente'!$A$2:$A$1000=$A21)*(('Agences & Après-vente'!$D$2:$D$1000="Agences")+('Agences & Après-vente'!$D$2:$D$1000="Agences et Après-vente"))*'Agences & Après-vente'!$E$2:$E$1000)),"yyyy-mm-dd"),""))))) -> ✓ | H21: =IF($R21="✓","✓",IF(ISNUMBER($R21),TEXT($R21,"yyyy-mm-dd"),IF($A21="","",IF($D21="Lisbonne","",IF(SUMPRODUCT(('Agences & Après-vente'!$A$2:$A$1000=$A21)*(('Agences & Après-vente'!$D$2:$D$1000="Agences")+('Agences & Après-vente'!$D$2:$D$1000="Agences et Après-vente"))*('Agences & Après-vente'!$I$2:$I$1000="DONE"))>0,"✓",IF(SUMPRODUCT(MAX(('Agences & Après-vente'!$A$2:$A$1000=$A21)*(('Agences & Après-vente'!$D$2:$D$1000="Agences")+('Agences & Après-vente'!$D$2:$D$1000="Agences et Après-vente"))*'Agences & Après-vente'!$E$2:$E$1000))>0,TEXT(SUMPRODUCT(MAX(('Agences & Après-vente'!$A$2:$A$1000=$A21)*(('Agences & Après-vente'!$D$2:$D$1000="Agences")+('Agences & Après-vente'!$D$2:$D$1000="Agences et Après-vente"))*'Agences & Après-vente'!$E$2:$E$1000)),"yyyy-mm-dd"),"")))))) -> ✓ | I21: =IF($S21="✓","✓",IF(ISNUMBER($S21),TEXT($S21,"yyyy-mm-dd"),IF($A21="","",IF(SUMPRODUCT(('Agences & Après-vente'!$A$2:$A$1000=$A21)*(('Agences & Après-vente'!$D$2:$D$1000="Après-vente")+('Agences & Après-vente'!$D$2:$D$1000="Agences et Après-vente"))*('Agences & Après-vente'!$I$2:$I$1000="DONE"))>0,"✓",IF(SUMPRODUCT(MAX(('Agences & Après-vente'!$A$2:$A$1000=$A21)*(('Agences & Après-vente'!$D$2:$D$1000="Après-vente")+('Agences & Après-vente'!$D$2:$D$1000="Agences et Après-vente"))*'Agences & Après-vente'!$E$2:$E$1000))>0,TEXT(SUMPRODUCT(MAX(('Agences & Après-vente'!$A$2:$A$1000=$A21)*(('Agences & Après-vente'!$D$2:$D$1000="Après-vente")+('Agences & Après-vente'!$D$2:$D$1000="Agences et Après-vente"))*'Agences & Après-vente'!$E$2:$E$1000)),"yyyy-mm-dd"),""))))) -> ✓ | J21: =IF($T21="✓","✓",IF(ISNUMBER($T21),TEXT($T21,"yyyy-mm-dd"),IF($A21="","",IF($D21="Lisbonne","",IF(SUMPRODUCT(('Agences & Après-vente'!$A$2:$A$1000=$A21)*(('Agences & Après-vente'!$D$2:$D$1000="Après-vente")+('Agences & Après-vente'!$D$2:$D$1000="Agences et Après-vente"))*('Agences & Après-vente'!$I$2:$I$1000="DONE"))>0,"✓",IF(SUMPRODUCT(MAX(('Agences & Après-vente'!$A$2:$A$1000=$A21)*(('Agences & Après-vente'!$D$2:$D$1000="Après-vente")+('Agences & Après-vente'!$D$2:$D$1000="Agences et Après-vente"))*'Agences & Après-vente'!$E$2:$E$1000))>0,TEXT(SUMPRODUCT(MAX(('Agences & Après-vente'!$A$2:$A$1000=$A21)*(('Agences & Après-vente'!$D$2:$D$1000="Après-vente")+('Agences & Après-vente'!$D$2:$D$1000="Agences et Après-vente"))*'Agences & Après-vente'!$E$2:$E$1000)),"yyyy-mm-dd"),"")))))) -> ✓ | K21: =IF($U21="✓","✓",IF(ISNUMBER($U21),TEXT($U21,"yyyy-mm-dd"),IF($D21="Lisbonne","",IF($A21="","",IF(SUMPRODUCT((Evermont!$A$2:$A$1000=$A21)*(Evermont!$Q$2:$Q$1000="Terminé"))>0,"✓",IF(SUMPRODUCT(MAX((Evermont!$A$2:$A$1000=$A21)*Evermont!$F$2:$F$1000))>0,TEXT(SUMPRODUCT(MAX((Evermont!$A$2:$A$1000=$A21)*Evermont!$F$2:$F$1000)),"yyyy-mm-dd"),"")))))) -> ✓ | L21: =IF($A21="","",COUNTIF(E21:K21,"✓")) -> 7 | M21: Active | O21: ✓ | P21: ✓ | W21: =IF($A21="","",IF($X21<>"",$X21,IFERROR(INDEX('Formation Initiale'!$B$2:$B$999,MATCH($A21,'Formation Initiale'!$A$2:$A$999,0)),"Général"))) -> 174
A22: TR021 | B22: Nevus | C22: Kelir | D22: Lisbonne | E22: =IF($O22="✓","✓",IF(ISNUMBER($O22),TEXT($O22,"yyyy-mm-dd"),IF($A22="","",IF(SUMPRODUCT(('Formation Initiale'!$A$2:$A$999=$A22)*('Formation Initiale'!$R$2:$R$999="Terminé"))>0,"✓",IF(SUMPRODUCT(MAX(('Formation Initiale'!$A$2:$A$999=$A22)*'Formation Initiale'!$G$2:$G$999))>0,TEXT(SUMPRODUCT(MAX(('Formation Initiale'!$A$2:$A$999=$A22)*'Formation Initiale'!$G$2:$G$999)),"yyyy-mm-dd"),""))))) -> ✓ | F22: =IF($P22="✓","✓",IF(ISNUMBER($P22),TEXT($P22,"yyyy-mm-dd"),IF($A22="","",IF($D22="Lisbonne","",IF(SUMPRODUCT(('Formation Initiale'!$A$2:$A$999=$A22)*('Formation Initiale'!$R$2:$R$999="Terminé"))>0,"✓",IF(SUMPRODUCT(MAX(('Formation Initiale'!$A$2:$A$999=$A22)*'Formation Initiale'!$G$2:$G$999))>0,TEXT(SUMPRODUCT(MAX(('Formation Initiale'!$A$2:$A$999=$A22)*'Formation Initiale'!$G$2:$G$999)),"yyyy-mm-dd"),"")))))) | G22: =IF($Q22="✓","✓",IF(ISNUMBER($Q22),TEXT($Q22,"yyyy-mm-dd"),IF($A22="","",IF(SUMPRODUCT(('Agences & Après-vente'!$A$2:$A$1000=$A22)*(('Agences & Après-vente'!$D$2:$D$1000="Agences")+('Agences & Après-vente'!$D$2:$D$1000="Agences et Après-vente"))*('Agences & Après-vente'!$I$2:$I$1000="DONE"))>0,"✓",IF(SUMPRODUCT(MAX(('Agences & Après-vente'!$A$2:$A$1000=$A22)*(('Agences & Après-vente'!$D$2:$D$1000="Agences")+('Agences & Après-vente'!$D$2:$D$1000="Agences et Après-vente"))*'Agences & Après-vente'!$E$2:$E$1000))>0,TEXT(SUMPRODUCT(MAX(('Agences & Après-vente'!$A$2:$A$1000=$A22)*(('Agences & Après-vente'!$D$2:$D$1000="Agences")+('Agences & Après-vente'!$D$2:$D$1000="Agences et Après-vente"))*'Agences & Après-vente'!$E$2:$E$1000)),"yyyy-mm-dd"),""))))) | H22: =IF($R22="✓","✓",IF(ISNUMBER($R22),TEXT($R22,"yyyy-mm-dd"),IF($A22="","",IF($D22="Lisbonne","",IF(SUMPRODUCT(('Agences & Après-vente'!$A$2:$A$1000=$A22)*(('Agences & Après-vente'!$D$2:$D$1000="Agences")+('Agences & Après-vente'!$D$2:$D$1000="Agences et Après-vente"))*('Agences & Après-vente'!$I$2:$I$1000="DONE"))>0,"✓",IF(SUMPRODUCT(MAX(('Agences & Après-vente'!$A$2:$A$1000=$A22)*(('Agences & Après-vente'!$D$2:$D$1000="Agences")+('Agences & Après-vente'!$D$2:$D$1000="Agences et Après-vente"))*'Agences & Après-vente'!$E$2:$E$1000))>0,TEXT(SUMPRODUCT(MAX(('Agences & Après-vente'!$A$2:$A$1000=$A22)*(('Agences & Après-vente'!$D$2:$D$1000="Agences")+('Agences & Après-vente'!$D$2:$D$1000="Agences et Après-vente"))*'Agences & Après-vente'!$E$2:$E$1000)),"yyyy-mm-dd"),"")))))) | I22: =IF($S22="✓","✓",IF(ISNUMBER($S22),TEXT($S22,"yyyy-mm-dd"),IF($A22="","",IF(SUMPRODUCT(('Agences & Après-vente'!$A$2:$A$1000=$A22)*(('Agences & Après-vente'!$D$2:$D$1000="Après-vente")+('Agences & Après-vente'!$D$2:$D$1000="Agences et Après-vente"))*('Agences & Après-vente'!$I$2:$I$1000="DONE"))>0,"✓",IF(SUMPRODUCT(MAX(('Agences & Après-vente'!$A$2:$A$1000=$A22)*(('Agences & Après-vente'!$D$2:$D$1000="Après-vente")+('Agences & Après-vente'!$D$2:$D$1000="Agences et Après-vente"))*'Agences & Après-vente'!$E$2:$E$1000))>0,TEXT(SUMPRODUCT(MAX(('Agences & Après-vente'!$A$2:$A$1000=$A22)*(('Agences & Après-vente'!$D$2:$D$1000="Après-vente")+('Agences & Après-vente'!$D$2:$D$1000="Agences et Après-vente"))*'Agences & Après-vente'!$E$2:$E$1000)),"yyyy-mm-dd"),""))))) | J22: =IF($T22="✓","✓",IF(ISNUMBER($T22),TEXT($T22,"yyyy-mm-dd"),IF($A22="","",IF($D22="Lisbonne","",IF(SUMPRODUCT(('Agences & Après-vente'!$A$2:$A$1000=$A22)*(('Agences & Après-vente'!$D$2:$D$1000="Après-vente")+('Agences & Après-vente'!$D$2:$D$1000="Agences et Après-vente"))*('Agences & Après-vente'!$I$2:$I$1000="DONE"))>0,"✓",IF(SUMPRODUCT(MAX(('Agences & Après-vente'!$A$2:$A$1000=$A22)*(('Agences & Après-vente'!$D$2:$D$1000="Après-vente")+('Agences & Après-vente'!$D$2:$D$1000="Agences et Après-vente"))*'Agences & Après-vente'!$E$2:$E$1000))>0,TEXT(SUMPRODUCT(MAX(('Agences & Après-vente'!$A$2:$A$1000=$A22)*(('Agences & Après-vente'!$D$2:$D$1000="Après-vente")+('Agences & Après-vente'!$D$2:$D$1000="Agences et Après-vente"))*'Agences & Après-vente'!$E$2:$E$1000)),"yyyy-mm-dd"),"")))))) | K22: =IF($U22="✓","✓",IF(ISNUMBER($U22),TEXT($U22,"yyyy-mm-dd"),IF($D22="Lisbonne","",IF($A22="","",IF(SUMPRODUCT((Evermont!$A$2:$A$1000=$A22)*(Evermont!$Q$2:$Q$1000="Terminé"))>0,"✓",IF(SUMPRODUCT(MAX((Evermont!$A$2:$A$1000=$A22)*Evermont!$F$2:$F$1000))>0,TEXT(SUMPRODUCT(MAX((Evermont!$A$2:$A$1000=$A22)*Evermont!$F$2:$F$1000)),"yyyy-mm-dd"),"")))))) | L22: =IF($A22="","",COUNTIF(E22:K22,"✓")) -> 1 | M22: COS | W22: =IF($A22="","",IF($X22<>"",$X22,IFERROR(INDEX('Formation Initiale'!$B$2:$B$999,MATCH($A22,'Formation Initiale'!$A$2:$A$999,0)),"Général"))) -> OS1
